Workbook

Sheet Dashboard
A1: Mofawtar Q2 Executive Dashboard
A2: Sample quarter: Meta Ads → Prospects → MQL → SQL → Deals → Revenue → ROAS.
A4: Spend | B4: =SUM('05_Daily_Funnel'!C5:C95) | D4: Funnel Conversion
A5: CRM Leads | B5: =SUM('05_Daily_Funnel'!E5:E95) | D5: Lead → MQL | E5: =IFERROR(B7/B6,0)
A6: MQL | B6: =SUM('05_Daily_Funnel'!F5:F95) | D6: MQL → SQL | E6: =IFERROR(B8/B7,0)
A7: SQL | B7: =SUM('05_Daily_Funnel'!G5:G95) | D7: SQL → Deal | E7: =IFERROR(B9/B8,0)
A8: Deals Won | B8: =SUM('05_Daily_Funnel'!H5:H95) | D8: Overall Lead → Deal | E8: =IFERROR(B9/B6,0)
A9: Revenue | B9: =SUM('05_Daily_Funnel'!J5:J95) | D9: SLA Met % | E9: =IFERROR(SUMPRODUCT('05_Daily_Funnel'!E5:E95,'05_Daily_Funnel'!Q5:Q95)/B6,0)
A10: ROAS | B10: =IFERROR(B10/B5,0)
A11: CAC | B11: =IFERROR(B5/B9,0)
A14: Campaign Comparison
A15: Campaign | B15: Spend | C15: Leads | D15: Deals | E15: Revenue | F15: ROAS
A16: In2out - MessCampaign#1 - Testing - 15/4 | B16: =SUMIFS('07_Campaign_Summary'!$C:$C,'07_Campaign_Summary'!$A:$A,"CMP-001") | C16: =SUMIFS('07_Campaign_Summary'!$E:$E,'07_Campaign_Summary'!$A:$A,"CMP-001") | D16: =SUMIFS('07_Campaign_Summary'!$H:$H,'07_Campaign_Summary'!$A:$A,"CMP-001") | E16: =SUMIFS('07_Campaign_Summary'!$J:$J,'07_Campaign_Summary'!$A:$A,"CMP-001") | F16: =SUMIFS('07_Campaign_Summary'!$O:$O,'07_Campaign_Summary'!$A:$A,"CMP-001")
A17: In2out - MessCampaign#2 - Testing - 20/4 | B17: =SUMIFS('07_Campaign_Summary'!$C:$C,'07_Campaign_Summary'!$A:$A,"CMP-002") | C17: =SUMIFS('07_Campaign_Summary'!$E:$E,'07_Campaign_Summary'!$A:$A,"CMP-002") | D17: =SUMIFS('07_Campaign_Summary'!$H:$H,'07_Campaign_Summary'!$A:$A,"CMP-002") | E17: =SUMIFS('07_Campaign_Summary'!$J:$J,'07_Campaign_Summary'!$A:$A,"CMP-002") | F17: =SUMIFS('07_Campaign_Summary'!$O:$O,'07_Campaign_Summary'!$A:$A,"CMP-002")
A18: Mofawtar - E-Receipt - Awareness - Q2 | B18: =SUMIFS('07_Campaign_Summary'!$C:$C,'07_Campaign_Summary'!$A:$A,"CMP-003") | C18: =SUMIFS('07_Campaign_Summary'!$E:$E,'07_Campaign_Summary'!$A:$A,"CMP-003") | D18: =SUMIFS('07_Campaign_Summary'!$H:$H,'07_Campaign_Summary'!$A:$A,"CMP-003") | E18: =SUMIFS('07_Campaign_Summary'!$J:$J,'07_Campaign_Summary'!$A:$A,"CMP-003") | F18: =SUMIFS('07_Campaign_Summary'!$O:$O,'07_Campaign_Summary'!$A:$A,"CMP-003")
A19: Mofawtar - Tax Invoice - Lead Gen - Q2 | B19: =SUMIFS('07_Campaign_Summary'!$C:$C,'07_Campaign_Summary'!$A:$A,"CMP-004") | C19: =SUMIFS('07_Campaign_Summary'!$E:$E,'07_Campaign_Summary'!$A:$A,"CMP-004") | D19: =SUMIFS('07_Campaign_Summary'!$H:$H,'07_Campaign_Summary'!$A:$A,"CMP-004") | E19: =SUMIFS('07_Campaign_Summary'!$J:$J,'07_Campaign_Summary'!$A:$A,"CMP-004") | F19: =SUMIFS('07_Campaign_Summary'!$O:$O,'07_Campaign_Summary'!$A:$A,"CMP-004")
A20: Mofawtar - Retargeting - Demo Booking - Q2 | B20: =SUMIFS('07_Campaign_Summary'!$C:$C,'07_Campaign_Summary'!$A:$A,"CMP-005") | C20: =SUMIFS('07_Campaign_Summary'!$E:$E,'07_Campaign_Summary'!$A:$A,"CMP-005") | D20: =SUMIFS('07_Campaign_Summary'!$H:$H,'07_Campaign_Summary'!$A:$A,"CMP-005") | E20: =SUMIFS('07_Campaign_Summary'!$J:$J,'07_Campaign_Summary'!$A:$A,"CMP-005") | F20: =SUMIFS('07_Campaign_Summary'!$O:$O,'07_Campaign_Summary'!$A:$A,"CMP-005")

Sheet 00_ReadMe
A1: Mofawtar Meta Ads + CRM + ROAS Tracker | Q2 Sample Filled
A2: Invented Q2 data to understand the full flow: Meta Ads > Prospect Info > Lead > MQL / SQL / Deal > Cost > Revenue > ROAS.
A4: Purpose | B4: Pre-filled quarter of realistic dummy data so the team can understand the model before live CRM/Meta integration.
A5: Quarter | B5: 2026-04-01 to 2026-06-30
A6: Daily contacts | B6: Average ~30 prospects/day across WhatsApp, Messenger, Instagram DM, Website Form and Phone Call.
A7: Granularity | B7: Day, week, month, quarter + Campaign / Ad Set / Ad.
A8: Live usage | B8: Replace sample data in 02_Meta_Raw_Data and 03_Prospects_CRM with actual exports while keeping same headers.
A9: Matching key | B9: Campaign ID + Ad Set ID + Ad ID + Date.
A10: Note | B10: All numbers are invented sample data.

Sheet 01_Settings_Lists
A1: Settings, Lists & Definitions
A2: Lookup values and funnel definitions.
A4: Lifecycle Stages | B4: Lead Statuses | C4: Channels | D4: Owners | E4: Products | F4: Industries | G4: Lost Reasons | H4: Campaigns
A5: Lead | B5: New | C5: WhatsApp | D5: Ahmed | E5: Electronic Receipts | F5: Retail | G5: No budget | H5: In2out - MessCampaign#1 - Testing - 15/4
A6: MQL | B6: Contacted | C6: Messenger | D6: Mona | E6: Electronic Invoices | F6: Pharmacy | G6: Not decision maker | H6: In2out - MessCampaign#2 - Testing - 20/4
A7: SQL | B7: Qualified | C7: Instagram DM | D7: Kareem | E7: SaaS Subscription | F7: Restaurant | G7: Wrong fit | H7: Mofawtar - E-Receipt - Awareness - Q2
A8: Deal Won | B8: Proposal Sent | C8: Website Form | D8: Salma | E8: POS Integration | F8: Medical | G8: No response | H8: Mofawtar - Tax Invoice - Lead Gen - Q2
A9: Deal Lost | B9: Negotiation | C9: Phone Call | D9: Youssef | F9: Services | G9: Using competitor | H9: Mofawtar - Retargeting - Demo Booking - Q2
A10: Nurture | B10: Deal Won | F10: Distribution | G10: Price objection
B11: Deal Lost | F11: E-commerce
B12: Nurture | F12: Manufacturing

Sheet 02_Meta_Raw_Data
A1: 02 | Meta Ads Raw Data
A2: Daily/ad-level Meta data for full quarter.
A4: Date | B4: Campaign ID | C4: Campaign Name | D4: Ad Set ID | E4: Ad Set Name | F4: Ad ID | G4: Ad Name | H4: Objective | I4: Product | J4: Amount Spent | K4: Impressions | L4: Reach | M4: Link Clicks | N4: CPC | O4: CPM | P4: Messaging Conversations Started | Q4: WhatsApp Conversations | R4: Messenger Conversations | S4: Instagram DM Conversations | T4: Messaging Conversations Replied | U4: Meta Leads | V4: Website Registrations
A5: 46113 | B5: CMP-001 | C5: In2out - MessCampaign#1 - Testing - 15/4 | D5: AS-0101 | E5: In2out - MessCampaign#1 - Testing - 15/4 | Broad SMEs | F5: AD-010101 | G5: Pain Point Static | Broad SMEs | H5: Messages | I5: Electronic Receipts | J5: 263.21 | K5: 6783 | L5: 4234 | M5: 131 | N5: 2.01 | O5: 38.8 | P5: 37 | Q5: 22 | R5: 12 | S5: 3 | T5: 15 | U5: 0 | V5: 0
A6: 46113 | B6: CMP-001 | C6: In2out - MessCampaign#1 - Testing - 15/4 | D6: AS-0101 | E6: In2out - MessCampaign#1 - Testing - 15/4 | Broad SMEs | F6: AD-010102 | G6: Demo Reel | Broad SMEs | H6: Messages | I6: Electronic Receipts | J6: 166.01 | K6: 3064 | L6: 1707 | M6: 57 | N6: 2.91 | O6: 54.17 | P6: 15 | Q6: 8 | R6: 3 | S6: 4 | T6: 8 | U6: 0 | V6: 0
A7: 46113 | B7: CMP-001 | C7: In2out - MessCampaign#1 - Testing - 15/4 | D7: AS-0101 | E7: In2out - MessCampaign#1 - Testing - 15/4 | Broad SMEs | F7: AD-010103 | G7: Offer Carousel | Broad SMEs | H7: Messages | I7: Electronic Receipts | J7: 301.64 | K7: 4998 | L7: 3208 | M7: 88 | N7: 3.43 | O7: 60.34 | P7: 29 | Q7: 14 | R7: 7 | S7: 8 | T7: 12 | U7: 1 | V7: 0
A8: 46113 | B8: CMP-001 | C8: In2out - MessCampaign#1 - Testing - 15/4 | D8: AS-0102 | E8: In2out - MessCampaign#1 - Testing - 15/4 | Interest Tax Owners | F8: AD-010201 | G8: Pain Point Static | Interest Tax Owners | H8: Messages | I8: Electronic Receipts | J8: 301.95 | K8: 4921 | L8: 3419 | M8: 189 | N8: 1.6 | O8: 61.35 | P8: 39 | Q8: 22 | R8: 13 | S8: 4 | T8: 23 | U8: 1 | V8: 0
A9: 46113 | B9: CMP-001 | C9: In2out - MessCampaign#1 - Testing - 15/4 | D9: AS-0102 | E9: In2out - MessCampaign#1 - Testing - 15/4 | Interest Tax Owners | F9: AD-010202 | G9: Demo Reel | Interest Tax Owners | H9: Messages | I9: Electronic Receipts | J9: 278.26 | K9: 7050 | L9: 4311 | M9: 148 | N9: 1.88 | O9: 39.47 | P9: 22 | Q9: 10 | R9: 5 | S9: 7 | T9: 10 | U9: 0 | V9: 0
A10: 46113 | B10: CMP-002 | C10: In2out - MessCampaign#2 - Testing - 20/4 | D10: AS-0201 | E10: In2out - MessCampaign#2 - Testing - 20/4 | Broad SMEs | F10: AD-020101 | G10: Pain Point Static | Broad SMEs | H10: Messages | I10: Electronic Receipts | J10: 201.01 | K10: 4496 | L10: 2796 | M10: 146 | N10: 1.38 | O10: 44.7 | P10: 30 | Q10: 17 | R10: 6 | S10: 7 | T10: 17 | U10: 0 | V10: 0
A11: 46113 | B11: CMP-002 | C11: In2out - MessCampaign#2 - Testing - 20/4 | D11: AS-0201 | E11: In2out - MessCampaign#2 - Testing - 20/4 | Broad SMEs | F11: AD-020102 | G11: Demo Reel | Broad SMEs | H11: Messages | I11: Electronic Receipts | J11: 344.08 | K11: 5883 | L11: 4120 | M11: 159 | N11: 2.16 | O11: 58.48 | P11: 37 | Q11: 23 | R11: 7 | S11: 7 | T11: 13 | U11: 0 | V11: 0
A12: 46113 | B12: CMP-002 | C12: In2out - MessCampaign#2 - Testing - 20/4 | D12: AS-0201 | E12: In2out - MessCampaign#2 - Testing - 20/4 | Broad SMEs | F12: AD-020103 | G12: Offer Carousel | Broad SMEs | H12: Messages | I12: Electronic Receipts | J12: 164.24 | K12: 2409 | L12: 1894 | M12: 45 | N12: 3.65 | O12: 68.17 | P12: 9 | Q12: 4 | R12: 4 | S12: 1 | T12: 4 | U12: 0 | V12: 0
A13: 46113 | B13: CMP-002 | C13: In2out - MessCampaign#2 - Testing - 20/4 | D13: AS-0202 | E13: In2out - MessCampaign#2 - Testing - 20/4 | Interest Tax Owners | F13: AD-020201 | G13: Pain Point Static | Interest Tax Owners | H13: Messages | I13: Electronic Receipts | J13: 245.18 | K13: 5283 | L13: 3739 | M13: 167 | N13: 1.47 | O13: 46.41 | P13: 27 | Q13: 12 | R13: 12 | S13: 3 | T13: 13 | U13: 0 | V13: 0
A14: 46113 | B14: CMP-002 | C14: In2out - MessCampaign#2 - Testing - 20/4 | D14: AS-0202 | E14: In2out - MessCampaign#2 - Testing - 20/4 | Interest Tax Owners | F14: AD-020202 | G14: Demo Reel | Interest Tax Owners | H14: Messages | I14: Electronic Receipts | J14: 140.83 | K14: 2424 | L14: 1851 | M14: 51 | N14: 2.76 | O14: 58.08 | P14: 5 | Q14: 2 | R14: 2 | S14: 1 | T14: 2 | U14: 0 | V14: 0
A15: 46113 | B15: CMP-003 | C15: Mofawtar - E-Receipt - Awareness - Q2 | D15: AS-0301 | E15: Mofawtar - E-Receipt - Awareness - Q2 | Broad SMEs | F15: AD-030101 | G15: Pain Point Static | Broad SMEs | H15: Messages | I15: Electronic Receipts | J15: 118.15 | K15: 1934 | L15: 1419 | M15: 46 | N15: 2.57 | O15: 61.06 | P15: 7 | Q15: 4 | R15: 1 | S15: 2 | T15: 3 | U15: 0 | V15: 0
A16: 46113 | B16: CMP-003 | C16: Mofawtar - E-Receipt - Awareness - Q2 | D16: AS-0301 | E16: Mofawtar - E-Receipt - Awareness - Q2 | Broad SMEs | F16: AD-030102 | G16: Demo Reel | Broad SMEs | H16: Messages | I16: Electronic Receipts | J16: 317.82 | K16: 6845 | L16: 4689 | M16: 109 | N16: 2.92 | O16: 46.43 | P16: 28 | Q16: 18 | R16: 5 | S16: 5 | T16: 15 | U16: 0 | V16: 0
... A2643: 46203 | B2643: CMP-005 | C2643: Mofawtar - Retargeting - Demo Booking - Q2 | D2643: AS-0503 | E2643: Mofawtar - Retargeting - Demo Booking - Q2 | Retargeting Visitors | F2643: AD-050302 | G2643: Demo Reel | Retargeting Visitors | H2643: Conversions | I2643: SaaS Subscription | J2643: 247.03 | K2643: 4845 | L2643: 3555 | M2643: 121 | N2643: 2.04 | O2643: 50.98 | P2643: 30 | Q2643: 19 | R2643: 5 | S2643: 6 | T2643: 17 | U2643: 0 | V2643: 0

Sheet 03_Prospects_CRM
A1: 03 | Prospects CRM
A2: Contact-level CRM data: the source of truth for MQL/SQL/Deal/Revenue.
A4: Lead ID | B4: Created Date | C4: Contact Name | D4: Company | E4: Phone | F4: Email | G4: City | H4: Industry | I4: Product | J4: Lead Source | K4: Channel | L4: Campaign ID | M4: Campaign Name | N4: Ad Set ID | O4: Ad Set Name | P4: Ad ID | Q4: Ad Name | R4: Owner | S4: Lead Status | T4: Lifecycle Stage | U4: Lead Score | V4: Package | W4: Expected Deal Value | X4: Revenue | Y4: MQL Date | Z4: SQL Date | AA4: Deal Won Date | AB4: Lost Date | AC4: First Response Minutes | AD4: SLA Met | AE4: Lost Reason | AF4: Next Follow-up Date | AG4: Notes
A5: L-00001 | B5: 46113 | C5: Customer 0001 | D5: Smart Medical 715 | E5: 01163404755 | F5: lead0001@example.com | G5: Assiut | H5: Medical | I5: Electronic Receipts | J5: Meta Ads | K5: Phone Call | L5: CMP-003 | M5: Mofawtar - E-Receipt - Awareness - Q2 | N5: AS-0302 | O5: Mofawtar - E-Receipt - Awareness - Q2 | Interest Tax Owners | P5: AD-030202 | Q5: Demo Reel | Interest Tax Owners | R5: Mona | S5: Contacted | T5: Lead | U5: 35 | V5: Starter 850 | W5: 850 | X5: 0 | AC5: 464 | AD5: No | AF5: 46114 | AG5: Asked for demo
A6: L-00002 | B6: 46113 | C6: Customer 0002 | D6: Golden Manufacturing 554 | E6: 01277131360 | F6: lead0002@example.com | G6: Giza | H6: Manufacturing | I6: Electronic Receipts | J6: Meta Ads | K6: WhatsApp | L6: CMP-001 | M6: In2out - MessCampaign#1 - Testing - 15/4 | N6: AS-0101 | O6: In2out - MessCampaign#1 - Testing - 15/4 | Broad SMEs | P6: AD-010102 | Q6: Demo Reel | Broad SMEs | R6: Youssef | S6: Nurture | T6: Nurture | U6: 29 | V6: Starter 850 | W6: 850 | X6: 0 | AC6: 382 | AD6: No | AF6: 46117 | AG6: High intent
A7: L-00003 | B7: 46113 | C7: Customer 0003 | D7: Green E-commerce 142 | E7: 01219880297 | F7: lead0003@example.com | G7: Qena | H7: E-commerce | I7: Electronic Receipts | J7: Meta Ads | K7: WhatsApp | L7: CMP-001 | M7: In2out - MessCampaign#1 - Testing - 15/4 | N7: AS-0101 | O7: In2out - MessCampaign#1 - Testing - 15/4 | Broad SMEs | P7: AD-010101 | Q7: Pain Point Static | Broad SMEs | R7: Salma | S7: Contacted | T7: Lead | U7: 58 | V7: Enterprise 12000 | W7: 12000 | X7: 0 | AC7: 17 | AD7: Yes | AF7: 46114 | AG7: Follow-up via WhatsApp
A8: L-00004 | B8: 46113 | C8: Customer 0004 | D8: Blue Medical 212 | E8: 01588583215 | F8: lead0004@example.com | G8: Zagazig | H8: Medical | I8: Electronic Invoices | J8: Meta Ads | K8: WhatsApp | L8: CMP-004 | M8: Mofawtar - Tax Invoice - Lead Gen - Q2 | N8: AS-0402 | O8: Mofawtar - Tax Invoice - Lead Gen - Q2 | Interest Tax Owners | P8: AD-040202 | Q8: Demo Reel | Interest Tax Owners | R8: Mona | S8: Contacted | T8: Lead | U8: 44 | V8: Starter 850 | W8: 850 | X8: 0 | AC8: 334 | AD8: No | AF8: 46118 | AG8: High intent
A9: L-00005 | B9: 46113 | C9: Customer 0005 | D9: Nile Distribution 299 | E9: 01112603456 | F9: lead0005@example.com | G9: Ismailia | H9: Distribution | I9: SaaS Subscription | J9: Meta Ads | K9: Instagram DM | L9: CMP-005 | M9: Mofawtar - Retargeting - Demo Booking - Q2 | N9: AS-0503 | O9: Mofawtar - Retargeting - Demo Booking - Q2 | Retargeting Visitors | P9: AD-050301 | Q9: Pain Point Static | Retargeting Visitors | R9: Kareem | S9: Contacted | T9: Lead | U9: 34 | V9: Starter 850 | W9: 850 | X9: 0 | AC9: 230 | AD9: No | AF9: 46117 | AG9: Price sensitive
A10: L-00006 | B10: 46113 | C10: Customer 0006 | D10: Omega Services 143 | E10: 01290703795 | F10: lead0006@example.com | G10: Giza | H10: Services | I10: Electronic Receipts | J10: Meta Ads | K10: Website Form | L10: CMP-001 | M10: In2out - MessCampaign#1 - Testing - 15/4 | N10: AS-0101 | O10: In2out - MessCampaign#1 - Testing - 15/4 | Broad SMEs | P10: AD-010103 | Q10: Offer Carousel | Broad SMEs | R10: Mona | S10: Contacted | T10: Lead | U10: 53 | V10: Business 5000 | W10: 5000 | X10: 0 | AC10: 84 | AD10: No | AF10: 46118 | AG10: Needs tax setup
A11: L-00007 | B11: 46113 | C11: Customer 0007 | D11: Lotus Manufacturing 185 | E11: 01249871655 | F11: lead0007@example.com | G11: Mansoura | H11: Manufacturing | I11: Electronic Receipts | J11: Meta Ads | K11: Instagram DM | L11: CMP-001 | M11: In2out - MessCampaign#1 - Testing - 15/4 | N11: AS-0102 | O11: In2out - MessCampaign#1 - Testing - 15/4 | Interest Tax Owners | P11: AD-010201 | Q11: Pain Point Static | Interest Tax Owners | R11: Salma | S11: Contacted | T11: Lead | U11: 35 | V11: Growth 2400 | W11: 2400 | X11: 0 | AC11: 239 | AD11: No | AF11: 46115 | AG11: Imported from Meta conversation
A12: L-00008 | B12: 46113 | C12: Customer 0008 | D12: Smart Manufacturing 925 | E12: 01031030803 | F12: lead0008@example.com | G12: Qena | H12: Manufacturing | I12: Electronic Receipts | J12: Referral | K12: Website Form | L12: CMP-002 | M12: In2out - MessCampaign#2 - Testing - 20/4 | N12: AS-0201 | O12: In2out - MessCampaign#2 - Testing - 20/4 | Broad SMEs | P12: AD-020103 | Q12: Offer Carousel | Broad SMEs | R12: Mona | S12: Qualified | T12: MQL | U12: 70 | V12: Starter 850 | W12: 850 | X12: 0 | Y12: 46115 | AC12: 388 | AD12: No | AF12: 46115 | AG12: Price sensitive
A13: L-00009 | B13: 46113 | C13: Customer 0009 | D13: Omega E-commerce 725 | E13: 01274817663 | F13: lead0009@example.com | G13: Mansoura | H13: E-commerce | I13: Electronic Receipts | J13: Meta Ads | K13: WhatsApp | L13: CMP-002 | M13: In2out - MessCampaign#2 - Testing - 20/4 | N13: AS-0201 | O13: In2out - MessCampaign#2 - Testing - 20/4 | Broad SMEs | P13: AD-020103 | Q13: Offer Carousel | Broad SMEs | R13: Ahmed | S13: Contacted | T13: Lead | U13: 21 | V13: Growth 2400 | W13: 2400 | X13: 0 | AC13: 36 | AD13: Yes | AF13: 46115 | AG13: Price sensitive
A14: L-00010 | B14: 46113 | C14: Customer 0010 | D14: Delta Restaurant 619 | E14: 01046028074 | F14: lead0010@example.com | G14: Cairo | H14: Restaurant | I14: Electronic Receipts | J14: Website | K14: Website Form | L14: CMP-002 | M14: In2out - MessCampaign#2 - Testing - 20/4 | N14: AS-0202 | O14: In2out - MessCampaign#2 - Testing - 20/4 | Interest Tax Owners | P14: AD-020202 | Q14: Demo Reel | Interest Tax Owners | R14: Mona | S14: Contacted | T14: Lead | U14: 59 | V14: Starter 850 | W14: 850 | X14: 0 | AC14: 121 | AD14: No | AF14: 46115 | AG14: Asked for demo
A15: L-00011 | B15: 46113 | C15: Customer 0011 | D15: Alfa Manufacturing 441 | E15: 01011546923 | F15: lead0011@example.com | G15: Giza | H15: Manufacturing | I15: SaaS Subscription | J15: Meta Ads | K15: WhatsApp | L15: CMP-005 | M15: Mofawtar - Retargeting - Demo Booking - Q2 | N15: AS-0503 | O15: Mofawtar - Retargeting - Demo Booking - Q2 | Retargeting Visitors | P15: AD-050301 | Q15: Pain Point Static | Retargeting Visitors | R15: Mona | S15: Contacted | T15: Lead | U15: 43 | V15: Starter 850 | W15: 850 | X15: 0 | AC15: 446 | AD15: No | AF15: 46115 | AG15: Follow-up via WhatsApp
A16: L-00012 | B16: 46113 | C16: Customer 0012 | D16: Target Services 672 | E16: 01292739430 | F16: lead0012@example.com | G16: Suez | H16: Services | I16: SaaS Subscription | J16: Meta Ads | K16: Messenger | L16: CMP-005 | M16: Mofawtar - Retargeting - Demo Booking - Q2 | N16: AS-0503 | O16: Mofawtar - Retargeting - Demo Booking - Q2 | Retargeting Visitors | P16: AD-050302 | Q16: Demo Reel | Retargeting Visitors | R16: Salma | S16: Nurture | T16: Nurture | U16: 47 | V16: Growth 2400 | W16: 2400 | X16: 0 | AC16: 409 | AD16: No | AF16: 46119 | AG16: Asked for demo
A17: L-00013 | B17: 46113 | C17: Customer 0013 | D17: Fast Medical 808 | E17: 01164047337 | F17: lead0013@example.com | G17: Zagazig | H17: Medical | I17: SaaS Subscription | J17: Meta Ads | K17: Phone Call | L17: CMP-005 | M17: Mofawtar - Retargeting - Demo Booking - Q2 | N17: AS-0502 | O17: Mofawtar - Retargeting - Demo Booking - Q2 | Interest Tax Owners | P17: AD-050202 | Q17: Demo Reel | Interest Tax Owners | R17: Youssef | S17: Contacted | T17: Lead | U17: 37 | V17: Business 5000 | W17: 5000 | X17: 0 | AC17: 241 | AD17: No | AF17: 46119 | AG17: Needs tax setup
A18: L-00014 | B18: 46113 | C18: Customer 0014 | D18: Royal Retail 510 | E18: 01153605467 | F18: lead0014@example.com | G18: Zagazig | H18: Retail | I18: Electronic Invoices | J18: Meta Ads | K18: Messenger | L18: CMP-004 | M18: Mofawtar - Tax Invoice - Lead Gen - Q2 | N18: AS-0401 | O18: Mofawtar - Tax Invoice - Lead Gen - Q2 | Broad SMEs | P18: AD-040101 | Q18: Pain Point Static | Broad SMEs | R18: Salma | S18: Qualified | T18: MQL | U18: 62 | V18: Business 5000 | W18: 5000 | X18: 0 | Y18: 46116 | AC18: 77 | AD18: No | AF18: 46114 | AG18: Imported from Meta conversation
A19: L-00015 | B19: 46113 | C19: Customer 0015 | D19: Smart Restaurant 646 | E19: 01151040696 | F19: lead0015@example.com | G19: Mansoura | H19: Restaurant | I19: Electronic Receipts | J19: Meta Ads | K19: Messenger | L19: CMP-003 | M19: Mofawtar - E-Receipt - Awareness - Q2 | N19: AS-0301 | O19: Mofawtar - E-Receipt - Awareness - Q2 | Broad SMEs | P19: AD-030101 | Q19: Pain Point Static | Broad SMEs | R19: Ahmed | S19: Contacted | T19: Lead | U19: 58 | V19: Business 5000 | W19: 5000 | X19: 0 | AC19: 295 | AD19: No | AF19: 46117 | AG19: Follow-up via WhatsApp
A20: L-00016 | B20: 46113 | C20: Customer 0016 | D20: Smart Restaurant 857 | E20: 01039704405 | F20: lead0016@example.com | G20: Mansoura | H20: Restaurant | I20: Electronic Receipts | J20: Meta Ads | K20: WhatsApp | L20: CMP-002 | M20: In2out - MessCampaign#2 - Testing - 20/4 | N20: AS-0201 | O20: In2out - MessCampaign#2 - Testing - 20/4 | Broad SMEs | P20: AD-020103 | Q20: Offer Carousel | Broad SMEs | R20: Kareem | S20: Contacted | T20: Lead | U20: 43 | V20: Growth 2400 | W20: 2400 | X20: 0 | AC20: 104 | AD20: No | AF20: 46117 | AG20: Needs tax setup
A21: L-00017 | B21: 46113 | C21: Customer 0017 | D21: Target Medical 497 | E21: 01212904310 | F21: lead0017@example.com | G21: Qena | H21: Medical | I21: Electronic Receipts | J21: Meta Ads | K21: Website Form | L21: CMP-002 | M21: In2out - MessCampaign#2 - Testing - 20/4 | N21: AS-0201 | O21: In2out - MessCampaign#2 - Testing - 20/4 | Broad SMEs | P21: AD-020101 | Q21: Pain Point Static | Broad SMEs | R21: Ahmed | S21: Contacted | T21: Lead | U21: 40 | V21: Starter 850 | W21: 850 | X21: 0 | AC21: 153 | AD21: No | AF21: 46115 | AG21: Imported from Meta conversation
A22: L-00018 | B22: 46113 | C22: Customer 0018 | D22: Lotus Retail 735 | E22: 01059075036 | F22: lead0018@example.com | G22: Zagazig | H22: Retail | I22: Electronic Receipts | J22: Meta Ads | K22: WhatsApp | L22: CMP-001 | M22: In2out - MessCampaign#1 - Testing - 15/4 | N22: AS-0101 | O22: In2out - MessCampaign#1 - Testing - 15/4 | Broad SMEs | P22: AD-010102 | Q22: Demo Reel | Broad SMEs | R22: Kareem | S22: Deal Lost | T22: Deal Lost | U22: 34 | V22: Starter 850 | W22: 850 | X22: 0 | AB22: 46115 | AC22: 52 | AD22: Yes | AE22: No response | AG22: High intent
A23: L-00019 | B23: 46113 | C23: Customer 0019 | D23: Cairo Distribution 338 | E23: 01178543887 | F23: lead0019@example.com | G23: Cairo | H23: Distribution | I23: SaaS Subscription | J23: Referral | K23: Instagram DM | L23: CMP-005 | M23: Mofawtar - Retargeting - Demo Booking - Q2 | N23: AS-0501 | O23: Mofawtar - Retargeting - Demo Booking - Q2 | Broad SMEs | P23: AD-050101 | Q23: Pain Point Static | Broad SMEs | R23: Salma | S23: Deal Lost | T23: Deal Lost | U23: 46 | V23: Growth 2400 | W23: 2400 | X23: 0 | AB23: 46117 | AC23: 193 | AD23: No | AE23: Using competitor | AG23: High intent
A24: L-00020 | B24: 46113 | C24: Customer 0020 | D24: Nile Services 925 | E24: 01568014632 | F24: lead0020@example.com | G24: Mansoura | H24: Services | I24: Electronic Invoices | J24: Meta Ads | K24: Messenger | L24: CMP-004 | M24: Mofawtar - Tax Invoice - Lead Gen - Q2 | N24: AS-0402 | O24: Mofawtar - Tax Invoice - Lead Gen - Q2 | Interest Tax Owners | P24: AD-040201 | Q24: Pain Point Static | Interest Tax Owners | R24: Ahmed | S24: Qualified | T24: MQL | U24: 57 | V24: Starter 850 | W24: 850 | X24: 0 | Y24: 46116 | AC24: 186 | AD24: No | AF24: 46118 | AG24: Imported from Meta conversation
A25: L-00021 | B25: 46113 | C25: Customer 0021 | D25: Golden E-commerce 383 | E25: 01541869535 | F25: lead0021@example.com | G25: Zagazig | H25: E-commerce | I25: Electronic Receipts | J25: Meta Ads | K25: Website Form | L25: CMP-002 | M25: In2out - MessCampaign#2 - Testing - 20/4 | N25: AS-0201 | O25: In2out - MessCampaign#2 - Testing - 20/4 | Broad SMEs | P25: AD-020101 | Q25: Pain Point Static | Broad SMEs | R25: Ahmed | S25: Contacted | T25: Lead | U25: 54 | V25: Starter 850 | W25: 850 | X25: 0 | AC25: 277 | AD25: No | AF25: 46114 | AG25: Asked for demo
A26: L-00022 | B26: 46113 | C26: Customer 0022 | D26: Omega Retail 619 | E26: 01571817885 | F26: lead0022@example.com | G26: Giza | H26: Retail | I26: Electronic Receipts | J26: Meta Ads | K26: WhatsApp | L26: CMP-002 | M26: In2out - MessCampaign#2 - Testing - 20/4 | N26: AS-0201 | O26: In2out - MessCampaign#2 - Testing - 20/4 | Broad SMEs | P26: AD-020103 | Q26: Offer Carousel | Broad SMEs | R26: Kareem | S26: Contacted | T26: Lead | U26: 70 | V26: Starter 850 | W26: 850 | X26: 0 | AC26: 336 | AD26: No | AF26: 46119 | AG26: Needs tax setup
A27: L-00023 | B27: 46113 | C27: Customer 0023 | D27: Blue Retail 61 | E27: 01190516640 | F27: lead0023@example.com | G27: Alexandria | H27: Retail | I27: Electronic Receipts | J27: Meta Ads | K27: Phone Call | L27: CMP-001 | M27: In2out - MessCampaign#1 - Testing - 15/4 | N27: AS-0101 | O27: In2out - MessCampaign#1 - Testing - 15/4 | Broad SMEs | P27: AD-010101 | Q27: Pain Point Static | Broad SMEs | R27: Youssef | S27: Deal Lost | T27: Deal Lost | U27: 33 | V27: Starter 850 | W27: 850 | X27: 0 | AB27: 46118 | AC27: 378 | AD27: No | AE27: Using competitor | AG27: Follow-up via WhatsApp
A28: L-00024 | B28: 46113 | C28: Customer 0024 | D28: Fast E-commerce 558 | E28: 01221891017 | F28: lead0024@example.com | G28: Assiut | H28: E-commerce | I28: Electronic Receipts | J28: Meta Ads | K28: Phone Call | L28: CMP-002 | M28: In2out - MessCampaign#2 - Testing - 20/4 | N28: AS-0201 | O28: In2out - MessCampaign#2 - Testing - 20/4 | Broad SMEs | P28: AD-020102 | Q28: Demo Reel | Broad SMEs | R28: Ahmed | S28: Contacted | T28: Lead | U28: 53 | V28: Starter 850 | W28: 850 | X28: 0 | AC28: 1449 | AD28: No | AF28: 46116 | AG28: Asked for demo
A29: L-00025 | B29: 46113 | C29: Customer 0025 | D29: Delta E-commerce 500 | E29: 01175535180 | F29: lead0025@example.com | G29: Alexandria | H29: E-commerce | I29: SaaS Subscription | J29: Meta Ads | K29: Instagram DM | L29: CMP-005 | M29: Mofawtar - Retargeting - Demo Booking - Q2 | N29: AS-0503 | O29: Mofawtar - Retargeting - Demo Booking - Q2 | Retargeting Visitors | P29: AD-050302 | Q29: Demo Reel | Retargeting Visitors | R29: Kareem | S29: Qualified | T29: MQL | U29: 63 | V29: Growth 2400 | W29: 2400 | X29: 0 | Y29: 46113 | AC29: 93 | AD29: No | AF29: 46119 | AG29: Imported from Meta conversation
A30: L-00026 | B30: 46113 | C30: Customer 0026 | D30: Fast Medical 809 | E30: 01081600765 | F30: lead0026@example.com | G30: Mansoura | H30: Medical | I30: Electronic Receipts | J30: Meta Ads | K30: WhatsApp | L30: CMP-001 | M30: In2out - MessCampaign#1 - Testing - 15/4 | N30: AS-0102 | O30: In2out - MessCampaign#1 - Testing - 15/4 | Interest Tax Owners | P30: AD-010201 | Q30: Pain Point Static | Interest Tax Owners | R30: Kareem | S30: Contacted | T30: Lead | U30: 46 | V30: Starter 850 | W30: 850 | X30: 0 | AC30: 373 | AD30: No | AF30: 46117 | AG30: Follow-up via WhatsApp
A31: L-00027 | B31: 46113 | C31: Customer 0027 | D31: Lotus Distribution 923 | E31: 01044925104 | F31: lead0027@example.com | G31: Suez | H31: Distribution | I31: Electronic Receipts | J31: Meta Ads | K31: Messenger | L31: CMP-003 | M31: Mofawtar - E-Receipt - Awareness - Q2 | N31: AS-0302 | O31: Mofawtar - E-Receipt - Awareness - Q2 | Interest Tax Owners | P31: AD-030201 | Q31: Pain Point Static | Interest Tax Owners | R31: Ahmed | S31: Contacted | T31: Lead | U31: 36 | V31: Starter 850 | W31: 850 | X31: 0 | AC31: 213 | AD31: No | AF31: 46118 | AG31: High intent
A32: L-00028 | B32: 46113 | C32: Customer 0028 | D32: Nile Manufacturing 445 | E32: 01257556484 | F32: lead0028@example.com | G32: Suez | H32: Manufacturing | I32: Electronic Receipts | J32: Meta Ads | K32: Instagram DM | L32: CMP-003 | M32: Mofawtar - E-Receipt - Awareness - Q2 | N32: AS-0302 | O32: Mofawtar - E-Receipt - Awareness - Q2 | Interest Tax Owners | P32: AD-030202 | Q32: Demo Reel | Interest Tax Owners | R32: Kareem | S32: Contacted | T32: Lead | U32: 24 | V32: Starter 850 | W32: 850 | X32: 0 | AC32: 54 | AD32: Yes | AF32: 46119 | AG32: Follow-up via WhatsApp
A33: L-00029 | B33: 46113 | C33: Customer 0029 | D33: Cairo Medical 26 | E33: 01028079492 | F33: lead0029@example.com | G33: Zagazig | H33: Medical | I33: Electronic Receipts | J33: Meta Ads | K33: Phone Call | L33: CMP-003 | M33: Mofawtar - E-Receipt - Awareness - Q2 | N33: AS-0301 | O33: Mofawtar - E-Receipt - Awareness - Q2 | Broad SMEs | P33: AD-030101 | Q33: Pain Point Static | Broad SMEs | R33: Ahmed | S33: Contacted | T33: Lead | U33: 58 | V33: Growth 2400 | W33: 2400 | X33: 0 | AC33: 480 | AD33: No | AF33: 46116 | AG33: Asked for demo
A34: L-00030 | B34: 46113 | C34: Customer 0030 | D34: Green Manufacturing 811 | E34: 01165792084 | F34: lead0030@example.com | G34: Giza | H34: Manufacturing | I34: Electronic Invoices | J34: Meta Ads | K34: WhatsApp | L34: CMP-004 | M34: Mofawtar - Tax Invoice - Lead Gen - Q2 | N34: AS-0403 | O34: Mofawtar - Tax Invoice - Lead Gen - Q2 | Retargeting Visitors | P34: AD-040302 | Q34: Demo Reel | Retargeting Visitors | R34: Salma | S34: Proposal Sent | T34: SQL | U34: 68 | V34: Growth 2400 | W34: 2400 | X34: 0 | Y34: 46116 | Z34: 46114 | AC34: 256 | AD34: No | AF34: 46118 | AG34: Asked for demo
A35: L-00031 | B35: 46114 | C35: Customer 0031 | D35: Royal Services 772 | E35: 01099363234 | F35: lead0031@example.com | G35: Qena | H35: Services | I35: Electronic Receipts | J35: Meta Ads | K35: Phone Call | L35: CMP-001 | M35: In2out - MessCampaign#1 - Testing - 15/4 | N35: AS-0101 | O35: In2out - MessCampaign#1 - Testing - 15/4 | Broad SMEs | P35: AD-010102 | Q35: Demo Reel | Broad SMEs | R35: Kareem | S35: Contacted | T35: Lead | U35: 46 | V35: Enterprise 12000 | W35: 12000 | X35: 0 | AC35: 19 | AD35: Yes | AF35: 46119 | AG35: Needs tax setup
A36: L-00032 | B36: 46114 | C36: Customer 0032 | D36: Smart Medical 827 | E36: 01243384061 | F36: lead0032@example.com | G36: Assiut | H36: Medical | I36: Electronic Receipts | J36: Meta Ads | K36: Instagram DM | L36: CMP-003 | M36: Mofawtar - E-Receipt - Awareness - Q2 | N36: AS-0302 | O36: Mofawtar - E-Receipt - Awareness - Q2 | Interest Tax Owners | P36: AD-030201 | Q36: Pain Point Static | Interest Tax Owners | R36: Youssef | S36: Qualified | T36: MQL | U36: 52 | V36: Starter 850 | W36: 850 | X36: 0 | Y36: 46114 | AC36: 112 | AD36: No | AF36: 46120 | AG36: High intent
A37: L-00033 | B37: 46114 | C37: Customer 0033 | D37: Nile Services 458 | E37: 01552156701 | F37: lead0033@example.com | G37: Tanta | H37: Services | I37: Electronic Receipts | J37: Meta Ads | K37: WhatsApp | L37: CMP-001 | M37: In2out - MessCampaign#1 - Testing - 15/4 | N37: AS-0102 | O37: In2out - MessCampaign#1 - Testing - 15/4 | Interest Tax Owners | P37: AD-010202 | Q37: Demo Reel | Interest Tax Owners | R37: Youssef | S37: Contacted | T37: Lead | U37: 34 | V37: Starter 850 | W37: 850 | X37: 0 | AC37: 1050 | AD37: No | AF37: 46118 | AG37: Needs tax setup
A38: L-00034 | B38: 46114 | C38: Customer 0034 | D38: Delta Pharmacy 179 | E38: 01143529159 | F38: lead0034@example.com | G38: Cairo | H38: Pharmacy | I38: Electronic Receipts | J38: Meta Ads | K38: WhatsApp | L38: CMP-003 | M38: Mofawtar - E-Receipt - Awareness - Q2 | N38: AS-0302 | O38: Mofawtar - E-Receipt - Awareness - Q2 | Interest Tax Owners | P38: AD-030201 | Q38: Pain Point Static | Interest Tax Owners | R38: Youssef | S38: Proposal Sent | T38: SQL | U38: 68 | V38: Starter 850 | W38: 850 | X38: 0 | Y38: 46117 | Z38: 46115 | AC38: 170 | AD38: No | AF38: 46117 | AG38: High intent
A39: L-00035 | B39: 46114 | C39: Customer 0035 | D39: Trust Retail 22 | E39: 01219321385 | F39: lead0035@example.com | G39: Suez | H39: Retail | I39: Electronic Receipts | J39: Meta Ads | K39: Instagram DM | L39: CMP-002 | M39: In2out - MessCampaign#2 - Testing - 20/4 | N39: AS-0202 | O39: In2out - MessCampaign#2 - Testing - 20/4 | Interest Tax Owners | P39: AD-020202 | Q39: Demo Reel | Interest Tax Owners | R39: Kareem | S39: Contacted | T39: Lead | U39: 38 | V39: Starter 850 | W39: 850 | X39: 0 | AC39: 454 | AD39: No | AF39: 46115 | AG39: Imported from Meta conversation
A40: L-00036 | B40: 46114 | C40: Customer 0036 | D40: Smart Restaurant 436 | E40: 01053806657 | F40: lead0036@example.com | G40: Alexandria | H40: Restaurant | I40: Electronic Receipts | J40: Meta Ads | K40: WhatsApp | L40: CMP-001 | M40: In2out - MessCampaign#1 - Testing - 15/4 | N40: AS-0101 | O40: In2out - MessCampaign#1 - Testing - 15/4 | Broad SMEs | P40: AD-010103 | Q40: Offer Carousel | Broad SMEs | R40: Salma | S40: Proposal Sent | T40: SQL | U40: 65 | V40: Starter 850 | W40: 850 | X40: 0 | Y40: 46117 | Z40: 46121 | AC40: 20 | AD40: Yes | AF40: 46119 | AG40: Price sensitive
A41: L-00037 | B41: 46114 | C41: Customer 0037 | D41: Smart Services 899 | E41: 01541501634 | F41: lead0037@example.com | G41: Ismailia | H41: Services | I41: Electronic Receipts | J41: Meta Ads | K41: Website Form | L41: CMP-001 | M41: In2out - MessCampaign#1 - Testing - 15/4 | N41: AS-0102 | O41: In2out - MessCampaign#1 - Testing - 15/4 | Interest Tax Owners | P41: AD-010201 | Q41: Pain Point Static | Interest Tax Owners | R41: Youssef | S41: Contacted | T41: Lead | U41: 39 | V41: Business 5000 | W41: 5000 | X41: 0 | AC41: 39 | AD41: Yes | AF41: 46117 | AG41: High intent
A42: L-00038 | B42: 46114 | C42: Customer 0038 | D42: Golden Retail 597 | E42: 01510859143 | F42: lead0038@example.com | G42: Suez | H42: Retail | I42: SaaS Subscription | J42: Meta Ads | K42: Website Form | L42: CMP-005 | M42: Mofawtar - Retargeting - Demo Booking - Q2 | N42: AS-0501 | O42: Mofawtar - Retargeting - Demo Booking - Q2 | Broad SMEs | P42: AD-050102 | Q42: Demo Reel | Broad SMEs | R42: Mona | S42: Contacted | T42: Lead | U42: 77 | V42: Growth 2400 | W42: 2400 | X42: 0 | AC42: 130 | AD42: No | AF42: 46117 | AG42: Asked for demo
A43: L-00039 | B43: 46114 | C43: Customer 0039 | D43: Golden Pharmacy 623 | E43: 01150771829 | F43: lead0039@example.com | G43: Ismailia | H43: Pharmacy | I43: Electronic Receipts | J43: Meta Ads | K43: Website Form | L43: CMP-003 | M43: Mofawtar - E-Receipt - Awareness - Q2 | N43: AS-0302 | O43: Mofawtar - E-Receipt - Awareness - Q2 | Interest Tax Owners | P43: AD-030201 | Q43: Pain Point Static | Interest Tax Owners | R43: Ahmed | S43: Contacted | T43: Lead | U43: 78 | V43: Business 5000 | W43: 5000 | X43: 0 | AC43: 339 | AD43: No | AF43: 46119 | AG43: Imported from Meta conversation
A44: L-00040 | B44: 46114 | C44: Customer 0040 | D44: Golden Services 116 | E44: 01211302913 | F44: lead0040@example.com | G44: Zagazig | H44: Services | I44: Electronic Receipts | J44: Organic Social | K44: WhatsApp | L44: CMP-001 | M44: In2out - MessCampaign#1 - Testing - 15/4 | N44: AS-0101 | O44: In2out - MessCampaign#1 - Testing - 15/4 | Broad SMEs | P44: AD-010102 | Q44: Demo Reel | Broad SMEs | R44: Ahmed | S44: Deal Lost | T44: Deal Lost | U44: 37 | V44: Growth 2400 | W44: 2400 | X44: 0 | AB44: 46133 | AC44: 59 | AD44: Yes | AE44: Not decision maker | AG44: Price sensitive
A45: L-00041 | B45: 46114 | C45: Customer 0041 | D45: Omega Distribution 474 | E45: 01049716661 | F45: lead0041@example.com | G45: Assiut | H45: Distribution | I45: Electronic Receipts | J45: Meta Ads | K45: WhatsApp | L45: CMP-002 | M45: In2out - MessCampaign#2 - Testing - 20/4 | N45: AS-0201 | O45: In2out - MessCampaign#2 - Testing - 20/4 | Broad SMEs | P45: AD-020103 | Q45: Offer Carousel | Broad SMEs | R45: Salma | S45: Contacted | T45: Lead | U45: 20 | V45: Starter 850 | W45: 850 | X45: 0 | AC45: 465 | AD45: No | AF45: 46116 | AG45: High intent
A46: L-00042 | B46: 46114 | C46: Customer 0042 | D46: Golden Distribution 493 | E46: 01217335354 | F46: lead0042@example.com | G46: Ismailia | H46: Distribution | I46: Electronic Receipts | J46: Meta Ads | K46: Website Form | L46: CMP-001 | M46: In2out - MessCampaign#1 - Testing - 15/4 | N46: AS-0101 | O46: In2out - MessCampaign#1 - Testing - 15/4 | Broad SMEs | P46: AD-010103 | Q46: Offer Carousel | Broad SMEs | R46: Salma | S46: Contacted | T46: Lead | U46: 48 | V46: Business 5000 | W46: 5000 | X46: 0 | AC46: 170 | AD46: No | AF46: 46115 | AG46: Needs tax setup
A47: L-00043 | B47: 46114 | C47: Customer 0043 | D47: Smart Services 633 | E47: 01040703561 | F47: lead0043@example.com | G47: Suez | H47: Services | I47: SaaS Subscription | J47: Meta Ads | K47: Messenger | L47: CMP-005 | M47: Mofawtar - Retargeting - Demo Booking - Q2 | N47: AS-0503 | O47: Mofawtar - Retargeting - Demo Booking - Q2 | Retargeting Visitors | P47: AD-050302 | Q47: Demo Reel | Retargeting Visitors | R47: Youssef | S47: Contacted | T47: Lead | U47: 72 | V47: Growth 2400 | W47: 2400 | X47: 0 | AC47: 120 | AD47: No | AF47: 46119 | AG47: Price sensitive
A48: L-00044 | B48: 46114 | C48: Customer 0044 | D48: Smart Services 972 | E48: 01096691736 | F48: lead0044@example.com | G48: Assiut | H48: Services | I48: SaaS Subscription | J48: Meta Ads | K48: Messenger | L48: CMP-005 | M48: Mofawtar - Retargeting - Demo Booking - Q2 | N48: AS-0501 | O48: Mofawtar - Retargeting - Demo Booking - Q2 | Broad SMEs | P48: AD-050101 | Q48: Pain Point Static | Broad SMEs | R48: Ahmed | S48: Deal Lost | T48: Deal Lost | U48: 32 | V48: Starter 850 | W48: 850 | X48: 0 | AB48: 46127 | AC48: 233 | AD48: No | AE48: No response | AG48: Asked for demo
A49: L-00045 | B49: 46114 | C49: Customer 0045 | D49: Prime Pharmacy 461 | E49: 01279934637 | F49: lead0045@example.com | G49: Suez | H49: Pharmacy | I49: Electronic Receipts | J49: Meta Ads | K49: Messenger | L49: CMP-002 | M49: In2out - MessCampaign#2 - Testing - 20/4 | N49: AS-0202 | O49: In2out - MessCampaign#2 - Testing - 20/4 | Interest Tax Owners | P49: AD-020201 | Q49: Pain Point Static | Interest Tax Owners | R49: Mona | S49: Contacted | T49: Lead | U49: 47 | V49: Starter 850 | W49: 850 | X49: 0 | AC49: 34 | AD49: Yes | AF49: 46117 | AG49: Follow-up via WhatsApp
A50: L-00046 | B50: 46114 | C50: Customer 0046 | D50: Delta Services 64 | E50: 01572885745 | F50: lead0046@example.com | G50: Cairo | H50: Services | I50: Electronic Invoices | J50: Meta Ads | K50: Messenger | L50: CMP-004 | M50: Mofawtar - Tax Invoice - Lead Gen - Q2 | N50: AS-0401 | O50: Mofawtar - Tax Invoice - Lead Gen - Q2 | Broad SMEs | P50: AD-040103 | Q50: Offer Carousel | Broad SMEs | R50: Youssef | S50: Qualified | T50: MQL | U50: 50 | V50: Starter 850 | W50: 850 | X50: 0 | Y50: 46114 | AC50: 210 | AD50: No | AF50: 46118 | AG50: Asked for demo
A51: L-00047 | B51: 46114 | C51: Customer 0047 | D51: Nile Medical 597 | E51: 01516988827 | F51: lead0047@example.com | G51: Cairo | H51: Medical | I51: Electronic Invoices | J51: Meta Ads | K51: WhatsApp | L51: CMP-004 | M51: Mofawtar - Tax Invoice - Lead Gen - Q2 | N51: AS-0401 | O51: Mofawtar - Tax Invoice - Lead Gen - Q2 | Broad SMEs | P51: AD-040101 | Q51: Pain Point Static | Broad SMEs | R51: Mona | S51: Contacted | T51: Lead | U51: 35 | V51: Starter 850 | W51: 850 | X51: 0 | AC51: 229 | AD51: No | AF51: 46115 | AG51: Needs tax setup
A52: L-00048 | B52: 46114 | C52: Customer 0048 | D52: Golden Distribution 588 | E52: 01555961943 | F52: lead0048@example.com | G52: Zagazig | H52: Distribution | I52: Electronic Receipts | J52: Organic Social | K52: WhatsApp | L52: CMP-002 | M52: In2out - MessCampaign#2 - Testing - 20/4 | N52: AS-0201 | O52: In2out - MessCampaign#2 - Testing - 20/4 | Broad SMEs | P52: AD-020102 | Q52: Demo Reel | Broad SMEs | R52: Kareem | S52: Qualified | T52: MQL | U52: 57 | V52: Starter 850 | W52: 850 | X52: 0 | Y52: 46116 | AC52: 343 | AD52: No | AF52: 46119 | AG52: High intent
A53: L-00049 | B53: 46114 | C53: Customer 0049 | D53: Fast Retail 124 | E53: 01596918659 | F53: lead0049@example.com | G53: Ismailia | H53: Retail | I53: Electronic Invoices | J53: Meta Ads | K53: WhatsApp | L53: CMP-004 | M53: Mofawtar - Tax Invoice - Lead Gen - Q2 | N53: AS-0402 | O53: Mofawtar - Tax Invoice - Lead Gen - Q2 | Interest Tax Owners | P53: AD-040202 | Q53: Demo Reel | Interest Tax Owners | R53: Ahmed | S53: Qualified | T53: MQL | U53: 60 | V53: Starter 850 | W53: 850 | X53: 0 | Y53: 46117 | AC53: 371 | AD53: No | AF53: 46118 | AG53: Needs tax setup
A54: L-00050 | B54: 46114 | C54: Customer 0050 | D54: Omega Manufacturing 888 | E54: 01298752010 | F54: lead0050@example.com | G54: Mansoura | H54: Manufacturing | I54: Electronic Invoices | J54: Meta Ads | K54: WhatsApp | L54: CMP-004 | M54: Mofawtar - Tax Invoice - Lead Gen - Q2 | N54: AS-0402 | O54: Mofawtar - Tax Invoice - Lead Gen - Q2 | Interest Tax Owners | P54: AD-040201 | Q54: Pain Point Static | Interest Tax Owners | R54: Mona | S54: Contacted | T54: Lead | U54: 50 | V54: Growth 2400 | W54: 2400 | X54: 0 | AC54: 272 | AD54: No | AF54: 46116 | AG54: Asked for demo
A55: L-00051 | B55: 46114 | C55: Customer 0051 | D55: Lotus Pharmacy 949 | E55: 01569098537 | F55: lead0051@example.com | G55: Cairo | H55: Pharmacy | I55: Electronic Receipts | J55: Meta Ads | K55: Messenger | L55: CMP-003 | M55: Mofawtar - E-Receipt - Awareness - Q2 | N55: AS-0301 | O55: Mofawtar - E-Receipt - Awareness - Q2 | Broad SMEs | P55: AD-030101 | Q55: Pain Point Static | Broad SMEs | R55: Kareem | S55: Contacted | T55: Lead | U55: 32 | V55: Starter 850 | W55: 850 | X55: 0 | AC55: 394 | AD55: No | AF55: 46117 | AG55: Price sensitive
A56: L-00052 | B56: 46114 | C56: Customer 0052 | D56: Fast Distribution 840 | E56: 01159794029 | F56: lead0052@example.com | G56: Tanta | H56: Distribution | I56: Electronic Receipts | J56: Meta Ads | K56: Website Form | L56: CMP-001 | M56: In2out - MessCampaign#1 - Testing - 15/4 | N56: AS-0101 | O56: In2out - MessCampaign#1 - Testing - 15/4 | Broad SMEs | P56: AD-010103 | Q56: Offer Carousel | Broad SMEs | R56: Salma | S56: Proposal Sent | T56: SQL | U56: 66 | V56: Growth 2400 | W56: 2400 | X56: 0 | Y56: 46114 | Z56: 46118 | AC56: 176 | AD56: No | AF56: 46118 | AG56: Needs tax setup
A57: L-00053 | B57: 46114 | C57: Customer 0053 | D57: Fast Distribution 870 | E57: 01082612653 | F57: lead0053@example.com | G57: Suez | H57: Distribution | I57: SaaS Subscription | J57: Meta Ads | K57: Instagram DM | L57: CMP-005 | M57: Mofawtar - Retargeting - Demo Booking - Q2 | N57: AS-0503 | O57: Mofawtar - Retargeting - Demo Booking - Q2 | Retargeting Visitors | P57: AD-050302 | Q57: Demo Reel | Retargeting Visitors | R57: Salma | S57: Contacted | T57: Lead | U57: 29 | V57: Starter 850 | W57: 850 | X57: 0 | AC57: 246 | AD57: No | AF57: 46120 | AG57: Follow-up via WhatsApp
A58: L-00054 | B58: 46114 | C58: Customer 0054 | D58: Target Retail 991 | E58: 01099553066 | F58: lead0054@example.com | G58: Cairo | H58: Retail | I58: Electronic Receipts | J58: Meta Ads | K58: Messenger | L58: CMP-002 | M58: In2out - MessCampaign#2 - Testing - 20/4 | N58: AS-0202 | O58: In2out - MessCampaign#2 - Testing - 20/4 | Interest Tax Owners | P58: AD-020201 | Q58: Pain Point Static | Interest Tax Owners | R58: Kareem | S58: Contacted | T58: Lead | U58: 27 | V58: Starter 850 | W58: 850 | X58: 0 | AC58: 44 | AD58: Yes | AF58: 46117 | AG58: Asked for demo
A59: L-00055 | B59: 46114 | C59: Customer 0055 | D59: Royal Medical 93 | E59: 01121773582 | F59: lead0055@example.com | G59: Mansoura | H59: Medical | I59: Electronic Receipts | J59: Meta Ads | K59: Messenger | L59: CMP-001 | M59: In2out - MessCampaign#1 - Testing - 15/4 | N59: AS-0101 | O59: In2out - MessCampaign#1 - Testing - 15/4 | Broad SMEs | P59: AD-010102 | Q59: Demo Reel | Broad SMEs | R59: Youssef | S59: Contacted | T59: Lead | U59: 36 | V59: Enterprise 12000 | W59: 12000 | X59: 0 | AC59: 323 | AD59: No | AF59: 46120 | AG59: Imported from Meta conversation
A60: L-00056 | B60: 46115 | C60: Customer 0056 | D60: Blue E-commerce 584 | E60: 01574165645 | F60: lead0056@example.com | G60: Alexandria | H60: E-commerce | I60: Electronic Receipts | J60: Meta Ads | K60: WhatsApp | L60: CMP-003 | M60: Mofawtar - E-Receipt - Awareness - Q2 | N60: AS-0302 | O60: Mofawtar - E-Receipt - Awareness - Q2 | Interest Tax Owners | P60: AD-030202 | Q60: Demo Reel | Interest Tax Owners | R60: Youssef | S60: Contacted | T60: Lead | U60: 23 | V60: Growth 2400 | W60: 2400 | X60: 0 | AC60: 365 | AD60: No | AF60: 46117 | AG60: High intent
A61: L-00057 | B61: 46115 | C61: Customer 0057 | D61: Fast Manufacturing 439 | E61: 01091323650 | F61: lead0057@example.com | G61: Alexandria | H61: Manufacturing | I61: Electronic Invoices | J61: Meta Ads | K61: Messenger | L61: CMP-004 | M61: Mofawtar - Tax Invoice - Lead Gen - Q2 | N61: AS-0402 | O61: Mofawtar - Tax Invoice - Lead Gen - Q2 | Interest Tax Owners | P61: AD-040201 | Q61: Pain Point Static | Interest Tax Owners | R61: Salma | S61: Contacted | T61: Lead | U61: 51 | V61: Business 5000 | W61: 5000 | X61: 0 | AC61: 1130 | AD61: No | AF61: 46116 | AG61: Follow-up via WhatsApp
A62: L-00058 | B62: 46115 | C62: Customer 0058 | D62: Nile Medical 663 | E62: 01113899798 | F62: lead0058@example.com | G62: Alexandria | H62: Medical | I62: SaaS Subscription | J62: Meta Ads | K62: WhatsApp | L62: CMP-005 | M62: Mofawtar - Retargeting - Demo Booking - Q2 | N62: AS-0501 | O62: Mofawtar - Retargeting - Demo Booking - Q2 | Broad SMEs | P62: AD-050103 | Q62: Offer Carousel | Broad SMEs | R62: Ahmed | S62: Contacted | T62: Lead | U62: 70 | V62: Business 5000 | W62: 5000 | X62: 0 | AC62: 199 | AD62: No | AF62: 46118 | AG62: High intent
A63: L-00059 | B63: 46115 | C63: Customer 0059 | D63: Cairo Medical 240 | E63: 01086714178 | F63: lead0059@example.com | G63: Mansoura | H63: Medical | I63: Electronic Receipts | J63: Meta Ads | K63: WhatsApp | L63: CMP-003 | M63: Mofawtar - E-Receipt - Awareness - Q2 | N63: AS-0301 | O63: Mofawtar - E-Receipt - Awareness - Q2 | Broad SMEs | P63: AD-030102 | Q63: Demo Reel | Broad SMEs | R63: Kareem | S63: Qualified | T63: MQL | U63: 57 | V63: Business 5000 | W63: 5000 | X63: 0 | Y63: 46116 | AC63: 10 | AD63: Yes | AF63: 46118 | AG63: Needs tax setup
A64: L-00060 | B64: 46115 | C64: Customer 0060 | D64: Trust Medical 200 | E64: 01234831499 | F64: lead0060@example.com | G64: Qena | H64: Medical | I64: SaaS Subscription | J64: Meta Ads | K64: WhatsApp | L64: CMP-005 | M64: Mofawtar - Retargeting - Demo Booking - Q2 | N64: AS-0502 | O64: Mofawtar - Retargeting - Demo Booking - Q2 | Interest Tax Owners | P64: AD-050201 | Q64: Pain Point Static | Interest Tax Owners | R64: Salma | S64: Qualified | T64: MQL | U64: 67 | V64: Growth 2400 | W64: 2400 | X64: 0 | Y64: 46116 | AC64: 443 | AD64: No | AF64: 46118 | AG64: Price sensitive
A65: L-00061 | B65: 46115 | C65: Customer 0061 | D65: Smart E-commerce 57 | E65: 01544561594 | F65: lead0061@example.com | G65: Cairo | H65: E-commerce | I65: Electronic Invoices | J65: Meta Ads | K65: Instagram DM | L65: CMP-004 | M65: Mofawtar - Tax Invoice - Lead Gen - Q2 | N65: AS-0403 | O65: Mofawtar - Tax Invoice - Lead Gen - Q2 | Retargeting Visitors | P65: AD-040302 | Q65: Demo Reel | Retargeting Visitors | R65: Youssef | S65: Qualified | T65: MQL | U65: 61 | V65: Enterprise 12000 | W65: 12000 | X65: 0 | Y65: 46116 | AC65: 161 | AD65: No | AF65: 46120 | AG65: High intent
A66: L-00062 | B66: 46115 | C66: Customer 0062 | D66: Target Distribution 503 | E66: 01591839237 | F66: lead0062@example.com | G66: Cairo | H66: Distribution | I66: Electronic Receipts | J66: Meta Ads | K66: WhatsApp | L66: CMP-001 | M66: In2out - MessCampaign#1 - Testing - 15/4 | N66: AS-0101 | O66: In2out - MessCampaign#1 - Testing - 15/4 | Broad SMEs | P66: AD-010102 | Q66: Demo Reel | Broad SMEs | R66: Youssef | S66: Contacted | T66: Lead | U66: 23 | V66: Business 5000 | W66: 5000 | X66: 0 | AC66: 88 | AD66: No | AF66: 46118 | AG66: Follow-up via WhatsApp
A67: L-00063 | B67: 46115 | C67: Customer 0063 | D67: Omega Services 414 | E67: 01039039901 | F67: lead0063@example.com | G67: Alexandria | H67: Services | I67: Electronic Receipts | J67: Meta Ads | K67: Instagram DM | L67: CMP-001 | M67: In2out - MessCampaign#1 - Testing - 15/4 | N67: AS-0102 | O67: In2out - MessCampaign#1 - Testing - 15/4 | Interest Tax Owners | P67: AD-010201 | Q67: Pain Point Static | Interest Tax Owners | R67: Salma | S67: Contacted | T67: Lead | U67: 35 | V67: Starter 850 | W67: 850 | X67: 0 | AC67: 373 | AD67: No | AF67: 46120 | AG67: Price sensitive
A68: L-00064 | B68: 46115 | C68: Customer 0064 | D68: Trust Distribution 825 | E68: 01190751332 | F68: lead0064@example.com | G68: Zagazig | H68: Distribution | I68: Electronic Invoices | J68: Website | K68: WhatsApp | L68: CMP-004 | M68: Mofawtar - Tax Invoice - Lead Gen - Q2 | N68: AS-0403 | O68: Mofawtar - Tax Invoice - Lead Gen - Q2 | Retargeting Visitors | P68: AD-040302 | Q68: Demo Reel | Retargeting Visitors | R68: Kareem | S68: Contacted | T68: Lead | U68: 72 | V68: Starter 850 | W68: 850 | X68: 0 | AC68: 236 | AD68: No | AF68: 46118 | AG68: High intent
A69: L-00065 | B69: 46115 | C69: Customer 0065 | D69: Smart Manufacturing 737 | E69: 01529920279 | F69: lead0065@example.com | G69: Zagazig | H69: Manufacturing | I69: SaaS Subscription | J69: Meta Ads | K69: WhatsApp | L69: CMP-005 | M69: Mofawtar - Retargeting - Demo Booking - Q2 | N69: AS-0501 | O69: Mofawtar - Retargeting - Demo Booking - Q2 | Broad SMEs | P69: AD-050101 | Q69: Pain Point Static | Broad SMEs | R69: Kareem | S69: Deal Lost | T69: Deal Lost | U69: 32 | V69: Growth 2400 | W69: 2400 | X69: 0 | AB69: 46117 | AC69: 1414 | AD69: No | AE69: Price objection | AG69: Asked for demo
A70: L-00066 | B70: 46115 | C70: Customer 0066 | D70: Cairo Retail 653 | E70: 01295562972 | F70: lead0066@example.com | G70: Assiut | H70: Retail | I70: SaaS Subscription | J70: Meta Ads | K70: WhatsApp | L70: CMP-005 | M70: Mofawtar - Retargeting - Demo Booking - Q2 | N70: AS-0501 | O70: Mofawtar - Retargeting - Demo Booking - Q2 | Broad SMEs | P70: AD-050102 | Q70: Demo Reel | Broad SMEs | R70: Ahmed | S70: Proposal Sent | T70: SQL | U70: 69 | V70: Starter 850 | W70: 850 | X70: 0 | Y70: 46116 | Z70: 46120 | AC70: 263 | AD70: No | AF70: 46119 | AG70: Needs tax setup
A71: L-00067 | B71: 46115 | C71: Customer 0067 | D71: Delta E-commerce 75 | E71: 01513020677 | F71: lead0067@example.com | G71: Assiut | H71: E-commerce | I71: Electronic Receipts | J71: Meta Ads | K71: Messenger | L71: CMP-001 | M71: In2out - MessCampaign#1 - Testing - 15/4 | N71: AS-0102 | O71: In2out - MessCampaign#1 - Testing - 15/4 | Interest Tax Owners | P71: AD-010201 | Q71: Pain Point Static | Interest Tax Owners | R71: Kareem | S71: Contacted | T71: Lead | U71: 38 | V71: Starter 850 | W71: 850 | X71: 0 | AC71: 71 | AD71: No | AF71: 46120 | AG71: Asked for demo
A72: L-00068 | B72: 46115 | C72: Customer 0068 | D72: Alfa Restaurant 349 | E72: 01012615123 | F72: lead0068@example.com | G72: Cairo | H72: Restaurant | I72: Electronic Invoices | J72: Referral | K72: Messenger | L72: CMP-004 | M72: Mofawtar - Tax Invoice - Lead Gen - Q2 | N72: AS-0402 | O72: Mofawtar - Tax Invoice - Lead Gen - Q2 | Interest Tax Owners | P72: AD-040201 | Q72: Pain Point Static | Interest Tax Owners | R72: Salma | S72: Qualified | T72: MQL | U72: 72 | V72: Starter 850 | W72: 850 | X72: 0 | Y72: 46117 | AC72: 377 | AD72: No | AF72: 46116 | AG72: Follow-up via WhatsApp
A73: L-00069 | B73: 46115 | C73: Customer 0069 | D73: Cairo Restaurant 142 | E73: 01153250159 | F73: lead0069@example.com | G73: Cairo | H73: Restaurant | I73: Electronic Receipts | J73: Meta Ads | K73: WhatsApp | L73: CMP-003 | M73: Mofawtar - E-Receipt - Awareness - Q2 | N73: AS-0302 | O73: Mofawtar - E-Receipt - Awareness - Q2 | Interest Tax Owners | P73: AD-030202 | Q73: Demo Reel | Interest Tax Owners | R73: Mona | S73: Qualified | T73: MQL | U73: 53 | V73: Starter 850 | W73: 850 | X73: 0 | Y73: 46118 | AC73: 8 | AD73: Yes | AF73: 46121 | AG73: Follow-up via WhatsApp
A74: L-00070 | B74: 46115 | C74: Customer 0070 | D74: Target Services 596 | E74: 01185196066 | F74: lead0070@example.com | G74: Cairo | H74: Services | I74: Electronic Receipts | J74: Meta Ads | K74: WhatsApp | L74: CMP-002 | M74: In2out - MessCampaign#2 - Testing - 20/4 | N74: AS-0201 | O74: In2out - MessCampaign#2 - Testing - 20/4 | Broad SMEs | P74: AD-020102 | Q74: Demo Reel | Broad SMEs | R74: Mona | S74: Contacted | T74: Lead | U74: 49 | V74: Starter 850 | W74: 850 | X74: 0 | AC74: 225 | AD74: No | AF74: 46116 | AG74: Asked for demo
A75: L-00071 | B75: 46115 | C75: Customer 0071 | D75: Smart E-commerce 221 | E75: 01044123401 | F75: lead0071@example.com | G75: Zagazig | H75: E-commerce | I75: Electronic Receipts | J75: Meta Ads | K75: Messenger | L75: CMP-001 | M75: In2out - MessCampaign#1 - Testing - 15/4 | N75: AS-0102 | O75: In2out - MessCampaign#1 - Testing - 15/4 | Interest Tax Owners | P75: AD-010202 | Q75: Demo Reel | Interest Tax Owners | R75: Youssef | S75: Contacted | T75: Lead | U75: 44 | V75: Starter 850 | W75: 850 | X75: 0 | AC75: 7 | AD75: Yes | AF75: 46118 | AG75: High intent
A76: L-00072 | B76: 46115 | C76: Customer 0072 | D76: Royal Manufacturing 38 | E76: 01054184184 | F76: lead0072@example.com | G76: Giza | H76: Manufacturing | I76: Electronic Receipts | J76: Meta Ads | K76: Messenger | L76: CMP-001 | M76: In2out - MessCampaign#1 - Testing - 15/4 | N76: AS-0101 | O76: In2out - MessCampaign#1 - Testing - 15/4 | Broad SMEs | P76: AD-010103 | Q76: Offer Carousel | Broad SMEs | R76: Ahmed | S76: Contacted | T76: Lead | U76: 21 | V76: Starter 850 | W76: 850 | X76: 0 | AC76: 172 | AD76: No | AF76: 46118 | AG76: Needs tax setup
A77: L-00073 | B77: 46115 | C77: Customer 0073 | D77: Green Retail 997 | E77: 01592580658 | F77: lead0073@example.com | G77: Qena | H77: Retail | I77: SaaS Subscription | J77: Direct WhatsApp | K77: WhatsApp | L77: CMP-005 | M77: Mofawtar - Retargeting - Demo Booking - Q2 | N77: AS-0501 | O77: Mofawtar - Retargeting - Demo Booking - Q2 | Broad SMEs | P77: AD-050101 | Q77: Pain Point Static | Broad SMEs | R77: Youssef | S77: Nurture | T77: Nurture | U77: 43 | V77: Starter 850 | W77: 850 | X77: 0 | AC77: 337 | AD77: No | AF77: 46116 | AG77: Imported from Meta conversation
A78: L-00074 | B78: 46115 | C78: Customer 0074 | D78: Royal Restaurant 967 | E78: 01053537171 | F78: lead0074@example.com | G78: Assiut | H78: Restaurant | I78: Electronic Receipts | J78: Meta Ads | K78: WhatsApp | L78: CMP-001 | M78: In2out - MessCampaign#1 - Testing - 15/4 | N78: AS-0102 | O78: In2out - MessCampaign#1 - Testing - 15/4 | Interest Tax Owners | P78: AD-010202 | Q78: Demo Reel | Interest Tax Owners | R78: Kareem | S78: Contacted | T78: Lead | U78: 49 | V78: Growth 2400 | W78: 2400 | X78: 0 | AC78: 409 | AD78: No | AF78: 46117 | AG78: Asked for demo
A79: L-00075 | B79: 46115 | C79: Customer 0075 | D79: Golden Services 213 | E79: 01216271035 | F79: lead0075@example.com | G79: Giza | H79: Services | I79: Electronic Invoices | J79: Meta Ads | K79: WhatsApp | L79: CMP-004 | M79: Mofawtar - Tax Invoice - Lead Gen - Q2 | N79: AS-0401 | O79: Mofawtar - Tax Invoice - Lead Gen - Q2 | Broad SMEs | P79: AD-040103 | Q79: Offer Carousel | Broad SMEs | R79: Ahmed | S79: Contacted | T79: Lead | U79: 52 | V79: Starter 850 | W79: 850 | X79: 0 | AC79: 448 | AD79: No | AF79: 46118 | AG79: Needs tax setup
A80: L-00076 | B80: 46115 | C80: Customer 0076 | D80: Lotus Restaurant 292 | E80: 01041938429 | F80: lead0076@example.com | G80: Cairo | H80: Restaurant | I80: Electronic Receipts | J80: Meta Ads | K80: Messenger | L80: CMP-003 | M80: Mofawtar - E-Receipt - Awareness - Q2 | N80: AS-0302 | O80: Mofawtar - E-Receipt - Awareness - Q2 | Interest Tax Owners | P80: AD-030201 | Q80: Pain Point Static | Interest Tax Owners | R80: Salma | S80: Contacted | T80: Lead | U80: 60 | V80: Starter 850 | W80: 850 | X80: 0 | AC80: 45 | AD80: Yes | AF80: 46118 | AG80: Follow-up via WhatsApp
A81: L-00077 | B81: 46115 | C81: Customer 0077 | D81: Smart Pharmacy 386 | E81: 01249596461 | F81: lead0077@example.com | G81: Zagazig | H81: Pharmacy | I81: Electronic Invoices | J81: Meta Ads | K81: Messenger | L81: CMP-004 | M81: Mofawtar - Tax Invoice - Lead Gen - Q2 | N81: AS-0402 | O81: Mofawtar - Tax Invoice - Lead Gen - Q2 | Interest Tax Owners | P81: AD-040202 | Q81: Demo Reel | Interest Tax Owners | R81: Youssef | S81: Contacted | T81: Lead | U81: 62 | V81: Starter 850 | W81: 850 | X81: 0 | AC81: 460 | AD81: No | AF81: 46117 | AG81: High intent
A82: L-00078 | B82: 46115 | C82: Customer 0078 | D82: Target Manufacturing 469 | E82: 01112459062 | F82: lead0078@example.com | G82: Tanta | H82: Manufacturing | I82: Electronic Invoices | J82: Meta Ads | K82: Messenger | L82: CMP-004 | M82: Mofawtar - Tax Invoice - Lead Gen - Q2 | N82: AS-0403 | O82: Mofawtar - Tax Invoice - Lead Gen - Q2 | Retargeting Visitors | P82: AD-040302 | Q82: Demo Reel | Retargeting Visitors | R82: Kareem | S82: Qualified | T82: MQL | U82: 61 | V82: Enterprise 12000 | W82: 12000 | X82: 0 | Y82: 46116 | AC82: 351 | AD82: No | AF82: 46119 | AG82: Asked for demo
A83: L-00079 | B83: 46115 | C83: Customer 0079 | D83: Target Pharmacy 784 | E83: 01056792399 | F83: lead0079@example.com | G83: Alexandria | H83: Pharmacy | I83: Electronic Invoices | J83: Meta Ads | K83: Instagram DM | L83: CMP-004 | M83: Mofawtar - Tax Invoice - Lead Gen - Q2 | N83: AS-0403 | O83: Mofawtar - Tax Invoice - Lead Gen - Q2 | Retargeting Visitors | P83: AD-040301 | Q83: Pain Point Static | Retargeting Visitors | R83: Salma | S83: Contacted | T83: Lead | U83: 43 | V83: Growth 2400 | W83: 2400 | X83: 0 | AC83: 22 | AD83: Yes | AF83: 46117 | AG83: Needs tax setup
A84: L-00080 | B84: 46115 | C84: Customer 0080 | D84: Delta Retail 713 | E84: 01547683408 | F84: lead0080@example.com | G84: Suez | H84: Retail | I84: Electronic Receipts | J84: Referral | K84: Website Form | L84: CMP-003 | M84: Mofawtar - E-Receipt - Awareness - Q2 | N84: AS-0302 | O84: Mofawtar - E-Receipt - Awareness - Q2 | Interest Tax Owners | P84: AD-030201 | Q84: Pain Point Static | Interest Tax Owners | R84: Ahmed | S84: Qualified | T84: MQL | U84: 69 | V84: Growth 2400 | W84: 2400 | X84: 0 | Y84: 46116 | AC84: 346 | AD84: No | AF84: 46121 | AG84: Needs tax setup
A85: L-00081 | B85: 46115 | C85: Customer 0081 | D85: Smart Restaurant 543 | E85: 01582612215 | F85: lead0081@example.com | G85: Assiut | H85: Restaurant | I85: SaaS Subscription | J85: Meta Ads | K85: Website Form | L85: CMP-005 | M85: Mofawtar - Retargeting - Demo Booking - Q2 | N85: AS-0501 | O85: Mofawtar - Retargeting - Demo Booking - Q2 | Broad SMEs | P85: AD-050103 | Q85: Offer Carousel | Broad SMEs | R85: Salma | S85: Contacted | T85: Lead | U85: 63 | V85: Business 5000 | W85: 5000 | X85: 0 | AC85: 115 | AD85: No | AF85: 46117 | AG85: Follow-up via WhatsApp
A86: L-00082 | B86: 46115 | C86: Customer 0082 | D86: Omega E-commerce 723 | E86: 01116865176 | F86: lead0082@example.com | G86: Qena | H86: E-commerce | I86: Electronic Invoices | J86: Meta Ads | K86: Phone Call | L86: CMP-004 | M86: Mofawtar - Tax Invoice - Lead Gen - Q2 | N86: AS-0401 | O86: Mofawtar - Tax Invoice - Lead Gen - Q2 | Broad SMEs | P86: AD-040103 | Q86: Offer Carousel | Broad SMEs | R86: Youssef | S86: Contacted | T86: Lead | U86: 58 | V86: Growth 2400 | W86: 2400 | X86: 0 | AC86: 1438 | AD86: No | AF86: 46116 | AG86: Asked for demo
A87: L-00083 | B87: 46115 | C87: Customer 0083 | D87: Prime Services 122 | E87: 01070652921 | F87: lead0083@example.com | G87: Suez | H87: Services | I87: Electronic Invoices | J87: Meta Ads | K87: Messenger | L87: CMP-004 | M87: Mofawtar - Tax Invoice - Lead Gen - Q2 | N87: AS-0401 | O87: Mofawtar - Tax Invoice - Lead Gen - Q2 | Broad SMEs | P87: AD-040101 | Q87: Pain Point Static | Broad SMEs | R87: Kareem | S87: Qualified | T87: MQL | U87: 53 | V87: Growth 2400 | W87: 2400 | X87: 0 | Y87: 46117 | AC87: 412 | AD87: No | AF87: 46117 | AG87: Imported from Meta conversation
A88: L-00084 | B88: 46116 | C88: Customer 0084 | D88: Fast Medical 275 | E88: 01155752482 | F88: lead0084@example.com | G88: Qena | H88: Medical | I88: Electronic Invoices | J88: Meta Ads | K88: WhatsApp | L88: CMP-004 | M88: Mofawtar - Tax Invoice - Lead Gen - Q2 | N88: AS-0403 | O88: Mofawtar - Tax Invoice - Lead Gen - Q2 | Retargeting Visitors | P88: AD-040302 | Q88: Demo Reel | Retargeting Visitors | R88: Kareem | S88: Contacted | T88: Lead | U88: 59 | V88: Starter 850 | W88: 850 | X88: 0 | AC88: 412 | AD88: No | AF88: 46121 | AG88: Needs tax setup
A89: L-00085 | B89: 46116 | C89: Customer 0085 | D89: Trust Retail 698 | E89: 01554273820 | F89: lead0085@example.com | G89: Suez | H89: Retail | I89: Electronic Receipts | J89: Meta Ads | K89: Instagram DM | L89: CMP-002 | M89: In2out - MessCampaign#2 - Testing - 20/4 | N89: AS-0202 | O89: In2out - MessCampaign#2 - Testing - 20/4 | Interest Tax Owners | P89: AD-020201 | Q89: Pain Point Static | Interest Tax Owners | R89: Salma | S89: Qualified | T89: MQL | U89: 68 | V89: Business 5000 | W89: 5000 | X89: 0 | Y89: 46117 | AC89: 390 | AD89: No | AF89: 46121 | AG89: High intent
A90: L-00086 | B90: 46116 | C90: Customer 0086 | D90: Lotus Manufacturing 990 | E90: 01522605652 | F90: lead0086@example.com | G90: Mansoura | H90: Manufacturing | I90: SaaS Subscription | J90: Meta Ads | K90: Instagram DM | L90: CMP-005 | M90: Mofawtar - Retargeting - Demo Booking - Q2 | N90: AS-0503 | O90: Mofawtar - Retargeting - Demo Booking - Q2 | Retargeting Visitors | P90: AD-050302 | Q90: Demo Reel | Retargeting Visitors | R90: Mona | S90: Contacted | T90: Lead | U90: 36 | V90: Starter 850 | W90: 850 | X90: 0 | AC90: 241 | AD90: No | AF90: 46117 | AG90: Imported from Meta conversation
A91: L-00087 | B91: 46116 | C91: Customer 0087 | D91: Prime E-commerce 23 | E91: 01135379284 | F91: lead0087@example.com | G91: Suez | H91: E-commerce | I91: Electronic Receipts | J91: Meta Ads | K91: Messenger | L91: CMP-003 | M91: Mofawtar - E-Receipt - Awareness - Q2 | N91: AS-0302 | O91: Mofawtar - E-Receipt - Awareness - Q2 | Interest Tax Owners | P91: AD-030201 | Q91: Pain Point Static | Interest Tax Owners | R91: Youssef | S91: Nurture | T91: Nurture | U91: 30 | V91: Starter 850 | W91: 850 | X91: 0 | AC91: 167 | AD91: No | AF91: 46121 | AG91: Price sensitive
A92: L-00088 | B92: 46116 | C92: Customer 0088 | D92: Cairo Restaurant 479 | E92: 01152085575 | F92: lead0088@example.com | G92: Zagazig | H92: Restaurant | I92: Electronic Receipts | J92: Meta Ads | K92: Instagram DM | L92: CMP-002 | M92: In2out - MessCampaign#2 - Testing - 20/4 | N92: AS-0202 | O92: In2out - MessCampaign#2 - Testing - 20/4 | Interest Tax Owners | P92: AD-020201 | Q92: Pain Point Static | Interest Tax Owners | R92: Mona | S92: Contacted | T92: Lead | U92: 31 | V92: Growth 2400 | W92: 2400 | X92: 0 | AC92: 103 | AD92: No | AF92: 46119 | AG92: Follow-up via WhatsApp
A93: L-00089 | B93: 46116 | C93: Customer 0089 | D93: Target Medical 637 | E93: 01214480164 | F93: lead0089@example.com | G93: Qena | H93: Medical | I93: Electronic Receipts | J93: Meta Ads | K93: Instagram DM | L93: CMP-002 | M93: In2out - MessCampaign#2 - Testing - 20/4 | N93: AS-0201 | O93: In2out - MessCampaign#2 - Testing - 20/4 | Broad SMEs | P93: AD-020102 | Q93: Demo Reel | Broad SMEs | R93: Mona | S93: Nurture | T93: Nurture | U93: 28 | V93: Starter 850 | W93: 850 | X93: 0 | AC93: 220 | AD93: No | AF93: 46119 | AG93: Price sensitive
A94: L-00090 | B94: 46116 | C94: Customer 0090 | D94: Prime Retail 969 | E94: 01285645219 | F94: lead0090@example.com | G94: Tanta | H94: Retail | I94: Electronic Invoices | J94: Meta Ads | K94: Phone Call | L94: CMP-004 | M94: Mofawtar - Tax Invoice - Lead Gen - Q2 | N94: AS-0402 | O94: Mofawtar - Tax Invoice - Lead Gen - Q2 | Interest Tax Owners | P94: AD-040201 | Q94: Pain Point Static | Interest Tax Owners | R94: Mona | S94: Contacted | T94: Lead | U94: 45 | V94: Starter 850 | W94: 850 | X94: 0 | AC94: 161 | AD94: No | AF94: 46120 | AG94: High intent
A95: L-00091 | B95: 46116 | C95: Customer 0091 | D95: Nile Pharmacy 937 | E95: 01132663997 | F95: lead0091@example.com | G95: Alexandria | H95: Pharmacy | I95: Electronic Receipts | J95: Organic Social | K95: WhatsApp | L95: CMP-003 | M95: Mofawtar - E-Receipt - Awareness - Q2 | N95: AS-0302 | O95: Mofawtar - E-Receipt - Awareness - Q2 | Interest Tax Owners | P95: AD-030202 | Q95: Demo Reel | Interest Tax Owners | R95: Mona | S95: Contacted | T95: Lead | U95: 54 | V95: Starter 850 | W95: 850 | X95: 0 | AC95: 210 | AD95: No | AF95: 46122 | AG95: Imported from Meta conversation
A96: L-00092 | B96: 46116 | C96: Customer 0092 | D96: Alfa E-commerce 840 | E96: 01287931150 | F96: lead0092@example.com | G96: Zagazig | H96: E-commerce | I96: Electronic Receipts | J96: Meta Ads | K96: WhatsApp | L96: CMP-002 | M96: In2out - MessCampaign#2 - Testing - 20/4 | N96: AS-0202 | O96: In2out - MessCampaign#2 - Testing - 20/4 | Interest Tax Owners | P96: AD-020202 | Q96: Demo Reel | Interest Tax Owners | R96: Youssef | S96: Nurture | T96: Nurture | U96: 42 | V96: Starter 850 | W96: 850 | X96: 0 | AC96: 192 | AD96: No | AF96: 46120 | AG96: Needs tax setup
A97: L-00093 | B97: 46116 | C97: Customer 0093 | D97: Golden Manufacturing 150 | E97: 01565021554 | F97: lead0093@example.com | G97: Mansoura | H97: Manufacturing | I97: Electronic Receipts | J97: Meta Ads | K97: Messenger | L97: CMP-003 | M97: Mofawtar - E-Receipt - Awareness - Q2 | N97: AS-0301 | O97: Mofawtar - E-Receipt - Awareness - Q2 | Broad SMEs | P97: AD-030102 | Q97: Demo Reel | Broad SMEs | R97: Youssef | S97: Contacted | T97: Lead | U97: 58 | V97: Starter 850 | W97: 850 | X97: 0 | AC97: 121 | AD97: No | AF97: 46121 | AG97: High intent
A98: L-00094 | B98: 46116 | C98: Customer 0094 | D98: Cairo Restaurant 979 | E98: 01130087920 | F98: lead0094@example.com | G98: Cairo | H98: Restaurant | I98: SaaS Subscription | J98: Meta Ads | K98: WhatsApp | L98: CMP-005 | M98: Mofawtar - Retargeting - Demo Booking - Q2 | N98: AS-0501 | O98: Mofawtar - Retargeting - Demo Booking - Q2 | Broad SMEs | P98: AD-050101 | Q98: Pain Point Static | Broad SMEs | R98: Mona | S98: Qualified | T98: MQL | U98: 70 | V98: Enterprise 12000 | W98: 12000 | X98: 0 | Y98: 46116 | AC98: 220 | AD98: No | AF98: 46119 | AG98: Price sensitive
A99: L-00095 | B99: 46116 | C99: Customer 0095 | D99: Cairo E-commerce 49 | E99: 01037810769 | F99: lead0095@example.com | G99: Qena | H99: E-commerce | I99: Electronic Receipts | J99: Meta Ads | K99: Messenger | L99: CMP-003 | M99: Mofawtar - E-Receipt - Awareness - Q2 | N99: AS-0301 | O99: Mofawtar - E-Receipt - Awareness - Q2 | Broad SMEs | P99: AD-030103 | Q99: Offer Carousel | Broad SMEs | R99: Salma | S99: Contacted | T99: Lead | U99: 21 | V99: Starter 850 | W99: 850 | X99: 0 | AC99: 58 | AD99: Yes | AF99: 46119 | AG99: Price sensitive
A100: L-00096 | B100: 46116 | C100: Customer 0096 | D100: Target Restaurant 712 | E100: 01188942330 | F100: lead0096@example.com | G100: Giza | H100: Restaurant | I100: Electronic Receipts | J100: Meta Ads | K100: Messenger | L100: CMP-003 | M100: Mofawtar - E-Receipt - Awareness - Q2 | N100: AS-0301 | O100: Mofawtar - E-Receipt - Awareness - Q2 | Broad SMEs | P100: AD-030103 | Q100: Offer Carousel | Broad SMEs | R100: Ahmed | S100: Contacted | T100: Lead | U100: 50 | V100: Growth 2400 | W100: 2400 | X100: 0 | AC100: 124 | AD100: No | AF100: 46118 | AG100: Follow-up via WhatsApp
A101: L-00097 | B101: 46116 | C101: Customer 0097 | D101: Trust Retail 582 | E101: 01129504200 | F101: lead0097@example.com | G101: Assiut | H101: Retail | I101: Electronic Invoices | J101: Meta Ads | K101: WhatsApp | L101: CMP-004 | M101: Mofawtar - Tax Invoice - Lead Gen - Q2 | N101: AS-0401 | O101: Mofawtar - Tax Invoice - Lead Gen - Q2 | Broad SMEs | P101: AD-040103 | Q101: Offer Carousel | Broad SMEs | R101: Kareem | S101: Qualified | T101: MQL | U101: 51 | V101: Starter 850 | W101: 850 | X101: 0 | Y101: 46116 | AC101: 446 | AD101: No | AF101: 46120 | AG101: Asked for demo
...

Sheet 04_Activity_Log
A1: 04 | Activity Log
A2: All daily events: lead created, first reply, MQL, demo/quote, payment.
A4: Event Date | B4: Event Timestamp | C4: Lead ID | D4: Event Type | E4: Channel | F4: Owner | G4: Campaign Name | H4: Ad Set Name | I4: Ad Name | J4: Event Notes | K4: Outcome
A5: 46113 | B5: 46113.41 | C5: L-00001 | D5: Lead Created | E5: Phone Call | F5: Mona | G5: Mofawtar - E-Receipt - Awareness - Q2 | H5: Mofawtar - E-Receipt - Awareness - Q2 | Interest Tax Owners | I5: Demo Reel | Interest Tax Owners | J5: Inbound prospect created | K5: Completed
A6: 46113 | B6: 46113.732 | C6: L-00001 | D6: First Reply | E6: Phone Call | F6: Mona | G6: Mofawtar - E-Receipt - Awareness - Q2 | H6: Mofawtar - E-Receipt - Awareness - Q2 | Interest Tax Owners | I6: Demo Reel | Interest Tax Owners | J6: Sales agent replied | K6: Completed
A7: 46113 | B7: 46113.433 | C7: L-00002 | D7: Lead Created | E7: WhatsApp | F7: Youssef | G7: In2out - MessCampaign#1 - Testing - 15/4 | H7: In2out - MessCampaign#1 - Testing - 15/4 | Broad SMEs | I7: Demo Reel | Broad SMEs | J7: Inbound prospect created | K7: Completed
A8: 46113 | B8: 46113.698 | C8: L-00002 | D8: First Reply | E8: WhatsApp | F8: Youssef | G8: In2out - MessCampaign#1 - Testing - 15/4 | H8: In2out - MessCampaign#1 - Testing - 15/4 | Broad SMEs | I8: Demo Reel | Broad SMEs | J8: Sales agent replied | K8: Completed
A9: 46113 | B9: 46113.483 | C9: L-00003 | D9: Lead Created | E9: WhatsApp | F9: Salma | G9: In2out - MessCampaign#1 - Testing - 15/4 | H9: In2out - MessCampaign#1 - Testing - 15/4 | Broad SMEs | I9: Pain Point Static | Broad SMEs | J9: Inbound prospect created | K9: Completed
A10: 46113 | B10: 46113.494 | C10: L-00003 | D10: First Reply | E10: WhatsApp | F10: Salma | G10: In2out - MessCampaign#1 - Testing - 15/4 | H10: In2out - MessCampaign#1 - Testing - 15/4 | Broad SMEs | I10: Pain Point Static | Broad SMEs | J10: Sales agent replied | K10: Completed
A11: 46113 | B11: 46113.607 | C11: L-00004 | D11: Lead Created | E11: WhatsApp | F11: Mona | G11: Mofawtar - Tax Invoice - Lead Gen - Q2 | H11: Mofawtar - Tax Invoice - Lead Gen - Q2 | Interest Tax Owners | I11: Demo Reel | Interest Tax Owners | J11: Inbound prospect created | K11: Completed
A12: 46113 | B12: 46113.839 | C12: L-00004 | D12: First Reply | E12: WhatsApp | F12: Mona | G12: Mofawtar - Tax Invoice - Lead Gen - Q2 | H12: Mofawtar - Tax Invoice - Lead Gen - Q2 | Interest Tax Owners | I12: Demo Reel | Interest Tax Owners | J12: Sales agent replied | K12: Completed
A13: 46113 | B13: 46113.871 | C13: L-00005 | D13: Lead Created | E13: Instagram DM | F13: Kareem | G13: Mofawtar - Retargeting - Demo Booking - Q2 | H13: Mofawtar - Retargeting - Demo Booking - Q2 | Retargeting Visitors | I13: Pain Point Static | Retargeting Visitors | J13: Inbound prospect created | K13: Completed
A14: 46114 | B14: 46114.031 | C14: L-00005 | D14: First Reply | E14: Instagram DM | F14: Kareem | G14: Mofawtar - Retargeting - Demo Booking - Q2 | H14: Mofawtar - Retargeting - Demo Booking - Q2 | Retargeting Visitors | I14: Pain Point Static | Retargeting Visitors | J14: Sales agent replied | K14: Completed
A15: 46113 | B15: 46113.836 | C15: L-00006 | D15: Lead Created | E15: Website Form | F15: Mona | G15: In2out - MessCampaign#1 - Testing - 15/4 | H15: In2out - MessCampaign#1 - Testing - 15/4 | Broad SMEs | I15: Offer Carousel | Broad SMEs | J15: Inbound prospect created | K15: Completed
A16: 46113 | B16: 46113.894 | C16: L-00006 | D16: First Reply | E16: Website Form | F16: Mona | G16: In2out - MessCampaign#1 - Testing - 15/4 | H16: In2out - MessCampaign#1 - Testing - 15/4 | Broad SMEs | I16: Offer Carousel | Broad SMEs | J16: Sales agent replied | K16: Completed
... A6545: 46208 | B6545: 46208.041 | C6545: L-02598 | D6545: Demo Booked | E6545: WhatsApp | F6545: Ahmed | G6545: In2out - MessCampaign#2 - Testing - 20/4 | H6545: In2out - MessCampaign#2 - Testing - 20/4 | Broad SMEs | I6545: Pain Point Static | Broad SMEs | J6545: Sales opportunity created | K6545: Completed

Sheet 05_Daily_Funnel
A1: 05 | Daily Funnel
A2: Daily operational KPIs for every day in the quarter.
A4: Date | B4: Day | C4: Spend | D4: Conversations | E4: CRM Leads | F4: MQL | G4: SQL | H4: Deals Won | I4: Deals Lost | J4: Revenue | K4: CPL | L4: Cost/MQL | M4: Cost/SQL | N4: CAC | O4: ROAS | P4: Reply Rate | Q4: SLA Met %
A5: 46113 | B5: Wed | C5: =SUMIFS('02_Meta_Raw_Data'!$J:$J,'02_Meta_Raw_Data'!$A:$A,$A5) | D5: =SUMIFS('02_Meta_Raw_Data'!$P:$P,'02_Meta_Raw_Data'!$A:$A,$A5) | E5: =COUNTIFS('03_Prospects_CRM'!$B:$B,$A5) | F5: =COUNTIFS('03_Prospects_CRM'!$B:$B,$A5,'03_Prospects_CRM'!$T:$T,"MQL")+COUNTIFS('03_Prospects_CRM'!$B:$B,$A5,'03_Prospects_CRM'!$T:$T,"SQL")+COUNTIFS('03_Prospects_CRM'!$B:$B,$A5,'03_Prospects_CRM'!$T:$T,"Deal Won") | G5: =COUNTIFS('03_Prospects_CRM'!$B:$B,$A5,'03_Prospects_CRM'!$T:$T,"SQL")+COUNTIFS('03_Prospects_CRM'!$B:$B,$A5,'03_Prospects_CRM'!$T:$T,"Deal Won") | H5: =COUNTIFS('03_Prospects_CRM'!$B:$B,$A5,'03_Prospects_CRM'!$T:$T,"Deal Won") | I5: =COUNTIFS('03_Prospects_CRM'!$B:$B,$A5,'03_Prospects_CRM'!$T:$T,"Deal Lost") | J5: =SUMIFS('03_Prospects_CRM'!$X:$X,'03_Prospects_CRM'!$B:$B,$A5) | K5: =IFERROR(C5/E5,0) | L5: =IFERROR(C5/F5,0) | M5: =IFERROR(C5/G5,0) | N5: =IFERROR(C5/H5,0) | O5: =IFERROR(J5/C5,0) | P5: =IFERROR(SUMIFS('02_Meta_Raw_Data'!$T:$T,'02_Meta_Raw_Data'!$A:$A,$A5)/D5,0) | Q5: =IFERROR(COUNTIFS('03_Prospects_CRM'!$B:$B,$A5,'03_Prospects_CRM'!$AD:$AD,"Yes")/E5,0)
A6: 46114 | B6: Thu | C6: =SUMIFS('02_Meta_Raw_Data'!$J:$J,'02_Meta_Raw_Data'!$A:$A,$A6) | D6: =SUMIFS('02_Meta_Raw_Data'!$P:$P,'02_Meta_Raw_Data'!$A:$A,$A6) | E6: =COUNTIFS('03_Prospects_CRM'!$B:$B,$A6) | F6: =COUNTIFS('03_Prospects_CRM'!$B:$B,$A6,'03_Prospects_CRM'!$T:$T,"MQL")+COUNTIFS('03_Prospects_CRM'!$B:$B,$A6,'03_Prospects_CRM'!$T:$T,"SQL")+COUNTIFS('03_Prospects_CRM'!$B:$B,$A6,'03_Prospects_CRM'!$T:$T,"Deal Won") | G6: =COUNTIFS('03_Prospects_CRM'!$B:$B,$A6,'03_Prospects_CRM'!$T:$T,"SQL")+COUNTIFS('03_Prospects_CRM'!$B:$B,$A6,'03_Prospects_CRM'!$T:$T,"Deal Won") | H6: =COUNTIFS('03_Prospects_CRM'!$B:$B,$A6,'03_Prospects_CRM'!$T:$T,"Deal Won") | I6: =COUNTIFS('03_Prospects_CRM'!$B:$B,$A6,'03_Prospects_CRM'!$T:$T,"Deal Lost") | J6: =SUMIFS('03_Prospects_CRM'!$X:$X,'03_Prospects_CRM'!$B:$B,$A6) | K6: =IFERROR(C6/E6,0) | L6: =IFERROR(C6/F6,0) | M6: =IFERROR(C6/G6,0) | N6: =IFERROR(C6/H6,0) | O6: =IFERROR(J6/C6,0) | P6: =IFERROR(SUMIFS('02_Meta_Raw_Data'!$T:$T,'02_Meta_Raw_Data'!$A:$A,$A6)/D6,0) | Q6: =IFERROR(COUNTIFS('03_Prospects_CRM'!$B:$B,$A6,'03_Prospects_CRM'!$AD:$AD,"Yes")/E6,0)
A7: 46115 | B7: Fri | C7: =SUMIFS('02_Meta_Raw_Data'!$J:$J,'02_Meta_Raw_Data'!$A:$A,$A7) | D7: =SUMIFS('02_Meta_Raw_Data'!$P:$P,'02_Meta_Raw_Data'!$A:$A,$A7) | E7: =COUNTIFS('03_Prospects_CRM'!$B:$B,$A7) | F7: =COUNTIFS('03_Prospects_CRM'!$B:$B,$A7,'03_Prospects_CRM'!$T:$T,"MQL")+COUNTIFS('03_Prospects_CRM'!$B:$B,$A7,'03_Prospects_CRM'!$T:$T,"SQL")+COUNTIFS('03_Prospects_CRM'!$B:$B,$A7,'03_Prospects_CRM'!$T:$T,"Deal Won") | G7: =COUNTIFS('03_Prospects_CRM'!$B:$B,$A7,'03_Prospects_CRM'!$T:$T,"SQL")+COUNTIFS('03_Prospects_CRM'!$B:$B,$A7,'03_Prospects_CRM'!$T:$T,"Deal Won") | H7: =COUNTIFS('03_Prospects_CRM'!$B:$B,$A7,'03_Prospects_CRM'!$T:$T,"Deal Won") | I7: =COUNTIFS('03_Prospects_CRM'!$B:$B,$A7,'03_Prospects_CRM'!$T:$T,"Deal Lost") | J7: =SUMIFS('03_Prospects_CRM'!$X:$X,'03_Prospects_CRM'!$B:$B,$A7) | K7: =IFERROR(C7/E7,0) | L7: =IFERROR(C7/F7,0) | M7: =IFERROR(C7/G7,0) | N7: =IFERROR(C7/H7,0) | O7: =IFERROR(J7/C7,0) | P7: =IFERROR(SUMIFS('02_Meta_Raw_Data'!$T:$T,'02_Meta_Raw_Data'!$A:$A,$A7)/D7,0) | Q7: =IFERROR(COUNTIFS('03_Prospects_CRM'!$B:$B,$A7,'03_Prospects_CRM'!$AD:$AD,"Yes")/E7,0)
A8: 46116 | B8: Sat | C8: =SUMIFS('02_Meta_Raw_Data'!$J:$J,'02_Meta_Raw_Data'!$A:$A,$A8) | D8: =SUMIFS('02_Meta_Raw_Data'!$P:$P,'02_Meta_Raw_Data'!$A:$A,$A8) | E8: =COUNTIFS('03_Prospects_CRM'!$B:$B,$A8) | F8: =COUNTIFS('03_Prospects_CRM'!$B:$B,$A8,'03_Prospects_CRM'!$T:$T,"MQL")+COUNTIFS('03_Prospects_CRM'!$B:$B,$A8,'03_Prospects_CRM'!$T:$T,"SQL")+COUNTIFS('03_Prospects_CRM'!$B:$B,$A8,'03_Prospects_CRM'!$T:$T,"Deal Won") | G8: =COUNTIFS('03_Prospects_CRM'!$B:$B,$A8,'03_Prospects_CRM'!$T:$T,"SQL")+COUNTIFS('03_Prospects_CRM'!$B:$B,$A8,'03_Prospects_CRM'!$T:$T,"Deal Won") | H8: =COUNTIFS('03_Prospects_CRM'!$B:$B,$A8,'03_Prospects_CRM'!$T:$T,"Deal Won") | I8: =COUNTIFS('03_Prospects_CRM'!$B:$B,$A8,'03_Prospects_CRM'!$T:$T,"Deal Lost") | J8: =SUMIFS('03_Prospects_CRM'!$X:$X,'03_Prospects_CRM'!$B:$B,$A8) | K8: =IFERROR(C8/E8,0) | L8: =IFERROR(C8/F8,0) | M8: =IFERROR(C8/G8,0) | N8: =IFERROR(C8/H8,0) | O8: =IFERROR(J8/C8,0) | P8: =IFERROR(SUMIFS('02_Meta_Raw_Data'!$T:$T,'02_Meta_Raw_Data'!$A:$A,$A8)/D8,0) | Q8: =IFERROR(COUNTIFS('03_Prospects_CRM'!$B:$B,$A8,'03_Prospects_CRM'!$AD:$AD,"Yes")/E8,0)
A9: 46117 | B9: Sun | C9: =SUMIFS('02_Meta_Raw_Data'!$J:$J,'02_Meta_Raw_Data'!$A:$A,$A9) | D9: =SUMIFS('02_Meta_Raw_Data'!$P:$P,'02_Meta_Raw_Data'!$A:$A,$A9) | E9: =COUNTIFS('03_Prospects_CRM'!$B:$B,$A9) | F9: =COUNTIFS('03_Prospects_CRM'!$B:$B,$A9,'03_Prospects_CRM'!$T:$T,"MQL")+COUNTIFS('03_Prospects_CRM'!$B:$B,$A9,'03_Prospects_CRM'!$T:$T,"SQL")+COUNTIFS('03_Prospects_CRM'!$B:$B,$A9,'03_Prospects_CRM'!$T:$T,"Deal Won") | G9: =COUNTIFS('03_Prospects_CRM'!$B:$B,$A9,'03_Prospects_CRM'!$T:$T,"SQL")+COUNTIFS('03_Prospects_CRM'!$B:$B,$A9,'03_Prospects_CRM'!$T:$T,"Deal Won") | H9: =COUNTIFS('03_Prospects_CRM'!$B:$B,$A9,'03_Prospects_CRM'!$T:$T,"Deal Won") | I9: =COUNTIFS('03_Prospects_CRM'!$B:$B,$A9,'03_Prospects_CRM'!$T:$T,"Deal Lost") | J9: =SUMIFS('03_Prospects_CRM'!$X:$X,'03_Prospects_CRM'!$B:$B,$A9) | K9: =IFERROR(C9/E9,0) | L9: =IFERROR(C9/F9,0) | M9: =IFERROR(C9/G9,0) | N9: =IFERROR(C9/H9,0) | O9: =IFERROR(J9/C9,0) | P9: =IFERROR(SUMIFS('02_Meta_Raw_Data'!$T:$T,'02_Meta_Raw_Data'!$A:$A,$A9)/D9,0) | Q9: =IFERROR(COUNTIFS('03_Prospects_CRM'!$B:$B,$A9,'03_Prospects_CRM'!$AD:$AD,"Yes")/E9,0)
A10: 46118 | B10: Mon | C10: =SUMIFS('02_Meta_Raw_Data'!$J:$J,'02_Meta_Raw_Data'!$A:$A,$A10) | D10: =SUMIFS('02_Meta_Raw_Data'!$P:$P,'02_Meta_Raw_Data'!$A:$A,$A10) | E10: =COUNTIFS('03_Prospects_CRM'!$B:$B,$A10) | F10: =COUNTIFS('03_Prospects_CRM'!$B:$B,$A10,'03_Prospects_CRM'!$T:$T,"MQL")+COUNTIFS('03_Prospects_CRM'!$B:$B,$A10,'03_Prospects_CRM'!$T:$T,"SQL")+COUNTIFS('03_Prospects_CRM'!$B:$B,$A10,'03_Prospects_CRM'!$T:$T,"Deal Won") | G10: =COUNTIFS('03_Prospects_CRM'!$B:$B,$A10,'03_Prospects_CRM'!$T:$T,"SQL")+COUNTIFS('03_Prospects_CRM'!$B:$B,$A10,'03_Prospects_CRM'!$T:$T,"Deal Won") | H10: =COUNTIFS('03_Prospects_CRM'!$B:$B,$A10,'03_Prospects_CRM'!$T:$T,"Deal Won") | I10: =COUNTIFS('03_Prospects_CRM'!$B:$B,$A10,'03_Prospects_CRM'!$T:$T,"Deal Lost") | J10: =SUMIFS('03_Prospects_CRM'!$X:$X,'03_Prospects_CRM'!$B:$B,$A10) | K10: =IFERROR(C10/E10,0) | L10: =IFERROR(C10/F10,0) | M10: =IFERROR(C10/G10,0) | N10: =IFERROR(C10/H10,0) | O10: =IFERROR(J10/C10,0) | P10: =IFERROR(SUMIFS('02_Meta_Raw_Data'!$T:$T,'02_Meta_Raw_Data'!$A:$A,$A10)/D10,0) | Q10: =IFERROR(COUNTIFS('03_Prospects_CRM'!$B:$B,$A10,'03_Prospects_CRM'!$AD:$AD,"Yes")/E10,0)
A11: 46119 | B11: Tue | C11: =SUMIFS('02_Meta_Raw_Data'!$J:$J,'02_Meta_Raw_Data'!$A:$A,$A11) | D11: =SUMIFS('02_Meta_Raw_Data'!$P:$P,'02_Meta_Raw_Data'!$A:$A,$A11) | E11: =COUNTIFS('03_Prospects_CRM'!$B:$B,$A11) | F11: =COUNTIFS('03_Prospects_CRM'!$B:$B,$A11,'03_Prospects_CRM'!$T:$T,"MQL")+COUNTIFS('03_Prospects_CRM'!$B:$B,$A11,'03_Prospects_CRM'!$T:$T,"SQL")+COUNTIFS('03_Prospects_CRM'!$B:$B,$A11,'03_Prospects_CRM'!$T:$T,"Deal Won") | G11: =COUNTIFS('03_Prospects_CRM'!$B:$B,$A11,'03_Prospects_CRM'!$T:$T,"SQL")+COUNTIFS('03_Prospects_CRM'!$B:$B,$A11,'03_Prospects_CRM'!$T:$T,"Deal Won") | H11: =COUNTIFS('03_Prospects_CRM'!$B:$B,$A11,'03_Prospects_CRM'!$T:$T,"Deal Won") | I11: =COUNTIFS('03_Prospects_CRM'!$B:$B,$A11,'03_Prospects_CRM'!$T:$T,"Deal Lost") | J11: =SUMIFS('03_Prospects_CRM'!$X:$X,'03_Prospects_CRM'!$B:$B,$A11) | K11: =IFERROR(C11/E11,0) | L11: =IFERROR(C11/F11,0) | M11: =IFERROR(C11/G11,0) | N11: =IFERROR(C11/H11,0) | O11: =IFERROR(J11/C11,0) | P11: =IFERROR(SUMIFS('02_Meta_Raw_Data'!$T:$T,'02_Meta_Raw_Data'!$A:$A,$A11)/D11,0) | Q11: =IFERROR(COUNTIFS('03_Prospects_CRM'!$B:$B,$A11,'03_Prospects_CRM'!$AD:$AD,"Yes")/E11,0)
A12: 46120 | B12: Wed | C12: =SUMIFS('02_Meta_Raw_Data'!$J:$J,'02_Meta_Raw_Data'!$A:$A,$A12) | D12: =SUMIFS('02_Meta_Raw_Data'!$P:$P,'02_Meta_Raw_Data'!$A:$A,$A12) | E12: =COUNTIFS('03_Prospects_CRM'!$B:$B,$A12) | F12: =COUNTIFS('03_Prospects_CRM'!$B:$B,$A12,'03_Prospects_CRM'!$T:$T,"MQL")+COUNTIFS('03_Prospects_CRM'!$B:$B,$A12,'03_Prospects_CRM'!$T:$T,"SQL")+COUNTIFS('03_Prospects_CRM'!$B:$B,$A12,'03_Prospects_CRM'!$T:$T,"Deal Won") | G12: =COUNTIFS('03_Prospects_CRM'!$B:$B,$A12,'03_Prospects_CRM'!$T:$T,"SQL")+COUNTIFS('03_Prospects_CRM'!$B:$B,$A12,'03_Prospects_CRM'!$T:$T,"Deal Won") | H12: =COUNTIFS('03_Prospects_CRM'!$B:$B,$A12,'03_Prospects_CRM'!$T:$T,"Deal Won") | I12: =COUNTIFS('03_Prospects_CRM'!$B:$B,$A12,'03_Prospects_CRM'!$T:$T,"Deal Lost") | J12: =SUMIFS('03_Prospects_CRM'!$X:$X,'03_Prospects_CRM'!$B:$B,$A12) | K12: =IFERROR(C12/E12,0) | L12: =IFERROR(C12/F12,0) | M12: =IFERROR(C12/G12,0) | N12: =IFERROR(C12/H12,0) | O12: =IFERROR(J12/C12,0) | P12: =IFERROR(SUMIFS('02_Meta_Raw_Data'!$T:$T,'02_Meta_Raw_Data'!$A:$A,$A12)/D12,0) | Q12: =IFERROR(COUNTIFS('03_Prospects_CRM'!$B:$B,$A12,'03_Prospects_CRM'!$AD:$AD,"Yes")/E12,0)
A13: 46121 | B13: Thu | C13: =SUMIFS('02_Meta_Raw_Data'!$J:$J,'02_Meta_Raw_Data'!$A:$A,$A13) | D13: =SUMIFS('02_Meta_Raw_Data'!$P:$P,'02_Meta_Raw_Data'!$A:$A,$A13) | E13: =COUNTIFS('03_Prospects_CRM'!$B:$B,$A13) | F13: =COUNTIFS('03_Prospects_CRM'!$B:$B,$A13,'03_Prospects_CRM'!$T:$T,"MQL")+COUNTIFS('03_Prospects_CRM'!$B:$B,$A13,'03_Prospects_CRM'!$T:$T,"SQL")+COUNTIFS('03_Prospects_CRM'!$B:$B,$A13,'03_Prospects_CRM'!$T:$T,"Deal Won") | G13: =COUNTIFS('03_Prospects_CRM'!$B:$B,$A13,'03_Prospects_CRM'!$T:$T,"SQL")+COUNTIFS('03_Prospects_CRM'!$B:$B,$A13,'03_Prospects_CRM'!$T:$T,"Deal Won") | H13: =COUNTIFS('03_Prospects_CRM'!$B:$B,$A13,'03_Prospects_CRM'!$T:$T,"Deal Won") | I13: =COUNTIFS('03_Prospects_CRM'!$B:$B,$A13,'03_Prospects_CRM'!$T:$T,"Deal Lost") | J13: =SUMIFS('03_Prospects_CRM'!$X:$X,'03_Prospects_CRM'!$B:$B,$A13) | K13: =IFERROR(C13/E13,0) | L13: =IFERROR(C13/F13,0) | M13: =IFERROR(C13/G13,0) | N13: =IFERROR(C13/H13,0) | O13: =IFERROR(J13/C13,0) | P13: =IFERROR(SUMIFS('02_Meta_Raw_Data'!$T:$T,'02_Meta_Raw_Data'!$A:$A,$A13)/D13,0) | Q13: =IFERROR(COUNTIFS('03_Prospects_CRM'!$B:$B,$A13,'03_Prospects_CRM'!$AD:$AD,"Yes")/E13,0)
A14: 46122 | B14: Fri | C14: =SUMIFS('02_Meta_Raw_Data'!$J:$J,'02_Meta_Raw_Data'!$A:$A,$A14) | D14: =SUMIFS('02_Meta_Raw_Data'!$P:$P,'02_Meta_Raw_Data'!$A:$A,$A14) | E14: =COUNTIFS('03_Prospects_CRM'!$B:$B,$A14) | F14: =COUNTIFS('03_Prospects_CRM'!$B:$B,$A14,'03_Prospects_CRM'!$T:$T,"MQL")+COUNTIFS('03_Prospects_CRM'!$B:$B,$A14,'03_Prospects_CRM'!$T:$T,"SQL")+COUNTIFS('03_Prospects_CRM'!$B:$B,$A14,'03_Prospects_CRM'!$T:$T,"Deal Won") | G14: =COUNTIFS('03_Prospects_CRM'!$B:$B,$A14,'03_Prospects_CRM'!$T:$T,"SQL")+COUNTIFS('03_Prospects_CRM'!$B:$B,$A14,'03_Prospects_CRM'!$T:$T,"Deal Won") | H14: =COUNTIFS('03_Prospects_CRM'!$B:$B,$A14,'03_Prospects_CRM'!$T:$T,"Deal Won") | I14: =COUNTIFS('03_Prospects_CRM'!$B:$B,$A14,'03_Prospects_CRM'!$T:$T,"Deal Lost") | J14: =SUMIFS('03_Prospects_CRM'!$X:$X,'03_Prospects_CRM'!$B:$B,$A14) | K14: =IFERROR(C14/E14,0) | L14: =IFERROR(C14/F14,0) | M14: =IFERROR(C14/G14,0) | N14: =IFERROR(C14/H14,0) | O14: =IFERROR(J14/C14,0) | P14: =IFERROR(SUMIFS('02_Meta_Raw_Data'!$T:$T,'02_Meta_Raw_Data'!$A:$A,$A14)/D14,0) | Q14: =IFERROR(COUNTIFS('03_Prospects_CRM'!$B:$B,$A14,'03_Prospects_CRM'!$AD:$AD,"Yes")/E14,0)
A15: 46123 | B15: Sat | C15: =SUMIFS('02_Meta_Raw_Data'!$J:$J,'02_Meta_Raw_Data'!$A:$A,$A15) | D15: =SUMIFS('02_Meta_Raw_Data'!$P:$P,'02_Meta_Raw_Data'!$A:$A,$A15) | E15: =COUNTIFS('03_Prospects_CRM'!$B:$B,$A15) | F15: =COUNTIFS('03_Prospects_CRM'!$B:$B,$A15,'03_Prospects_CRM'!$T:$T,"MQL")+COUNTIFS('03_Prospects_CRM'!$B:$B,$A15,'03_Prospects_CRM'!$T:$T,"SQL")+COUNTIFS('03_Prospects_CRM'!$B:$B,$A15,'03_Prospects_CRM'!$T:$T,"Deal Won") | G15: =COUNTIFS('03_Prospects_CRM'!$B:$B,$A15,'03_Prospects_CRM'!$T:$T,"SQL")+COUNTIFS('03_Prospects_CRM'!$B:$B,$A15,'03_Prospects_CRM'!$T:$T,"Deal Won") | H15: =COUNTIFS('03_Prospects_CRM'!$B:$B,$A15,'03_Prospects_CRM'!$T:$T,"Deal Won") | I15: =COUNTIFS('03_Prospects_CRM'!$B:$B,$A15,'03_Prospects_CRM'!$T:$T,"Deal Lost") | J15: =SUMIFS('03_Prospects_CRM'!$X:$X,'03_Prospects_CRM'!$B:$B,$A15) | K15: =IFERROR(C15/E15,0) | L15: =IFERROR(C15/F15,0) | M15: =IFERROR(C15/G15,0) | N15: =IFERROR(C15/H15,0) | O15: =IFERROR(J15/C15,0) | P15: =IFERROR(SUMIFS('02_Meta_Raw_Data'!$T:$T,'02_Meta_Raw_Data'!$A:$A,$A15)/D15,0) | Q15: =IFERROR(COUNTIFS('03_Prospects_CRM'!$B:$B,$A15,'03_Prospects_CRM'!$AD:$AD,"Yes")/E15,0)
A16: 46124 | B16: Sun | C16: =SUMIFS('02_Meta_Raw_Data'!$J:$J,'02_Meta_Raw_Data'!$A:$A,$A16) | D16: =SUMIFS('02_Meta_Raw_Data'!$P:$P,'02_Meta_Raw_Data'!$A:$A,$A16) | E16: =COUNTIFS('03_Prospects_CRM'!$B:$B,$A16) | F16: =COUNTIFS('03_Prospects_CRM'!$B:$B,$A16,'03_Prospects_CRM'!$T:$T,"MQL")+COUNTIFS('03_Prospects_CRM'!$B:$B,$A16,'03_Prospects_CRM'!$T:$T,"SQL")+COUNTIFS('03_Prospects_CRM'!$B:$B,$A16,'03_Prospects_CRM'!$T:$T,"Deal Won") | G16: =COUNTIFS('03_Prospects_CRM'!$B:$B,$A16,'03_Prospects_CRM'!$T:$T,"SQL")+COUNTIFS('03_Prospects_CRM'!$B:$B,$A16,'03_Prospects_CRM'!$T:$T,"Deal Won") | H16: =COUNTIFS('03_Prospects_CRM'!$B:$B,$A16,'03_Prospects_CRM'!$T:$T,"Deal Won") | I16: =COUNTIFS('03_Prospects_CRM'!$B:$B,$A16,'03_Prospects_CRM'!$T:$T,"Deal Lost") | J16: =SUMIFS('03_Prospects_CRM'!$X:$X,'03_Prospects_CRM'!$B:$B,$A16) | K16: =IFERROR(C16/E16,0) | L16: =IFERROR(C16/F16,0) | M16: =IFERROR(C16/G16,0) | N16: =IFERROR(C16/H16,0) | O16: =IFERROR(J16/C16,0) | P16: =IFERROR(SUMIFS('02_Meta_Raw_Data'!$T:$T,'02_Meta_Raw_Data'!$A:$A,$A16)/D16,0) | Q16: =IFERROR(COUNTIFS('03_Prospects_CRM'!$B:$B,$A16,'03_Prospects_CRM'!$AD:$AD,"Yes")/E16,0)
... A95: 46203 | B95: Tue | C95: =SUMIFS('02_Meta_Raw_Data'!$J:$J,'02_Meta_Raw_Data'!$A:$A,$A95) | D95: =SUMIFS('02_Meta_Raw_Data'!$P:$P,'02_Meta_Raw_Data'!$A:$A,$A95) | E95: =COUNTIFS('03_Prospects_CRM'!$B:$B,$A95) | F95: =COUNTIFS('03_Prospects_CRM'!$B:$B,$A95,'03_Prospects_CRM'!$T:$T,"MQL")+COUNTIFS('03_Prospects_CRM'!$B:$B,$A95,'03_Prospects_CRM'!$T:$T,"SQL")+COUNTIFS('03_Prospects_CRM'!$B:$B,$A95,'03_Prospects_CRM'!$T:$T,"Deal Won") | G95: =COUNTIFS('03_Prospects_CRM'!$B:$B,$A95,'03_Prospects_CRM'!$T:$T,"SQL")+COUNTIFS('03_Prospects_CRM'!$B:$B,$A95,'03_Prospects_CRM'!$T:$T,"Deal Won") | H95: =COUNTIFS('03_Prospects_CRM'!$B:$B,$A95,'03_Prospects_CRM'!$T:$T,"Deal Won") | I95: =COUNTIFS('03_Prospects_CRM'!$B:$B,$A95,'03_Prospects_CRM'!$T:$T,"Deal Lost") | J95: =SUMIFS('03_Prospects_CRM'!$X:$X,'03_Prospects_CRM'!$B:$B,$A95) | K95: =IFERROR(C95/E95,0) | L95: =IFERROR(C95/F95,0) | M95: =IFERROR(C95/G95,0) | N95: =IFERROR(C95/H95,0) | O95: =IFERROR(J95/C95,0) | P95: =IFERROR(SUMIFS('02_Meta_Raw_Data'!$T:$T,'02_Meta_Raw_Data'!$A:$A,$A95)/D95,0) | Q95: =IFERROR(COUNTIFS('03_Prospects_CRM'!$B:$B,$A95,'03_Prospects_CRM'!$AD:$AD,"Yes")/E95,0)

Sheet 06_Merged_Performance
A1: 06 | Merged Performance
A2: Daily/ad-level merged performance with Meta cost and CRM outcomes.
A4: Date | B4: Campaign ID | C4: Campaign Name | D4: Ad Set ID | E4: Ad Set Name | F4: Ad ID | G4: Ad Name | H4: Spend | I4: Conversations | J4: CRM Leads | K4: MQL | L4: SQL | M4: Deals Won | N4: Deals Lost | O4: Revenue | P4: CPL | Q4: Cost/MQL | R4: Cost/SQL | S4: CAC | T4: ROAS
A5: 46113 | B5: CMP-001 | C5: In2out - MessCampaign#1 - Testing - 15/4 | D5: AS-0101 | E5: In2out - MessCampaign#1 - Testing - 15/4 | Broad SMEs | F5: AD-010101 | G5: Pain Point Static | Broad SMEs | H5: 263.21 | I5: 37 | J5: 2 | K5: 0 | L5: 0 | M5: 0 | N5: 1 | O5: 0 | P5: 131.6 | Q5: 0 | R5: 0 | S5: 0 | T5: 0
A6: 46113 | B6: CMP-001 | C6: In2out - MessCampaign#1 - Testing - 15/4 | D6: AS-0101 | E6: In2out - MessCampaign#1 - Testing - 15/4 | Broad SMEs | F6: AD-010102 | G6: Demo Reel | Broad SMEs | H6: 166.01 | I6: 15 | J6: 2 | K6: 0 | L6: 0 | M6: 0 | N6: 1 | O6: 0 | P6: 83 | Q6: 0 | R6: 0 | S6: 0 | T6: 0
A7: 46113 | B7: CMP-001 | C7: In2out - MessCampaign#1 - Testing - 15/4 | D7: AS-0101 | E7: In2out - MessCampaign#1 - Testing - 15/4 | Broad SMEs | F7: AD-010103 | G7: Offer Carousel | Broad SMEs | H7: 301.64 | I7: 29 | J7: 1 | K7: 0 | L7: 0 | M7: 0 | N7: 0 | O7: 0 | P7: 301.64 | Q7: 0 | R7: 0 | S7: 0 | T7: 0
A8: 46113 | B8: CMP-001 | C8: In2out - MessCampaign#1 - Testing - 15/4 | D8: AS-0102 | E8: In2out - MessCampaign#1 - Testing - 15/4 | Interest Tax Owners | F8: AD-010201 | G8: Pain Point Static | Interest Tax Owners | H8: 301.95 | I8: 39 | J8: 2 | K8: 0 | L8: 0 | M8: 0 | N8: 0 | O8: 0 | P8: 150.97 | Q8: 0 | R8: 0 | S8: 0 | T8: 0
A9: 46113 | B9: CMP-001 | C9: In2out - MessCampaign#1 - Testing - 15/4 | D9: AS-0102 | E9: In2out - MessCampaign#1 - Testing - 15/4 | Interest Tax Owners | F9: AD-010202 | G9: Demo Reel | Interest Tax Owners | H9: 278.26 | I9: 22 | J9: 0 | K9: 0 | L9: 0 | M9: 0 | N9: 0 | O9: 0 | P9: 0 | Q9: 0 | R9: 0 | S9: 0 | T9: 0
A10: 46113 | B10: CMP-002 | C10: In2out - MessCampaign#2 - Testing - 20/4 | D10: AS-0201 | E10: In2out - MessCampaign#2 - Testing - 20/4 | Broad SMEs | F10: AD-020101 | G10: Pain Point Static | Broad SMEs | H10: 201.01 | I10: 30 | J10: 2 | K10: 0 | L10: 0 | M10: 0 | N10: 0 | O10: 0 | P10: 100.5 | Q10: 0 | R10: 0 | S10: 0 | T10: 0
A11: 46113 | B11: CMP-002 | C11: In2out - MessCampaign#2 - Testing - 20/4 | D11: AS-0201 | E11: In2out - MessCampaign#2 - Testing - 20/4 | Broad SMEs | F11: AD-020102 | G11: Demo Reel | Broad SMEs | H11: 344.08 | I11: 37 | J11: 1 | K11: 0 | L11: 0 | M11: 0 | N11: 0 | O11: 0 | P11: 344.08 | Q11: 0 | R11: 0 | S11: 0 | T11: 0
A12: 46113 | B12: CMP-002 | C12: In2out - MessCampaign#2 - Testing - 20/4 | D12: AS-0201 | E12: In2out - MessCampaign#2 - Testing - 20/4 | Broad SMEs | F12: AD-020103 | G12: Offer Carousel | Broad SMEs | H12: 164.24 | I12: 9 | J12: 4 | K12: 1 | L12: 0 | M12: 0 | N12: 0 | O12: 0 | P12: 41.06 | Q12: 164.24 | R12: 0 | S12: 0 | T12: 0
A13: 46113 | B13: CMP-002 | C13: In2out - MessCampaign#2 - Testing - 20/4 | D13: AS-0202 | E13: In2out - MessCampaign#2 - Testing - 20/4 | Interest Tax Owners | F13: AD-020201 | G13: Pain Point Static | Interest Tax Owners | H13: 245.18 | I13: 27 | J13: 0 | K13: 0 | L13: 0 | M13: 0 | N13: 0 | O13: 0 | P13: 0 | Q13: 0 | R13: 0 | S13: 0 | T13: 0
A14: 46113 | B14: CMP-002 | C14: In2out - MessCampaign#2 - Testing - 20/4 | D14: AS-0202 | E14: In2out - MessCampaign#2 - Testing - 20/4 | Interest Tax Owners | F14: AD-020202 | G14: Demo Reel | Interest Tax Owners | H14: 140.83 | I14: 5 | J14: 1 | K14: 0 | L14: 0 | M14: 0 | N14: 0 | O14: 0 | P14: 140.83 | Q14: 0 | R14: 0 | S14: 0 | T14: 0
A15: 46113 | B15: CMP-003 | C15: Mofawtar - E-Receipt - Awareness - Q2 | D15: AS-0301 | E15: Mofawtar - E-Receipt - Awareness - Q2 | Broad SMEs | F15: AD-030101 | G15: Pain Point Static | Broad SMEs | H15: 118.15 | I15: 7 | J15: 2 | K15: 0 | L15: 0 | M15: 0 | N15: 0 | O15: 0 | P15: 59.08 | Q15: 0 | R15: 0 | S15: 0 | T15: 0
A16: 46113 | B16: CMP-003 | C16: Mofawtar - E-Receipt - Awareness - Q2 | D16: AS-0301 | E16: Mofawtar - E-Receipt - Awareness - Q2 | Broad SMEs | F16: AD-030102 | G16: Demo Reel | Broad SMEs | H16: 317.82 | I16: 28 | J16: 0 | K16: 0 | L16: 0 | M16: 0 | N16: 0 | O16: 0 | P16: 0 | Q16: 0 | R16: 0 | S16: 0 | T16: 0
... A2643: 46203 | B2643: CMP-005 | C2643: Mofawtar - Retargeting - Demo Booking - Q2 | D2643: AS-0503 | E2643: Mofawtar - Retargeting - Demo Booking - Q2 | Retargeting Visitors | F2643: AD-050302 | G2643: Demo Reel | Retargeting Visitors | H2643: 247.03 | I2643: 30 | J2643: 0 | K2643: 0 | L2643: 0 | M2643: 0 | N2643: 0 | O2643: 0 | P2643: 0 | Q2643: 0 | R2643: 0 | S2643: 0 | T2643: 0

Sheet 07_Campaign_Summary
A1: 07 Campaign Summary
A2: Campaign rollup: cost, funnel and revenue.
A4: ID | B4: Name | C4: Spend | D4: Conversations | E4: CRM Leads | F4: MQL | G4: SQL | H4: Deals Won | I4: Deals Lost | J4: Revenue | K4: CPL | L4: Cost/MQL | M4: Cost/SQL | N4: CAC | O4: ROAS | P4: Lead→MQL | Q4: MQL→SQL | R4: SQL→Deal
A5: CMP-001 | B5: In2out - MessCampaign#1 - Testing - 15/4 | C5: =SUMIFS('02_Meta_Raw_Data'!$J:$J,'02_Meta_Raw_Data'!$B:$B,$A5) | D5: =SUMIFS('02_Meta_Raw_Data'!$P:$P,'02_Meta_Raw_Data'!$B:$B,$A5) | E5: =COUNTIFS('03_Prospects_CRM'!$L:$L,$A5) | F5: =COUNTIFS('03_Prospects_CRM'!$L:$L,$A5,'03_Prospects_CRM'!$T:$T,"MQL")+COUNTIFS('03_Prospects_CRM'!$L:$L,$A5,'03_Prospects_CRM'!$T:$T,"SQL")+COUNTIFS('03_Prospects_CRM'!$L:$L,$A5,'03_Prospects_CRM'!$T:$T,"Deal Won") | G5: =COUNTIFS('03_Prospects_CRM'!$L:$L,$A5,'03_Prospects_CRM'!$T:$T,"SQL")+COUNTIFS('03_Prospects_CRM'!$L:$L,$A5,'03_Prospects_CRM'!$T:$T,"Deal Won") | H5: =COUNTIFS('03_Prospects_CRM'!$L:$L,$A5,'03_Prospects_CRM'!$T:$T,"Deal Won") | I5: =COUNTIFS('03_Prospects_CRM'!$L:$L,$A5,'03_Prospects_CRM'!$T:$T,"Deal Lost") | J5: =SUMIFS('03_Prospects_CRM'!$X:$X,'03_Prospects_CRM'!$L:$L,$A5) | K5: =IFERROR(C5/E5,0) | L5: =IFERROR(C5/F5,0) | M5: =IFERROR(C5/G5,0) | N5: =IFERROR(C5/H5,0) | O5: =IFERROR(J5/C5,0) | P5: =IFERROR(F5/E5,0) | Q5: =IFERROR(G5/F5,0) | R5: =IFERROR(H5/G5,0)
A6: CMP-002 | B6: In2out - MessCampaign#2 - Testing - 20/4 | C6: =SUMIFS('02_Meta_Raw_Data'!$J:$J,'02_Meta_Raw_Data'!$B:$B,$A6) | D6: =SUMIFS('02_Meta_Raw_Data'!$P:$P,'02_Meta_Raw_Data'!$B:$B,$A6) | E6: =COUNTIFS('03_Prospects_CRM'!$L:$L,$A6) | F6: =COUNTIFS('03_Prospects_CRM'!$L:$L,$A6,'03_Prospects_CRM'!$T:$T,"MQL")+COUNTIFS('03_Prospects_CRM'!$L:$L,$A6,'03_Prospects_CRM'!$T:$T,"SQL")+COUNTIFS('03_Prospects_CRM'!$L:$L,$A6,'03_Prospects_CRM'!$T:$T,"Deal Won") | G6: =COUNTIFS('03_Prospects_CRM'!$L:$L,$A6,'03_Prospects_CRM'!$T:$T,"SQL")+COUNTIFS('03_Prospects_CRM'!$L:$L,$A6,'03_Prospects_CRM'!$T:$T,"Deal Won") | H6: =COUNTIFS('03_Prospects_CRM'!$L:$L,$A6,'03_Prospects_CRM'!$T:$T,"Deal Won") | I6: =COUNTIFS('03_Prospects_CRM'!$L:$L,$A6,'03_Prospects_CRM'!$T:$T,"Deal Lost") | J6: =SUMIFS('03_Prospects_CRM'!$X:$X,'03_Prospects_CRM'!$L:$L,$A6) | K6: =IFERROR(C6/E6,0) | L6: =IFERROR(C6/F6,0) | M6: =IFERROR(C6/G6,0) | N6: =IFERROR(C6/H6,0) | O6: =IFERROR(J6/C6,0) | P6: =IFERROR(F6/E6,0) | Q6: =IFERROR(G6/F6,0) | R6: =IFERROR(H6/G6,0)
A7: CMP-003 | B7: Mofawtar - E-Receipt - Awareness - Q2 | C7: =SUMIFS('02_Meta_Raw_Data'!$J:$J,'02_Meta_Raw_Data'!$B:$B,$A7) | D7: =SUMIFS('02_Meta_Raw_Data'!$P:$P,'02_Meta_Raw_Data'!$B:$B,$A7) | E7: =COUNTIFS('03_Prospects_CRM'!$L:$L,$A7) | F7: =COUNTIFS('03_Prospects_CRM'!$L:$L,$A7,'03_Prospects_CRM'!$T:$T,"MQL")+COUNTIFS('03_Prospects_CRM'!$L:$L,$A7,'03_Prospects_CRM'!$T:$T,"SQL")+COUNTIFS('03_Prospects_CRM'!$L:$L,$A7,'03_Prospects_CRM'!$T:$T,"Deal Won") | G7: =COUNTIFS('03_Prospects_CRM'!$L:$L,$A7,'03_Prospects_CRM'!$T:$T,"SQL")+COUNTIFS('03_Prospects_CRM'!$L:$L,$A7,'03_Prospects_CRM'!$T:$T,"Deal Won") | H7: =COUNTIFS('03_Prospects_CRM'!$L:$L,$A7,'03_Prospects_CRM'!$T:$T,"Deal Won") | I7: =COUNTIFS('03_Prospects_CRM'!$L:$L,$A7,'03_Prospects_CRM'!$T:$T,"Deal Lost") | J7: =SUMIFS('03_Prospects_CRM'!$X:$X,'03_Prospects_CRM'!$L:$L,$A7) | K7: =IFERROR(C7/E7,0) | L7: =IFERROR(C7/F7,0) | M7: =IFERROR(C7/G7,0) | N7: =IFERROR(C7/H7,0) | O7: =IFERROR(J7/C7,0) | P7: =IFERROR(F7/E7,0) | Q7: =IFERROR(G7/F7,0) | R7: =IFERROR(H7/G7,0)
A8: CMP-004 | B8: Mofawtar - Tax Invoice - Lead Gen - Q2 | C8: =SUMIFS('02_Meta_Raw_Data'!$J:$J,'02_Meta_Raw_Data'!$B:$B,$A8) | D8: =SUMIFS('02_Meta_Raw_Data'!$P:$P,'02_Meta_Raw_Data'!$B:$B,$A8) | E8: =COUNTIFS('03_Prospects_CRM'!$L:$L,$A8) | F8: =COUNTIFS('03_Prospects_CRM'!$L:$L,$A8,'03_Prospects_CRM'!$T:$T,"MQL")+COUNTIFS('03_Prospects_CRM'!$L:$L,$A8,'03_Prospects_CRM'!$T:$T,"SQL")+COUNTIFS('03_Prospects_CRM'!$L:$L,$A8,'03_Prospects_CRM'!$T:$T,"Deal Won") | G8: =COUNTIFS('03_Prospects_CRM'!$L:$L,$A8,'03_Prospects_CRM'!$T:$T,"SQL")+COUNTIFS('03_Prospects_CRM'!$L:$L,$A8,'03_Prospects_CRM'!$T:$T,"Deal Won") | H8: =COUNTIFS('03_Prospects_CRM'!$L:$L,$A8,'03_Prospects_CRM'!$T:$T,"Deal Won") | I8: =COUNTIFS('03_Prospects_CRM'!$L:$L,$A8,'03_Prospects_CRM'!$T:$T,"Deal Lost") | J8: =SUMIFS('03_Prospects_CRM'!$X:$X,'03_Prospects_CRM'!$L:$L,$A8) | K8: =IFERROR(C8/E8,0) | L8: =IFERROR(C8/F8,0) | M8: =IFERROR(C8/G8,0) | N8: =IFERROR(C8/H8,0) | O8: =IFERROR(J8/C8,0) | P8: =IFERROR(F8/E8,0) | Q8: =IFERROR(G8/F8,0) | R8: =IFERROR(H8/G8,0)
A9: CMP-005 | B9: Mofawtar - Retargeting - Demo Booking - Q2 | C9: =SUMIFS('02_Meta_Raw_Data'!$J:$J,'02_Meta_Raw_Data'!$B:$B,$A9) | D9: =SUMIFS('02_Meta_Raw_Data'!$P:$P,'02_Meta_Raw_Data'!$B:$B,$A9) | E9: =COUNTIFS('03_Prospects_CRM'!$L:$L,$A9) | F9: =COUNTIFS('03_Prospects_CRM'!$L:$L,$A9,'03_Prospects_CRM'!$T:$T,"MQL")+COUNTIFS('03_Prospects_CRM'!$L:$L,$A9,'03_Prospects_CRM'!$T:$T,"SQL")+COUNTIFS('03_Prospects_CRM'!$L:$L,$A9,'03_Prospects_CRM'!$T:$T,"Deal Won") | G9: =COUNTIFS('03_Prospects_CRM'!$L:$L,$A9,'03_Prospects_CRM'!$T:$T,"SQL")+COUNTIFS('03_Prospects_CRM'!$L:$L,$A9,'03_Prospects_CRM'!$T:$T,"Deal Won") | H9: =COUNTIFS('03_Prospects_CRM'!$L:$L,$A9,'03_Prospects_CRM'!$T:$T,"Deal Won") | I9: =COUNTIFS('03_Prospects_CRM'!$L:$L,$A9,'03_Prospects_CRM'!$T:$T,"Deal Lost") | J9: =SUMIFS('03_Prospects_CRM'!$X:$X,'03_Prospects_CRM'!$L:$L,$A9) | K9: =IFERROR(C9/E9,0) | L9: =IFERROR(C9/F9,0) | M9: =IFERROR(C9/G9,0) | N9: =IFERROR(C9/H9,0) | O9: =IFERROR(J9/C9,0) | P9: =IFERROR(F9/E9,0) | Q9: =IFERROR(G9/F9,0) | R9: =IFERROR(H9/G9,0)

Sheet 08_AdSet_Summary
A1: 08 AdSet Summary
A2: Ad Set rollup: cost, funnel and revenue.
A4: ID | B4: Name | C4: Campaign ID | D4: Campaign Name | E4: Spend | F4: Conversations | G4: CRM Leads | H4: MQL | I4: SQL | J4: Deals Won | K4: Deals Lost | L4: Revenue | M4: CPL | N4: Cost/MQL | O4: Cost/SQL | P4: CAC | Q4: ROAS | R4: Lead→MQL | S4: MQL→SQL | T4: SQL→Deal
A5: AS-0101 | B5: In2out - MessCampaign#1 - Testing - 15/4 | Broad SMEs | C5: CMP-001 | D5: In2out - MessCampaign#1 - Testing - 15/4 | E5: =SUMIFS('02_Meta_Raw_Data'!$J:$J,'02_Meta_Raw_Data'!$D:$D,$A5) | F5: =SUMIFS('02_Meta_Raw_Data'!$P:$P,'02_Meta_Raw_Data'!$D:$D,$A5) | G5: =COUNTIFS('03_Prospects_CRM'!$N:$N,$A5) | H5: =COUNTIFS('03_Prospects_CRM'!$N:$N,$A5,'03_Prospects_CRM'!$T:$T,"MQL")+COUNTIFS('03_Prospects_CRM'!$N:$N,$A5,'03_Prospects_CRM'!$T:$T,"SQL")+COUNTIFS('03_Prospects_CRM'!$N:$N,$A5,'03_Prospects_CRM'!$T:$T,"Deal Won") | I5: =COUNTIFS('03_Prospects_CRM'!$N:$N,$A5,'03_Prospects_CRM'!$T:$T,"SQL")+COUNTIFS('03_Prospects_CRM'!$N:$N,$A5,'03_Prospects_CRM'!$T:$T,"Deal Won") | J5: =COUNTIFS('03_Prospects_CRM'!$N:$N,$A5,'03_Prospects_CRM'!$T:$T,"Deal Won") | K5: =COUNTIFS('03_Prospects_CRM'!$N:$N,$A5,'03_Prospects_CRM'!$T:$T,"Deal Lost") | L5: =SUMIFS('03_Prospects_CRM'!$X:$X,'03_Prospects_CRM'!$N:$N,$A5) | M5: =IFERROR(E5/G5,0) | N5: =IFERROR(E5/H5,0) | O5: =IFERROR(E5/I5,0) | P5: =IFERROR(E5/J5,0) | Q5: =IFERROR(L5/E5,0) | R5: =IFERROR(H5/G5,0) | S5: =IFERROR(I5/H5,0) | T5: =IFERROR(J5/I5,0)
A6: AS-0102 | B6: In2out - MessCampaign#1 - Testing - 15/4 | Interest Tax Owners | C6: CMP-001 | D6: In2out - MessCampaign#1 - Testing - 15/4 | E6: =SUMIFS('02_Meta_Raw_Data'!$J:$J,'02_Meta_Raw_Data'!$D:$D,$A6) | F6: =SUMIFS('02_Meta_Raw_Data'!$P:$P,'02_Meta_Raw_Data'!$D:$D,$A6) | G6: =COUNTIFS('03_Prospects_CRM'!$N:$N,$A6) | H6: =COUNTIFS('03_Prospects_CRM'!$N:$N,$A6,'03_Prospects_CRM'!$T:$T,"MQL")+COUNTIFS('03_Prospects_CRM'!$N:$N,$A6,'03_Prospects_CRM'!$T:$T,"SQL")+COUNTIFS('03_Prospects_CRM'!$N:$N,$A6,'03_Prospects_CRM'!$T:$T,"Deal Won") | I6: =COUNTIFS('03_Prospects_CRM'!$N:$N,$A6,'03_Prospects_CRM'!$T:$T,"SQL")+COUNTIFS('03_Prospects_CRM'!$N:$N,$A6,'03_Prospects_CRM'!$T:$T,"Deal Won") | J6: =COUNTIFS('03_Prospects_CRM'!$N:$N,$A6,'03_Prospects_CRM'!$T:$T,"Deal Won") | K6: =COUNTIFS('03_Prospects_CRM'!$N:$N,$A6,'03_Prospects_CRM'!$T:$T,"Deal Lost") | L6: =SUMIFS('03_Prospects_CRM'!$X:$X,'03_Prospects_CRM'!$N:$N,$A6) | M6: =IFERROR(E6/G6,0) | N6: =IFERROR(E6/H6,0) | O6: =IFERROR(E6/I6,0) | P6: =IFERROR(E6/J6,0) | Q6: =IFERROR(L6/E6,0) | R6: =IFERROR(H6/G6,0) | S6: =IFERROR(I6/H6,0) | T6: =IFERROR(J6/I6,0)
A7: AS-0201 | B7: In2out - MessCampaign#2 - Testing - 20/4 | Broad SMEs | C7: CMP-002 | D7: In2out - MessCampaign#2 - Testing - 20/4 | E7: =SUMIFS('02_Meta_Raw_Data'!$J:$J,'02_Meta_Raw_Data'!$D:$D,$A7) | F7: =SUMIFS('02_Meta_Raw_Data'!$P:$P,'02_Meta_Raw_Data'!$D:$D,$A7) | G7: =COUNTIFS('03_Prospects_CRM'!$N:$N,$A7) | H7: =COUNTIFS('03_Prospects_CRM'!$N:$N,$A7,'03_Prospects_CRM'!$T:$T,"MQL")+COUNTIFS('03_Prospects_CRM'!$N:$N,$A7,'03_Prospects_CRM'!$T:$T,"SQL")+COUNTIFS('03_Prospects_CRM'!$N:$N,$A7,'03_Prospects_CRM'!$T:$T,"Deal Won") | I7: =COUNTIFS('03_Prospects_CRM'!$N:$N,$A7,'03_Prospects_CRM'!$T:$T,"SQL")+COUNTIFS('03_Prospects_CRM'!$N:$N,$A7,'03_Prospects_CRM'!$T:$T,"Deal Won") | J7: =COUNTIFS('03_Prospects_CRM'!$N:$N,$A7,'03_Prospects_CRM'!$T:$T,"Deal Won") | K7: =COUNTIFS('03_Prospects_CRM'!$N:$N,$A7,'03_Prospects_CRM'!$T:$T,"Deal Lost") | L7: =SUMIFS('03_Prospects_CRM'!$X:$X,'03_Prospects_CRM'!$N:$N,$A7) | M7: =IFERROR(E7/G7,0) | N7: =IFERROR(E7/H7,0) | O7: =IFERROR(E7/I7,0) | P7: =IFERROR(E7/J7,0) | Q7: =IFERROR(L7/E7,0) | R7: =IFERROR(H7/G7,0) | S7: =IFERROR(I7/H7,0) | T7: =IFERROR(J7/I7,0)
A8: AS-0202 | B8: In2out - MessCampaign#2 - Testing - 20/4 | Interest Tax Owners | C8: CMP-002 | D8: In2out - MessCampaign#2 - Testing - 20/4 | E8: =SUMIFS('02_Meta_Raw_Data'!$J:$J,'02_Meta_Raw_Data'!$D:$D,$A8) | F8: =SUMIFS('02_Meta_Raw_Data'!$P:$P,'02_Meta_Raw_Data'!$D:$D,$A8) | G8: =COUNTIFS('03_Prospects_CRM'!$N:$N,$A8) | H8: =COUNTIFS('03_Prospects_CRM'!$N:$N,$A8,'03_Prospects_CRM'!$T:$T,"MQL")+COUNTIFS('03_Prospects_CRM'!$N:$N,$A8,'03_Prospects_CRM'!$T:$T,"SQL")+COUNTIFS('03_Prospects_CRM'!$N:$N,$A8,'03_Prospects_CRM'!$T:$T,"Deal Won") | I8: =COUNTIFS('03_Prospects_CRM'!$N:$N,$A8,'03_Prospects_CRM'!$T:$T,"SQL")+COUNTIFS('03_Prospects_CRM'!$N:$N,$A8,'03_Prospects_CRM'!$T:$T,"Deal Won") | J8: =COUNTIFS('03_Prospects_CRM'!$N:$N,$A8,'03_Prospects_CRM'!$T:$T,"Deal Won") | K8: =COUNTIFS('03_Prospects_CRM'!$N:$N,$A8,'03_Prospects_CRM'!$T:$T,"Deal Lost") | L8: =SUMIFS('03_Prospects_CRM'!$X:$X,'03_Prospects_CRM'!$N:$N,$A8) | M8: =IFERROR(E8/G8,0) | N8: =IFERROR(E8/H8,0) | O8: =IFERROR(E8/I8,0) | P8: =IFERROR(E8/J8,0) | Q8: =IFERROR(L8/E8,0) | R8: =IFERROR(H8/G8,0) | S8: =IFERROR(I8/H8,0) | T8: =IFERROR(J8/I8,0)
A9: AS-0301 | B9: Mofawtar - E-Receipt - Awareness - Q2 | Broad SMEs | C9: CMP-003 | D9: Mofawtar - E-Receipt - Awareness - Q2 | E9: =SUMIFS('02_Meta_Raw_Data'!$J:$J,'02_Meta_Raw_Data'!$D:$D,$A9) | F9: =SUMIFS('02_Meta_Raw_Data'!$P:$P,'02_Meta_Raw_Data'!$D:$D,$A9) | G9: =COUNTIFS('03_Prospects_CRM'!$N:$N,$A9) | H9: =COUNTIFS('03_Prospects_CRM'!$N:$N,$A9,'03_Prospects_CRM'!$T:$T,"MQL")+COUNTIFS('03_Prospects_CRM'!$N:$N,$A9,'03_Prospects_CRM'!$T:$T,"SQL")+COUNTIFS('03_Prospects_CRM'!$N:$N,$A9,'03_Prospects_CRM'!$T:$T,"Deal Won") | I9: =COUNTIFS('03_Prospects_CRM'!$N:$N,$A9,'03_Prospects_CRM'!$T:$T,"SQL")+COUNTIFS('03_Prospects_CRM'!$N:$N,$A9,'03_Prospects_CRM'!$T:$T,"Deal Won") | J9: =COUNTIFS('03_Prospects_CRM'!$N:$N,$A9,'03_Prospects_CRM'!$T:$T,"Deal Won") | K9: =COUNTIFS('03_Prospects_CRM'!$N:$N,$A9,'03_Prospects_CRM'!$T:$T,"Deal Lost") | L9: =SUMIFS('03_Prospects_CRM'!$X:$X,'03_Prospects_CRM'!$N:$N,$A9) | M9: =IFERROR(E9/G9,0) | N9: =IFERROR(E9/H9,0) | O9: =IFERROR(E9/I9,0) | P9: =IFERROR(E9/J9,0) | Q9: =IFERROR(L9/E9,0) | R9: =IFERROR(H9/G9,0) | S9: =IFERROR(I9/H9,0) | T9: =IFERROR(J9/I9,0)
A10: AS-0302 | B10: Mofawtar - E-Receipt - Awareness - Q2 | Interest Tax Owners | C10: CMP-003 | D10: Mofawtar - E-Receipt - Awareness - Q2 | E10: =SUMIFS('02_Meta_Raw_Data'!$J:$J,'02_Meta_Raw_Data'!$D:$D,$A10) | F10: =SUMIFS('02_Meta_Raw_Data'!$P:$P,'02_Meta_Raw_Data'!$D:$D,$A10) | G10: =COUNTIFS('03_Prospects_CRM'!$N:$N,$A10) | H10: =COUNTIFS('03_Prospects_CRM'!$N:$N,$A10,'03_Prospects_CRM'!$T:$T,"MQL")+COUNTIFS('03_Prospects_CRM'!$N:$N,$A10,'03_Prospects_CRM'!$T:$T,"SQL")+COUNTIFS('03_Prospects_CRM'!$N:$N,$A10,'03_Prospects_CRM'!$T:$T,"Deal Won") | I10: =COUNTIFS('03_Prospects_CRM'!$N:$N,$A10,'03_Prospects_CRM'!$T:$T,"SQL")+COUNTIFS('03_Prospects_CRM'!$N:$N,$A10,'03_Prospects_CRM'!$T:$T,"Deal Won") | J10: =COUNTIFS('03_Prospects_CRM'!$N:$N,$A10,'03_Prospects_CRM'!$T:$T,"Deal Won") | K10: =COUNTIFS('03_Prospects_CRM'!$N:$N,$A10,'03_Prospects_CRM'!$T:$T,"Deal Lost") | L10: =SUMIFS('03_Prospects_CRM'!$X:$X,'03_Prospects_CRM'!$N:$N,$A10) | M10: =IFERROR(E10/G10,0) | N10: =IFERROR(E10/H10,0) | O10: =IFERROR(E10/I10,0) | P10: =IFERROR(E10/J10,0) | Q10: =IFERROR(L10/E10,0) | R10: =IFERROR(H10/G10,0) | S10: =IFERROR(I10/H10,0) | T10: =IFERROR(J10/I10,0)
A11: AS-0401 | B11: Mofawtar - Tax Invoice - Lead Gen - Q2 | Broad SMEs | C11: CMP-004 | D11: Mofawtar - Tax Invoice - Lead Gen - Q2 | E11: =SUMIFS('02_Meta_Raw_Data'!$J:$J,'02_Meta_Raw_Data'!$D:$D,$A11) | F11: =SUMIFS('02_Meta_Raw_Data'!$P:$P,'02_Meta_Raw_Data'!$D:$D,$A11) | G11: =COUNTIFS('03_Prospects_CRM'!$N:$N,$A11) | H11: =COUNTIFS('03_Prospects_CRM'!$N:$N,$A11,'03_Prospects_CRM'!$T:$T,"MQL")+COUNTIFS('03_Prospects_CRM'!$N:$N,$A11,'03_Prospects_CRM'!$T:$T,"SQL")+COUNTIFS('03_Prospects_CRM'!$N:$N,$A11,'03_Prospects_CRM'!$T:$T,"Deal Won") | I11: =COUNTIFS('03_Prospects_CRM'!$N:$N,$A11,'03_Prospects_CRM'!$T:$T,"SQL")+COUNTIFS('03_Prospects_CRM'!$N:$N,$A11,'03_Prospects_CRM'!$T:$T,"Deal Won") | J11: =COUNTIFS('03_Prospects_CRM'!$N:$N,$A11,'03_Prospects_CRM'!$T:$T,"Deal Won") | K11: =COUNTIFS('03_Prospects_CRM'!$N:$N,$A11,'03_Prospects_CRM'!$T:$T,"Deal Lost") | L11: =SUMIFS('03_Prospects_CRM'!$X:$X,'03_Prospects_CRM'!$N:$N,$A11) | M11: =IFERROR(E11/G11,0) | N11: =IFERROR(E11/H11,0) | O11: =IFERROR(E11/I11,0) | P11: =IFERROR(E11/J11,0) | Q11: =IFERROR(L11/E11,0) | R11: =IFERROR(H11/G11,0) | S11: =IFERROR(I11/H11,0) | T11: =IFERROR(J11/I11,0)
A12: AS-0402 | B12: Mofawtar - Tax Invoice - Lead Gen - Q2 | Interest Tax Owners | C12: CMP-004 | D12: Mofawtar - Tax Invoice - Lead Gen - Q2 | E12: =SUMIFS('02_Meta_Raw_Data'!$J:$J,'02_Meta_Raw_Data'!$D:$D,$A12) | F12: =SUMIFS('02_Meta_Raw_Data'!$P:$P,'02_Meta_Raw_Data'!$D:$D,$A12) | G12: =COUNTIFS('03_Prospects_CRM'!$N:$N,$A12) | H12: =COUNTIFS('03_Prospects_CRM'!$N:$N,$A12,'03_Prospects_CRM'!$T:$T,"MQL")+COUNTIFS('03_Prospects_CRM'!$N:$N,$A12,'03_Prospects_CRM'!$T:$T,"SQL")+COUNTIFS('03_Prospects_CRM'!$N:$N,$A12,'03_Prospects_CRM'!$T:$T,"Deal Won") | I12: =COUNTIFS('03_Prospects_CRM'!$N:$N,$A12,'03_Prospects_CRM'!$T:$T,"SQL")+COUNTIFS('03_Prospects_CRM'!$N:$N,$A12,'03_Prospects_CRM'!$T:$T,"Deal Won") | J12: =COUNTIFS('03_Prospects_CRM'!$N:$N,$A12,'03_Prospects_CRM'!$T:$T,"Deal Won") | K12: =COUNTIFS('03_Prospects_CRM'!$N:$N,$A12,'03_Prospects_CRM'!$T:$T,"Deal Lost") | L12: =SUMIFS('03_Prospects_CRM'!$X:$X,'03_Prospects_CRM'!$N:$N,$A12) | M12: =IFERROR(E12/G12,0) | N12: =IFERROR(E12/H12,0) | O12: =IFERROR(E12/I12,0) | P12: =IFERROR(E12/J12,0) | Q12: =IFERROR(L12/E12,0) | R12: =IFERROR(H12/G12,0) | S12: =IFERROR(I12/H12,0) | T12: =IFERROR(J12/I12,0)
A13: AS-0403 | B13: Mofawtar - Tax Invoice - Lead Gen - Q2 | Retargeting Visitors | C13: CMP-004 | D13: Mofawtar - Tax Invoice - Lead Gen - Q2 | E13: =SUMIFS('02_Meta_Raw_Data'!$J:$J,'02_Meta_Raw_Data'!$D:$D,$A13) | F13: =SUMIFS('02_Meta_Raw_Data'!$P:$P,'02_Meta_Raw_Data'!$D:$D,$A13) | G13: =COUNTIFS('03_Prospects_CRM'!$N:$N,$A13) | H13: =COUNTIFS('03_Prospects_CRM'!$N:$N,$A13,'03_Prospects_CRM'!$T:$T,"MQL")+COUNTIFS('03_Prospects_CRM'!$N:$N,$A13,'03_Prospects_CRM'!$T:$T,"SQL")+COUNTIFS('03_Prospects_CRM'!$N:$N,$A13,'03_Prospects_CRM'!$T:$T,"Deal Won") | I13: =COUNTIFS('03_Prospects_CRM'!$N:$N,$A13,'03_Prospects_CRM'!$T:$T,"SQL")+COUNTIFS('03_Prospects_CRM'!$N:$N,$A13,'03_Prospects_CRM'!$T:$T,"Deal Won") | J13: =COUNTIFS('03_Prospects_CRM'!$N:$N,$A13,'03_Prospects_CRM'!$T:$T,"Deal Won") | K13: =COUNTIFS('03_Prospects_CRM'!$N:$N,$A13,'03_Prospects_CRM'!$T:$T,"Deal Lost") | L13: =SUMIFS('03_Prospects_CRM'!$X:$X,'03_Prospects_CRM'!$N:$N,$A13) | M13: =IFERROR(E13/G13,0) | N13: =IFERROR(E13/H13,0) | O13: =IFERROR(E13/I13,0) | P13: =IFERROR(E13/J13,0) | Q13: =IFERROR(L13/E13,0) | R13: =IFERROR(H13/G13,0) | S13: =IFERROR(I13/H13,0) | T13: =IFERROR(J13/I13,0)
A14: AS-0501 | B14: Mofawtar - Retargeting - Demo Booking - Q2 | Broad SMEs | C14: CMP-005 | D14: Mofawtar - Retargeting - Demo Booking - Q2 | E14: =SUMIFS('02_Meta_Raw_Data'!$J:$J,'02_Meta_Raw_Data'!$D:$D,$A14) | F14: =SUMIFS('02_Meta_Raw_Data'!$P:$P,'02_Meta_Raw_Data'!$D:$D,$A14) | G14: =COUNTIFS('03_Prospects_CRM'!$N:$N,$A14) | H14: =COUNTIFS('03_Prospects_CRM'!$N:$N,$A14,'03_Prospects_CRM'!$T:$T,"MQL")+COUNTIFS('03_Prospects_CRM'!$N:$N,$A14,'03_Prospects_CRM'!$T:$T,"SQL")+COUNTIFS('03_Prospects_CRM'!$N:$N,$A14,'03_Prospects_CRM'!$T:$T,"Deal Won") | I14: =COUNTIFS('03_Prospects_CRM'!$N:$N,$A14,'03_Prospects_CRM'!$T:$T,"SQL")+COUNTIFS('03_Prospects_CRM'!$N:$N,$A14,'03_Prospects_CRM'!$T:$T,"Deal Won") | J14: =COUNTIFS('03_Prospects_CRM'!$N:$N,$A14,'03_Prospects_CRM'!$T:$T,"Deal Won") | K14: =COUNTIFS('03_Prospects_CRM'!$N:$N,$A14,'03_Prospects_CRM'!$T:$T,"Deal Lost") | L14: =SUMIFS('03_Prospects_CRM'!$X:$X,'03_Prospects_CRM'!$N:$N,$A14) | M14: =IFERROR(E14/G14,0) | N14: =IFERROR(E14/H14,0) | O14: =IFERROR(E14/I14,0) | P14: =IFERROR(E14/J14,0) | Q14: =IFERROR(L14/E14,0) | R14: =IFERROR(H14/G14,0) | S14: =IFERROR(I14/H14,0) | T14: =IFERROR(J14/I14,0)
A15: AS-0502 | B15: Mofawtar - Retargeting - Demo Booking - Q2 | Interest Tax Owners | C15: CMP-005 | D15: Mofawtar - Retargeting - Demo Booking - Q2 | E15: =SUMIFS('02_Meta_Raw_Data'!$J:$J,'02_Meta_Raw_Data'!$D:$D,$A15) | F15: =SUMIFS('02_Meta_Raw_Data'!$P:$P,'02_Meta_Raw_Data'!$D:$D,$A15) | G15: =COUNTIFS('03_Prospects_CRM'!$N:$N,$A15) | H15: =COUNTIFS('03_Prospects_CRM'!$N:$N,$A15,'03_Prospects_CRM'!$T:$T,"MQL")+COUNTIFS('03_Prospects_CRM'!$N:$N,$A15,'03_Prospects_CRM'!$T:$T,"SQL")+COUNTIFS('03_Prospects_CRM'!$N:$N,$A15,'03_Prospects_CRM'!$T:$T,"Deal Won") | I15: =COUNTIFS('03_Prospects_CRM'!$N:$N,$A15,'03_Prospects_CRM'!$T:$T,"SQL")+COUNTIFS('03_Prospects_CRM'!$N:$N,$A15,'03_Prospects_CRM'!$T:$T,"Deal Won") | J15: =COUNTIFS('03_Prospects_CRM'!$N:$N,$A15,'03_Prospects_CRM'!$T:$T,"Deal Won") | K15: =COUNTIFS('03_Prospects_CRM'!$N:$N,$A15,'03_Prospects_CRM'!$T:$T,"Deal Lost") | L15: =SUMIFS('03_Prospects_CRM'!$X:$X,'03_Prospects_CRM'!$N:$N,$A15) | M15: =IFERROR(E15/G15,0) | N15: =IFERROR(E15/H15,0) | O15: =IFERROR(E15/I15,0) | P15: =IFERROR(E15/J15,0) | Q15: =IFERROR(L15/E15,0) | R15: =IFERROR(H15/G15,0) | S15: =IFERROR(I15/H15,0) | T15: =IFERROR(J15/I15,0)
A16: AS-0503 | B16: Mofawtar - Retargeting - Demo Booking - Q2 | Retargeting Visitors | C16: CMP-005 | D16: Mofawtar - Retargeting - Demo Booking - Q2 | E16: =SUMIFS('02_Meta_Raw_Data'!$J:$J,'02_Meta_Raw_Data'!$D:$D,$A16) | F16: =SUMIFS('02_Meta_Raw_Data'!$P:$P,'02_Meta_Raw_Data'!$D:$D,$A16) | G16: =COUNTIFS('03_Prospects_CRM'!$N:$N,$A16) | H16: =COUNTIFS('03_Prospects_CRM'!$N:$N,$A16,'03_Prospects_CRM'!$T:$T,"MQL")+COUNTIFS('03_Prospects_CRM'!$N:$N,$A16,'03_Prospects_CRM'!$T:$T,"SQL")+COUNTIFS('03_Prospects_CRM'!$N:$N,$A16,'03_Prospects_CRM'!$T:$T,"Deal Won") | I16: =COUNTIFS('03_Prospects_CRM'!$N:$N,$A16,'03_Prospects_CRM'!$T:$T,"SQL")+COUNTIFS('03_Prospects_CRM'!$N:$N,$A16,'03_Prospects_CRM'!$T:$T,"Deal Won") | J16: =COUNTIFS('03_Prospects_CRM'!$N:$N,$A16,'03_Prospects_CRM'!$T:$T,"Deal Won") | K16: =COUNTIFS('03_Prospects_CRM'!$N:$N,$A16,'03_Prospects_CRM'!$T:$T,"Deal Lost") | L16: =SUMIFS('03_Prospects_CRM'!$X:$X,'03_Prospects_CRM'!$N:$N,$A16) | M16: =IFERROR(E16/G16,0) | N16: =IFERROR(E16/H16,0) | O16: =IFERROR(E16/I16,0) | P16: =IFERROR(E16/J16,0) | Q16: =IFERROR(L16/E16,0) | R16: =IFERROR(H16/G16,0) | S16: =IFERROR(I16/H16,0) | T16: =IFERROR(J16/I16,0)

Sheet 09_Ad_Summary
A1: 09 Ad Summary
A2: Ad rollup: cost, funnel and revenue.
A4: ID | B4: Name | C4: Campaign ID | D4: Campaign Name | E4: Ad Set ID | F4: Ad Set Name | G4: Spend | H4: Conversations | I4: CRM Leads | J4: MQL | K4: SQL | L4: Deals Won | M4: Deals Lost | N4: Revenue | O4: CPL | P4: Cost/MQL | Q4: Cost/SQL | R4: CAC | S4: ROAS | T4: Lead→MQL | U4: MQL→SQL | V4: SQL→Deal
A5: AD-010101 | B5: Pain Point Static | Broad SMEs | C5: CMP-001 | D5: In2out - MessCampaign#1 - Testing - 15/4 | E5: AS-0101 | F5: In2out - MessCampaign#1 - Testing - 15/4 | Broad SMEs | G5: =SUMIFS('02_Meta_Raw_Data'!$J:$J,'02_Meta_Raw_Data'!$F:$F,$A5) | H5: =SUMIFS('02_Meta_Raw_Data'!$P:$P,'02_Meta_Raw_Data'!$F:$F,$A5) | I5: =COUNTIFS('03_Prospects_CRM'!$P:$P,$A5) | J5: =COUNTIFS('03_Prospects_CRM'!$P:$P,$A5,'03_Prospects_CRM'!$T:$T,"MQL")+COUNTIFS('03_Prospects_CRM'!$P:$P,$A5,'03_Prospects_CRM'!$T:$T,"SQL")+COUNTIFS('03_Prospects_CRM'!$P:$P,$A5,'03_Prospects_CRM'!$T:$T,"Deal Won") | K5: =COUNTIFS('03_Prospects_CRM'!$P:$P,$A5,'03_Prospects_CRM'!$T:$T,"SQL")+COUNTIFS('03_Prospects_CRM'!$P:$P,$A5,'03_Prospects_CRM'!$T:$T,"Deal Won") | L5: =COUNTIFS('03_Prospects_CRM'!$P:$P,$A5,'03_Prospects_CRM'!$T:$T,"Deal Won") | M5: =COUNTIFS('03_Prospects_CRM'!$P:$P,$A5,'03_Prospects_CRM'!$T:$T,"Deal Lost") | N5: =SUMIFS('03_Prospects_CRM'!$X:$X,'03_Prospects_CRM'!$P:$P,$A5) | O5: =IFERROR(G5/I5,0) | P5: =IFERROR(G5/J5,0) | Q5: =IFERROR(G5/K5,0) | R5: =IFERROR(G5/L5,0) | S5: =IFERROR(N5/G5,0) | T5: =IFERROR(J5/I5,0) | U5: =IFERROR(K5/J5,0) | V5: =IFERROR(L5/K5,0)
A6: AD-010102 | B6: Demo Reel | Broad SMEs | C6: CMP-001 | D6: In2out - MessCampaign#1 - Testing - 15/4 | E6: AS-0101 | F6: In2out - MessCampaign#1 - Testing - 15/4 | Broad SMEs | G6: =SUMIFS('02_Meta_Raw_Data'!$J:$J,'02_Meta_Raw_Data'!$F:$F,$A6) | H6: =SUMIFS('02_Meta_Raw_Data'!$P:$P,'02_Meta_Raw_Data'!$F:$F,$A6) | I6: =COUNTIFS('03_Prospects_CRM'!$P:$P,$A6) | J6: =COUNTIFS('03_Prospects_CRM'!$P:$P,$A6,'03_Prospects_CRM'!$T:$T,"MQL")+COUNTIFS('03_Prospects_CRM'!$P:$P,$A6,'03_Prospects_CRM'!$T:$T,"SQL")+COUNTIFS('03_Prospects_CRM'!$P:$P,$A6,'03_Prospects_CRM'!$T:$T,"Deal Won") | K6: =COUNTIFS('03_Prospects_CRM'!$P:$P,$A6,'03_Prospects_CRM'!$T:$T,"SQL")+COUNTIFS('03_Prospects_CRM'!$P:$P,$A6,'03_Prospects_CRM'!$T:$T,"Deal Won") | L6: =COUNTIFS('03_Prospects_CRM'!$P:$P,$A6,'03_Prospects_CRM'!$T:$T,"Deal Won") | M6: =COUNTIFS('03_Prospects_CRM'!$P:$P,$A6,'03_Prospects_CRM'!$T:$T,"Deal Lost") | N6: =SUMIFS('03_Prospects_CRM'!$X:$X,'03_Prospects_CRM'!$P:$P,$A6) | O6: =IFERROR(G6/I6,0) | P6: =IFERROR(G6/J6,0) | Q6: =IFERROR(G6/K6,0) | R6: =IFERROR(G6/L6,0) | S6: =IFERROR(N6/G6,0) | T6: =IFERROR(J6/I6,0) | U6: =IFERROR(K6/J6,0) | V6: =IFERROR(L6/K6,0)
A7: AD-010103 | B7: Offer Carousel | Broad SMEs | C7: CMP-001 | D7: In2out - MessCampaign#1 - Testing - 15/4 | E7: AS-0101 | F7: In2out - MessCampaign#1 - Testing - 15/4 | Broad SMEs | G7: =SUMIFS('02_Meta_Raw_Data'!$J:$J,'02_Meta_Raw_Data'!$F:$F,$A7) | H7: =SUMIFS('02_Meta_Raw_Data'!$P:$P,'02_Meta_Raw_Data'!$F:$F,$A7) | I7: =COUNTIFS('03_Prospects_CRM'!$P:$P,$A7) | J7: =COUNTIFS('03_Prospects_CRM'!$P:$P,$A7,'03_Prospects_CRM'!$T:$T,"MQL")+COUNTIFS('03_Prospects_CRM'!$P:$P,$A7,'03_Prospects_CRM'!$T:$T,"SQL")+COUNTIFS('03_Prospects_CRM'!$P:$P,$A7,'03_Prospects_CRM'!$T:$T,"Deal Won") | K7: =COUNTIFS('03_Prospects_CRM'!$P:$P,$A7,'03_Prospects_CRM'!$T:$T,"SQL")+COUNTIFS('03_Prospects_CRM'!$P:$P,$A7,'03_Prospects_CRM'!$T:$T,"Deal Won") | L7: =COUNTIFS('03_Prospects_CRM'!$P:$P,$A7,'03_Prospects_CRM'!$T:$T,"Deal Won") | M7: =COUNTIFS('03_Prospects_CRM'!$P:$P,$A7,'03_Prospects_CRM'!$T:$T,"Deal Lost") | N7: =SUMIFS('03_Prospects_CRM'!$X:$X,'03_Prospects_CRM'!$P:$P,$A7) | O7: =IFERROR(G7/I7,0) | P7: =IFERROR(G7/J7,0) | Q7: =IFERROR(G7/K7,0) | R7: =IFERROR(G7/L7,0) | S7: =IFERROR(N7/G7,0) | T7: =IFERROR(J7/I7,0) | U7: =IFERROR(K7/J7,0) | V7: =IFERROR(L7/K7,0)
A8: AD-010201 | B8: Pain Point Static | Interest Tax Owners | C8: CMP-001 | D8: In2out - MessCampaign#1 - Testing - 15/4 | E8: AS-0102 | F8: In2out - MessCampaign#1 - Testing - 15/4 | Interest Tax Owners | G8: =SUMIFS('02_Meta_Raw_Data'!$J:$J,'02_Meta_Raw_Data'!$F:$F,$A8) | H8: =SUMIFS('02_Meta_Raw_Data'!$P:$P,'02_Meta_Raw_Data'!$F:$F,$A8) | I8: =COUNTIFS('03_Prospects_CRM'!$P:$P,$A8) | J8: =COUNTIFS('03_Prospects_CRM'!$P:$P,$A8,'03_Prospects_CRM'!$T:$T,"MQL")+COUNTIFS('03_Prospects_CRM'!$P:$P,$A8,'03_Prospects_CRM'!$T:$T,"SQL")+COUNTIFS('03_Prospects_CRM'!$P:$P,$A8,'03_Prospects_CRM'!$T:$T,"Deal Won") | K8: =COUNTIFS('03_Prospects_CRM'!$P:$P,$A8,'03_Prospects_CRM'!$T:$T,"SQL")+COUNTIFS('03_Prospects_CRM'!$P:$P,$A8,'03_Prospects_CRM'!$T:$T,"Deal Won") | L8: =COUNTIFS('03_Prospects_CRM'!$P:$P,$A8,'03_Prospects_CRM'!$T:$T,"Deal Won") | M8: =COUNTIFS('03_Prospects_CRM'!$P:$P,$A8,'03_Prospects_CRM'!$T:$T,"Deal Lost") | N8: =SUMIFS('03_Prospects_CRM'!$X:$X,'03_Prospects_CRM'!$P:$P,$A8) | O8: =IFERROR(G8/I8,0) | P8: =IFERROR(G8/J8,0) | Q8: =IFERROR(G8/K8,0) | R8: =IFERROR(G8/L8,0) | S8: =IFERROR(N8/G8,0) | T8: =IFERROR(J8/I8,0) | U8: =IFERROR(K8/J8,0) | V8: =IFERROR(L8/K8,0)
A9: AD-010202 | B9: Demo Reel | Interest Tax Owners | C9: CMP-001 | D9: In2out - MessCampaign#1 - Testing - 15/4 | E9: AS-0102 | F9: In2out - MessCampaign#1 - Testing - 15/4 | Interest Tax Owners | G9: =SUMIFS('02_Meta_Raw_Data'!$J:$J,'02_Meta_Raw_Data'!$F:$F,$A9) | H9: =SUMIFS('02_Meta_Raw_Data'!$P:$P,'02_Meta_Raw_Data'!$F:$F,$A9) | I9: =COUNTIFS('03_Prospects_CRM'!$P:$P,$A9) | J9: =COUNTIFS('03_Prospects_CRM'!$P:$P,$A9,'03_Prospects_CRM'!$T:$T,"MQL")+COUNTIFS('03_Prospects_CRM'!$P:$P,$A9,'03_Prospects_CRM'!$T:$T,"SQL")+COUNTIFS('03_Prospects_CRM'!$P:$P,$A9,'03_Prospects_CRM'!$T:$T,"Deal Won") | K9: =COUNTIFS('03_Prospects_CRM'!$P:$P,$A9,'03_Prospects_CRM'!$T:$T,"SQL")+COUNTIFS('03_Prospects_CRM'!$P:$P,$A9,'03_Prospects_CRM'!$T:$T,"Deal Won") | L9: =COUNTIFS('03_Prospects_CRM'!$P:$P,$A9,'03_Prospects_CRM'!$T:$T,"Deal Won") | M9: =COUNTIFS('03_Prospects_CRM'!$P:$P,$A9,'03_Prospects_CRM'!$T:$T,"Deal Lost") | N9: =SUMIFS('03_Prospects_CRM'!$X:$X,'03_Prospects_CRM'!$P:$P,$A9) | O9: =IFERROR(G9/I9,0) | P9: =IFERROR(G9/J9,0) | Q9: =IFERROR(G9/K9,0) | R9: =IFERROR(G9/L9,0) | S9: =IFERROR(N9/G9,0) | T9: =IFERROR(J9/I9,0) | U9: =IFERROR(K9/J9,0) | V9: =IFERROR(L9/K9,0)
A10: AD-020101 | B10: Pain Point Static | Broad SMEs | C10: CMP-002 | D10: In2out - MessCampaign#2 - Testing - 20/4 | E10: AS-0201 | F10: In2out - MessCampaign#2 - Testing - 20/4 | Broad SMEs | G10: =SUMIFS('02_Meta_Raw_Data'!$J:$J,'02_Meta_Raw_Data'!$F:$F,$A10) | H10: =SUMIFS('02_Meta_Raw_Data'!$P:$P,'02_Meta_Raw_Data'!$F:$F,$A10) | I10: =COUNTIFS('03_Prospects_CRM'!$P:$P,$A10) | J10: =COUNTIFS('03_Prospects_CRM'!$P:$P,$A10,'03_Prospects_CRM'!$T:$T,"MQL")+COUNTIFS('03_Prospects_CRM'!$P:$P,$A10,'03_Prospects_CRM'!$T:$T,"SQL")+COUNTIFS('03_Prospects_CRM'!$P:$P,$A10,'03_Prospects_CRM'!$T:$T,"Deal Won") | K10: =COUNTIFS('03_Prospects_CRM'!$P:$P,$A10,'03_Prospects_CRM'!$T:$T,"SQL")+COUNTIFS('03_Prospects_CRM'!$P:$P,$A10,'03_Prospects_CRM'!$T:$T,"Deal Won") | L10: =COUNTIFS('03_Prospects_CRM'!$P:$P,$A10,'03_Prospects_CRM'!$T:$T,"Deal Won") | M10: =COUNTIFS('03_Prospects_CRM'!$P:$P,$A10,'03_Prospects_CRM'!$T:$T,"Deal Lost") | N10: =SUMIFS('03_Prospects_CRM'!$X:$X,'03_Prospects_CRM'!$P:$P,$A10) | O10: =IFERROR(G10/I10,0) | P10: =IFERROR(G10/J10,0) | Q10: =IFERROR(G10/K10,0) | R10: =IFERROR(G10/L10,0) | S10: =IFERROR(N10/G10,0) | T10: =IFERROR(J10/I10,0) | U10: =IFERROR(K10/J10,0) | V10: =IFERROR(L10/K10,0)
A11: AD-020102 | B11: Demo Reel | Broad SMEs | C11: CMP-002 | D11: In2out - MessCampaign#2 - Testing - 20/4 | E11: AS-0201 | F11: In2out - MessCampaign#2 - Testing - 20/4 | Broad SMEs | G11: =SUMIFS('02_Meta_Raw_Data'!$J:$J,'02_Meta_Raw_Data'!$F:$F,$A11) | H11: =SUMIFS('02_Meta_Raw_Data'!$P:$P,'02_Meta_Raw_Data'!$F:$F,$A11) | I11: =COUNTIFS('03_Prospects_CRM'!$P:$P,$A11) | J11: =COUNTIFS('03_Prospects_CRM'!$P:$P,$A11,'03_Prospects_CRM'!$T:$T,"MQL")+COUNTIFS('03_Prospects_CRM'!$P:$P,$A11,'03_Prospects_CRM'!$T:$T,"SQL")+COUNTIFS('03_Prospects_CRM'!$P:$P,$A11,'03_Prospects_CRM'!$T:$T,"Deal Won") | K11: =COUNTIFS('03_Prospects_CRM'!$P:$P,$A11,'03_Prospects_CRM'!$T:$T,"SQL")+COUNTIFS('03_Prospects_CRM'!$P:$P,$A11,'03_Prospects_CRM'!$T:$T,"Deal Won") | L11: =COUNTIFS('03_Prospects_CRM'!$P:$P,$A11,'03_Prospects_CRM'!$T:$T,"Deal Won") | M11: =COUNTIFS('03_Prospects_CRM'!$P:$P,$A11,'03_Prospects_CRM'!$T:$T,"Deal Lost") | N11: =SUMIFS('03_Prospects_CRM'!$X:$X,'03_Prospects_CRM'!$P:$P,$A11) | O11: =IFERROR(G11/I11,0) | P11: =IFERROR(G11/J11,0) | Q11: =IFERROR(G11/K11,0) | R11: =IFERROR(G11/L11,0) | S11: =IFERROR(N11/G11,0) | T11: =IFERROR(J11/I11,0) | U11: =IFERROR(K11/J11,0) | V11: =IFERROR(L11/K11,0)
A12: AD-020103 | B12: Offer Carousel | Broad SMEs | C12: CMP-002 | D12: In2out - MessCampaign#2 - Testing - 20/4 | E12: AS-0201 | F12: In2out - MessCampaign#2 - Testing - 20/4 | Broad SMEs | G12: =SUMIFS('02_Meta_Raw_Data'!$J:$J,'02_Meta_Raw_Data'!$F:$F,$A12) | H12: =SUMIFS('02_Meta_Raw_Data'!$P:$P,'02_Meta_Raw_Data'!$F:$F,$A12) | I12: =COUNTIFS('03_Prospects_CRM'!$P:$P,$A12) | J12: =COUNTIFS('03_Prospects_CRM'!$P:$P,$A12,'03_Prospects_CRM'!$T:$T,"MQL")+COUNTIFS('03_Prospects_CRM'!$P:$P,$A12,'03_Prospects_CRM'!$T:$T,"SQL")+COUNTIFS('03_Prospects_CRM'!$P:$P,$A12,'03_Prospects_CRM'!$T:$T,"Deal Won") | K12: =COUNTIFS('03_Prospects_CRM'!$P:$P,$A12,'03_Prospects_CRM'!$T:$T,"SQL")+COUNTIFS('03_Prospects_CRM'!$P:$P,$A12,'03_Prospects_CRM'!$T:$T,"Deal Won") | L12: =COUNTIFS('03_Prospects_CRM'!$P:$P,$A12,'03_Prospects_CRM'!$T:$T,"Deal Won") | M12: =COUNTIFS('03_Prospects_CRM'!$P:$P,$A12,'03_Prospects_CRM'!$T:$T,"Deal Lost") | N12: =SUMIFS('03_Prospects_CRM'!$X:$X,'03_Prospects_CRM'!$P:$P,$A12) | O12: =IFERROR(G12/I12,0) | P12: =IFERROR(G12/J12,0) | Q12: =IFERROR(G12/K12,0) | R12: =IFERROR(G12/L12,0) | S12: =IFERROR(N12/G12,0) | T12: =IFERROR(J12/I12,0) | U12: =IFERROR(K12/J12,0) | V12: =IFERROR(L12/K12,0)
A13: AD-020201 | B13: Pain Point Static | Interest Tax Owners | C13: CMP-002 | D13: In2out - MessCampaign#2 - Testing - 20/4 | E13: AS-0202 | F13: In2out - MessCampaign#2 - Testing - 20/4 | Interest Tax Owners | G13: =SUMIFS('02_Meta_Raw_Data'!$J:$J,'02_Meta_Raw_Data'!$F:$F,$A13) | H13: =SUMIFS('02_Meta_Raw_Data'!$P:$P,'02_Meta_Raw_Data'!$F:$F,$A13) | I13: =COUNTIFS('03_Prospects_CRM'!$P:$P,$A13) | J13: =COUNTIFS('03_Prospects_CRM'!$P:$P,$A13,'03_Prospects_CRM'!$T:$T,"MQL")+COUNTIFS('03_Prospects_CRM'!$P:$P,$A13,'03_Prospects_CRM'!$T:$T,"SQL")+COUNTIFS('03_Prospects_CRM'!$P:$P,$A13,'03_Prospects_CRM'!$T:$T,"Deal Won") | K13: =COUNTIFS('03_Prospects_CRM'!$P:$P,$A13,'03_Prospects_CRM'!$T:$T,"SQL")+COUNTIFS('03_Prospects_CRM'!$P:$P,$A13,'03_Prospects_CRM'!$T:$T,"Deal Won") | L13: =COUNTIFS('03_Prospects_CRM'!$P:$P,$A13,'03_Prospects_CRM'!$T:$T,"Deal Won") | M13: =COUNTIFS('03_Prospects_CRM'!$P:$P,$A13,'03_Prospects_CRM'!$T:$T,"Deal Lost") | N13: =SUMIFS('03_Prospects_CRM'!$X:$X,'03_Prospects_CRM'!$P:$P,$A13) | O13: =IFERROR(G13/I13,0) | P13: =IFERROR(G13/J13,0) | Q13: =IFERROR(G13/K13,0) | R13: =IFERROR(G13/L13,0) | S13: =IFERROR(N13/G13,0) | T13: =IFERROR(J13/I13,0) | U13: =IFERROR(K13/J13,0) | V13: =IFERROR(L13/K13,0)
A14: AD-020202 | B14: Demo Reel | Interest Tax Owners | C14: CMP-002 | D14: In2out - MessCampaign#2 - Testing - 20/4 | E14: AS-0202 | F14: In2out - MessCampaign#2 - Testing - 20/4 | Interest Tax Owners | G14: =SUMIFS('02_Meta_Raw_Data'!$J:$J,'02_Meta_Raw_Data'!$F:$F,$A14) | H14: =SUMIFS('02_Meta_Raw_Data'!$P:$P,'02_Meta_Raw_Data'!$F:$F,$A14) | I14: =COUNTIFS('03_Prospects_CRM'!$P:$P,$A14) | J14: =COUNTIFS('03_Prospects_CRM'!$P:$P,$A14,'03_Prospects_CRM'!$T:$T,"MQL")+COUNTIFS('03_Prospects_CRM'!$P:$P,$A14,'03_Prospects_CRM'!$T:$T,"SQL")+COUNTIFS('03_Prospects_CRM'!$P:$P,$A14,'03_Prospects_CRM'!$T:$T,"Deal Won") | K14: =COUNTIFS('03_Prospects_CRM'!$P:$P,$A14,'03_Prospects_CRM'!$T:$T,"SQL")+COUNTIFS('03_Prospects_CRM'!$P:$P,$A14,'03_Prospects_CRM'!$T:$T,"Deal Won") | L14: =COUNTIFS('03_Prospects_CRM'!$P:$P,$A14,'03_Prospects_CRM'!$T:$T,"Deal Won") | M14: =COUNTIFS('03_Prospects_CRM'!$P:$P,$A14,'03_Prospects_CRM'!$T:$T,"Deal Lost") | N14: =SUMIFS('03_Prospects_CRM'!$X:$X,'03_Prospects_CRM'!$P:$P,$A14) | O14: =IFERROR(G14/I14,0) | P14: =IFERROR(G14/J14,0) | Q14: =IFERROR(G14/K14,0) | R14: =IFERROR(G14/L14,0) | S14: =IFERROR(N14/G14,0) | T14: =IFERROR(J14/I14,0) | U14: =IFERROR(K14/J14,0) | V14: =IFERROR(L14/K14,0)
A15: AD-030101 | B15: Pain Point Static | Broad SMEs | C15: CMP-003 | D15: Mofawtar - E-Receipt - Awareness - Q2 | E15: AS-0301 | F15: Mofawtar - E-Receipt - Awareness - Q2 | Broad SMEs | G15: =SUMIFS('02_Meta_Raw_Data'!$J:$J,'02_Meta_Raw_Data'!$F:$F,$A15) | H15: =SUMIFS('02_Meta_Raw_Data'!$P:$P,'02_Meta_Raw_Data'!$F:$F,$A15) | I15: =COUNTIFS('03_Prospects_CRM'!$P:$P,$A15) | J15: =COUNTIFS('03_Prospects_CRM'!$P:$P,$A15,'03_Prospects_CRM'!$T:$T,"MQL")+COUNTIFS('03_Prospects_CRM'!$P:$P,$A15,'03_Prospects_CRM'!$T:$T,"SQL")+COUNTIFS('03_Prospects_CRM'!$P:$P,$A15,'03_Prospects_CRM'!$T:$T,"Deal Won") | K15: =COUNTIFS('03_Prospects_CRM'!$P:$P,$A15,'03_Prospects_CRM'!$T:$T,"SQL")+COUNTIFS('03_Prospects_CRM'!$P:$P,$A15,'03_Prospects_CRM'!$T:$T,"Deal Won") | L15: =COUNTIFS('03_Prospects_CRM'!$P:$P,$A15,'03_Prospects_CRM'!$T:$T,"Deal Won") | M15: =COUNTIFS('03_Prospects_CRM'!$P:$P,$A15,'03_Prospects_CRM'!$T:$T,"Deal Lost") | N15: =SUMIFS('03_Prospects_CRM'!$X:$X,'03_Prospects_CRM'!$P:$P,$A15) | O15: =IFERROR(G15/I15,0) | P15: =IFERROR(G15/J15,0) | Q15: =IFERROR(G15/K15,0) | R15: =IFERROR(G15/L15,0) | S15: =IFERROR(N15/G15,0) | T15: =IFERROR(J15/I15,0) | U15: =IFERROR(K15/J15,0) | V15: =IFERROR(L15/K15,0)
A16: AD-030102 | B16: Demo Reel | Broad SMEs | C16: CMP-003 | D16: Mofawtar - E-Receipt - Awareness - Q2 | E16: AS-0301 | F16: Mofawtar - E-Receipt - Awareness - Q2 | Broad SMEs | G16: =SUMIFS('02_Meta_Raw_Data'!$J:$J,'02_Meta_Raw_Data'!$F:$F,$A16) | H16: =SUMIFS('02_Meta_Raw_Data'!$P:$P,'02_Meta_Raw_Data'!$F:$F,$A16) | I16: =COUNTIFS('03_Prospects_CRM'!$P:$P,$A16) | J16: =COUNTIFS('03_Prospects_CRM'!$P:$P,$A16,'03_Prospects_CRM'!$T:$T,"MQL")+COUNTIFS('03_Prospects_CRM'!$P:$P,$A16,'03_Prospects_CRM'!$T:$T,"SQL")+COUNTIFS('03_Prospects_CRM'!$P:$P,$A16,'03_Prospects_CRM'!$T:$T,"Deal Won") | K16: =COUNTIFS('03_Prospects_CRM'!$P:$P,$A16,'03_Prospects_CRM'!$T:$T,"SQL")+COUNTIFS('03_Prospects_CRM'!$P:$P,$A16,'03_Prospects_CRM'!$T:$T,"Deal Won") | L16: =COUNTIFS('03_Prospects_CRM'!$P:$P,$A16,'03_Prospects_CRM'!$T:$T,"Deal Won") | M16: =COUNTIFS('03_Prospects_CRM'!$P:$P,$A16,'03_Prospects_CRM'!$T:$T,"Deal Lost") | N16: =SUMIFS('03_Prospects_CRM'!$X:$X,'03_Prospects_CRM'!$P:$P,$A16) | O16: =IFERROR(G16/I16,0) | P16: =IFERROR(G16/J16,0) | Q16: =IFERROR(G16/K16,0) | R16: =IFERROR(G16/L16,0) | S16: =IFERROR(N16/G16,0) | T16: =IFERROR(J16/I16,0) | U16: =IFERROR(K16/J16,0) | V16: =IFERROR(L16/K16,0)
... A33: AD-050302 | B33: Demo Reel | Retargeting Visitors | C33: CMP-005 | D33: Mofawtar - Retargeting - Demo Booking - Q2 | E33: AS-0503 | F33: Mofawtar - Retargeting - Demo Booking - Q2 | Retargeting Visitors | G33: =SUMIFS('02_Meta_Raw_Data'!$J:$J,'02_Meta_Raw_Data'!$F:$F,$A33) | H33: =SUMIFS('02_Meta_Raw_Data'!$P:$P,'02_Meta_Raw_Data'!$F:$F,$A33) | I33: =COUNTIFS('03_Prospects_CRM'!$P:$P,$A33) | J33: =COUNTIFS('03_Prospects_CRM'!$P:$P,$A33,'03_Prospects_CRM'!$T:$T,"MQL")+COUNTIFS('03_Prospects_CRM'!$P:$P,$A33,'03_Prospects_CRM'!$T:$T,"SQL")+COUNTIFS('03_Prospects_CRM'!$P:$P,$A33,'03_Prospects_CRM'!$T:$T,"Deal Won") | K33: =COUNTIFS('03_Prospects_CRM'!$P:$P,$A33,'03_Prospects_CRM'!$T:$T,"SQL")+COUNTIFS('03_Prospects_CRM'!$P:$P,$A33,'03_Prospects_CRM'!$T:$T,"Deal Won") | L33: =COUNTIFS('03_Prospects_CRM'!$P:$P,$A33,'03_Prospects_CRM'!$T:$T,"Deal Won") | M33: =COUNTIFS('03_Prospects_CRM'!$P:$P,$A33,'03_Prospects_CRM'!$T:$T,"Deal Lost") | N33: =SUMIFS('03_Prospects_CRM'!$X:$X,'03_Prospects_CRM'!$P:$P,$A33) | O33: =IFERROR(G33/I33,0) | P33: =IFERROR(G33/J33,0) | Q33: =IFERROR(G33/K33,0) | R33: =IFERROR(G33/L33,0) | S33: =IFERROR(N33/G33,0) | T33: =IFERROR(J33/I33,0) | U33: =IFERROR(K33/J33,0) | V33: =IFERROR(L33/K33,0)

Sheet 10_Weekly_Tracker
A1: 10 Weekly Tracker
A2: Time-based rollup for management reporting.
A4: Period | B4: Start Date | C4: End Date | D4: Spend | E4: Conversations | F4: CRM Leads | G4: MQL | H4: SQL | I4: Deals Won | J4: Revenue | K4: CPL | L4: CAC | M4: ROAS | N4: Lead→MQL | O4: MQL→SQL | P4: SQL→Deal | Q4: SLA Met %
A5: W14 2026 | B5: 46113 | C5: 46117 | D5: =SUMIFS('05_Daily_Funnel'!$C:$C,'05_Daily_Funnel'!$A:$A,">="&$B5,'05_Daily_Funnel'!$A:$A,"<="&$C5) | E5: =SUMIFS('05_Daily_Funnel'!$D:$D,'05_Daily_Funnel'!$A:$A,">="&$B5,'05_Daily_Funnel'!$A:$A,"<="&$C5) | F5: =SUMIFS('05_Daily_Funnel'!$E:$E,'05_Daily_Funnel'!$A:$A,">="&$B5,'05_Daily_Funnel'!$A:$A,"<="&$C5) | G5: =SUMIFS('05_Daily_Funnel'!$F:$F,'05_Daily_Funnel'!$A:$A,">="&$B5,'05_Daily_Funnel'!$A:$A,"<="&$C5) | H5: =SUMIFS('05_Daily_Funnel'!$G:$G,'05_Daily_Funnel'!$A:$A,">="&$B5,'05_Daily_Funnel'!$A:$A,"<="&$C5) | I5: =SUMIFS('05_Daily_Funnel'!$H:$H,'05_Daily_Funnel'!$A:$A,">="&$B5,'05_Daily_Funnel'!$A:$A,"<="&$C5) | J5: =SUMIFS('05_Daily_Funnel'!$J:$J,'05_Daily_Funnel'!$A:$A,">="&$B5,'05_Daily_Funnel'!$A:$A,"<="&$C5) | K5: =IFERROR(D5/F5,0) | L5: =IFERROR(D5/I5,0) | M5: =IFERROR(J5/D5,0) | N5: =IFERROR(G5/F5,0) | O5: =IFERROR(H5/G5,0) | P5: =IFERROR(I5/H5,0) | Q5: =IFERROR(SUMPRODUCT(('05_Daily_Funnel'!$A$5:$A$95>=$B5)*('05_Daily_Funnel'!$A$5:$A$95<=$C5)*('05_Daily_Funnel'!$E$5:$E$95)*('05_Daily_Funnel'!$Q$5:$Q$95))/F5,0)
A6: W15 2026 | B6: 46118 | C6: 46124 | D6: =SUMIFS('05_Daily_Funnel'!$C:$C,'05_Daily_Funnel'!$A:$A,">="&$B6,'05_Daily_Funnel'!$A:$A,"<="&$C6) | E6: =SUMIFS('05_Daily_Funnel'!$D:$D,'05_Daily_Funnel'!$A:$A,">="&$B6,'05_Daily_Funnel'!$A:$A,"<="&$C6) | F6: =SUMIFS('05_Daily_Funnel'!$E:$E,'05_Daily_Funnel'!$A:$A,">="&$B6,'05_Daily_Funnel'!$A:$A,"<="&$C6) | G6: =SUMIFS('05_Daily_Funnel'!$F:$F,'05_Daily_Funnel'!$A:$A,">="&$B6,'05_Daily_Funnel'!$A:$A,"<="&$C6) | H6: =SUMIFS('05_Daily_Funnel'!$G:$G,'05_Daily_Funnel'!$A:$A,">="&$B6,'05_Daily_Funnel'!$A:$A,"<="&$C6) | I6: =SUMIFS('05_Daily_Funnel'!$H:$H,'05_Daily_Funnel'!$A:$A,">="&$B6,'05_Daily_Funnel'!$A:$A,"<="&$C6) | J6: =SUMIFS('05_Daily_Funnel'!$J:$J,'05_Daily_Funnel'!$A:$A,">="&$B6,'05_Daily_Funnel'!$A:$A,"<="&$C6) | K6: =IFERROR(D6/F6,0) | L6: =IFERROR(D6/I6,0) | M6: =IFERROR(J6/D6,0) | N6: =IFERROR(G6/F6,0) | O6: =IFERROR(H6/G6,0) | P6: =IFERROR(I6/H6,0) | Q6: =IFERROR(SUMPRODUCT(('05_Daily_Funnel'!$A$5:$A$95>=$B6)*('05_Daily_Funnel'!$A$5:$A$95<=$C6)*('05_Daily_Funnel'!$E$5:$E$95)*('05_Daily_Funnel'!$Q$5:$Q$95))/F6,0)
A7: W16 2026 | B7: 46125 | C7: 46131 | D7: =SUMIFS('05_Daily_Funnel'!$C:$C,'05_Daily_Funnel'!$A:$A,">="&$B7,'05_Daily_Funnel'!$A:$A,"<="&$C7) | E7: =SUMIFS('05_Daily_Funnel'!$D:$D,'05_Daily_Funnel'!$A:$A,">="&$B7,'05_Daily_Funnel'!$A:$A,"<="&$C7) | F7: =SUMIFS('05_Daily_Funnel'!$E:$E,'05_Daily_Funnel'!$A:$A,">="&$B7,'05_Daily_Funnel'!$A:$A,"<="&$C7) | G7: =SUMIFS('05_Daily_Funnel'!$F:$F,'05_Daily_Funnel'!$A:$A,">="&$B7,'05_Daily_Funnel'!$A:$A,"<="&$C7) | H7: =SUMIFS('05_Daily_Funnel'!$G:$G,'05_Daily_Funnel'!$A:$A,">="&$B7,'05_Daily_Funnel'!$A:$A,"<="&$C7) | I7: =SUMIFS('05_Daily_Funnel'!$H:$H,'05_Daily_Funnel'!$A:$A,">="&$B7,'05_Daily_Funnel'!$A:$A,"<="&$C7) | J7: =SUMIFS('05_Daily_Funnel'!$J:$J,'05_Daily_Funnel'!$A:$A,">="&$B7,'05_Daily_Funnel'!$A:$A,"<="&$C7) | K7: =IFERROR(D7/F7,0) | L7: =IFERROR(D7/I7,0) | M7: =IFERROR(J7/D7,0) | N7: =IFERROR(G7/F7,0) | O7: =IFERROR(H7/G7,0) | P7: =IFERROR(I7/H7,0) | Q7: =IFERROR(SUMPRODUCT(('05_Daily_Funnel'!$A$5:$A$95>=$B7)*('05_Daily_Funnel'!$A$5:$A$95<=$C7)*('05_Daily_Funnel'!$E$5:$E$95)*('05_Daily_Funnel'!$Q$5:$Q$95))/F7,0)
A8: W17 2026 | B8: 46132 | C8: 46138 | D8: =SUMIFS('05_Daily_Funnel'!$C:$C,'05_Daily_Funnel'!$A:$A,">="&$B8,'05_Daily_Funnel'!$A:$A,"<="&$C8) | E8: =SUMIFS('05_Daily_Funnel'!$D:$D,'05_Daily_Funnel'!$A:$A,">="&$B8,'05_Daily_Funnel'!$A:$A,"<="&$C8) | F8: =SUMIFS('05_Daily_Funnel'!$E:$E,'05_Daily_Funnel'!$A:$A,">="&$B8,'05_Daily_Funnel'!$A:$A,"<="&$C8) | G8: =SUMIFS('05_Daily_Funnel'!$F:$F,'05_Daily_Funnel'!$A:$A,">="&$B8,'05_Daily_Funnel'!$A:$A,"<="&$C8) | H8: =SUMIFS('05_Daily_Funnel'!$G:$G,'05_Daily_Funnel'!$A:$A,">="&$B8,'05_Daily_Funnel'!$A:$A,"<="&$C8) | I8: =SUMIFS('05_Daily_Funnel'!$H:$H,'05_Daily_Funnel'!$A:$A,">="&$B8,'05_Daily_Funnel'!$A:$A,"<="&$C8) | J8: =SUMIFS('05_Daily_Funnel'!$J:$J,'05_Daily_Funnel'!$A:$A,">="&$B8,'05_Daily_Funnel'!$A:$A,"<="&$C8) | K8: =IFERROR(D8/F8,0) | L8: =IFERROR(D8/I8,0) | M8: =IFERROR(J8/D8,0) | N8: =IFERROR(G8/F8,0) | O8: =IFERROR(H8/G8,0) | P8: =IFERROR(I8/H8,0) | Q8: =IFERROR(SUMPRODUCT(('05_Daily_Funnel'!$A$5:$A$95>=$B8)*('05_Daily_Funnel'!$A$5:$A$95<=$C8)*('05_Daily_Funnel'!$E$5:$E$95)*('05_Daily_Funnel'!$Q$5:$Q$95))/F8,0)
A9: W18 2026 | B9: 46139 | C9: 46145 | D9: =SUMIFS('05_Daily_Funnel'!$C:$C,'05_Daily_Funnel'!$A:$A,">="&$B9,'05_Daily_Funnel'!$A:$A,"<="&$C9) | E9: =SUMIFS('05_Daily_Funnel'!$D:$D,'05_Daily_Funnel'!$A:$A,">="&$B9,'05_Daily_Funnel'!$A:$A,"<="&$C9) | F9: =SUMIFS('05_Daily_Funnel'!$E:$E,'05_Daily_Funnel'!$A:$A,">="&$B9,'05_Daily_Funnel'!$A:$A,"<="&$C9) | G9: =SUMIFS('05_Daily_Funnel'!$F:$F,'05_Daily_Funnel'!$A:$A,">="&$B9,'05_Daily_Funnel'!$A:$A,"<="&$C9) | H9: =SUMIFS('05_Daily_Funnel'!$G:$G,'05_Daily_Funnel'!$A:$A,">="&$B9,'05_Daily_Funnel'!$A:$A,"<="&$C9) | I9: =SUMIFS('05_Daily_Funnel'!$H:$H,'05_Daily_Funnel'!$A:$A,">="&$B9,'05_Daily_Funnel'!$A:$A,"<="&$C9) | J9: =SUMIFS('05_Daily_Funnel'!$J:$J,'05_Daily_Funnel'!$A:$A,">="&$B9,'05_Daily_Funnel'!$A:$A,"<="&$C9) | K9: =IFERROR(D9/F9,0) | L9: =IFERROR(D9/I9,0) | M9: =IFERROR(J9/D9,0) | N9: =IFERROR(G9/F9,0) | O9: =IFERROR(H9/G9,0) | P9: =IFERROR(I9/H9,0) | Q9: =IFERROR(SUMPRODUCT(('05_Daily_Funnel'!$A$5:$A$95>=$B9)*('05_Daily_Funnel'!$A$5:$A$95<=$C9)*('05_Daily_Funnel'!$E$5:$E$95)*('05_Daily_Funnel'!$Q$5:$Q$95))/F9,0)
A10: W19 2026 | B10: 46146 | C10: 46152 | D10: =SUMIFS('05_Daily_Funnel'!$C:$C,'05_Daily_Funnel'!$A:$A,">="&$B10,'05_Daily_Funnel'!$A:$A,"<="&$C10) | E10: =SUMIFS('05_Daily_Funnel'!$D:$D,'05_Daily_Funnel'!$A:$A,">="&$B10,'05_Daily_Funnel'!$A:$A,"<="&$C10) | F10: =SUMIFS('05_Daily_Funnel'!$E:$E,'05_Daily_Funnel'!$A:$A,">="&$B10,'05_Daily_Funnel'!$A:$A,"<="&$C10) | G10: =SUMIFS('05_Daily_Funnel'!$F:$F,'05_Daily_Funnel'!$A:$A,">="&$B10,'05_Daily_Funnel'!$A:$A,"<="&$C10) | H10: =SUMIFS('05_Daily_Funnel'!$G:$G,'05_Daily_Funnel'!$A:$A,">="&$B10,'05_Daily_Funnel'!$A:$A,"<="&$C10) | I10: =SUMIFS('05_Daily_Funnel'!$H:$H,'05_Daily_Funnel'!$A:$A,">="&$B10,'05_Daily_Funnel'!$A:$A,"<="&$C10) | J10: =SUMIFS('05_Daily_Funnel'!$J:$J,'05_Daily_Funnel'!$A:$A,">="&$B10,'05_Daily_Funnel'!$A:$A,"<="&$C10) | K10: =IFERROR(D10/F10,0) | L10: =IFERROR(D10/I10,0) | M10: =IFERROR(J10/D10,0) | N10: =IFERROR(G10/F10,0) | O10: =IFERROR(H10/G10,0) | P10: =IFERROR(I10/H10,0) | Q10: =IFERROR(SUMPRODUCT(('05_Daily_Funnel'!$A$5:$A$95>=$B10)*('05_Daily_Funnel'!$A$5:$A$95<=$C10)*('05_Daily_Funnel'!$E$5:$E$95)*('05_Daily_Funnel'!$Q$5:$Q$95))/F10,0)
A11: W20 2026 | B11: 46153 | C11: 46159 | D11: =SUMIFS('05_Daily_Funnel'!$C:$C,'05_Daily_Funnel'!$A:$A,">="&$B11,'05_Daily_Funnel'!$A:$A,"<="&$C11) | E11: =SUMIFS('05_Daily_Funnel'!$D:$D,'05_Daily_Funnel'!$A:$A,">="&$B11,'05_Daily_Funnel'!$A:$A,"<="&$C11) | F11: =SUMIFS('05_Daily_Funnel'!$E:$E,'05_Daily_Funnel'!$A:$A,">="&$B11,'05_Daily_Funnel'!$A:$A,"<="&$C11) | G11: =SUMIFS('05_Daily_Funnel'!$F:$F,'05_Daily_Funnel'!$A:$A,">="&$B11,'05_Daily_Funnel'!$A:$A,"<="&$C11) | H11: =SUMIFS('05_Daily_Funnel'!$G:$G,'05_Daily_Funnel'!$A:$A,">="&$B11,'05_Daily_Funnel'!$A:$A,"<="&$C11) | I11: =SUMIFS('05_Daily_Funnel'!$H:$H,'05_Daily_Funnel'!$A:$A,">="&$B11,'05_Daily_Funnel'!$A:$A,"<="&$C11) | J11: =SUMIFS('05_Daily_Funnel'!$J:$J,'05_Daily_Funnel'!$A:$A,">="&$B11,'05_Daily_Funnel'!$A:$A,"<="&$C11) | K11: =IFERROR(D11/F11,0) | L11: =IFERROR(D11/I11,0) | M11: =IFERROR(J11/D11,0) | N11: =IFERROR(G11/F11,0) | O11: =IFERROR(H11/G11,0) | P11: =IFERROR(I11/H11,0) | Q11: =IFERROR(SUMPRODUCT(('05_Daily_Funnel'!$A$5:$A$95>=$B11)*('05_Daily_Funnel'!$A$5:$A$95<=$C11)*('05_Daily_Funnel'!$E$5:$E$95)*('05_Daily_Funnel'!$Q$5:$Q$95))/F11,0)
A12: W21 2026 | B12: 46160 | C12: 46166 | D12: =SUMIFS('05_Daily_Funnel'!$C:$C,'05_Daily_Funnel'!$A:$A,">="&$B12,'05_Daily_Funnel'!$A:$A,"<="&$C12) | E12: =SUMIFS('05_Daily_Funnel'!$D:$D,'05_Daily_Funnel'!$A:$A,">="&$B12,'05_Daily_Funnel'!$A:$A,"<="&$C12) | F12: =SUMIFS('05_Daily_Funnel'!$E:$E,'05_Daily_Funnel'!$A:$A,">="&$B12,'05_Daily_Funnel'!$A:$A,"<="&$C12) | G12: =SUMIFS('05_Daily_Funnel'!$F:$F,'05_Daily_Funnel'!$A:$A,">="&$B12,'05_Daily_Funnel'!$A:$A,"<="&$C12) | H12: =SUMIFS('05_Daily_Funnel'!$G:$G,'05_Daily_Funnel'!$A:$A,">="&$B12,'05_Daily_Funnel'!$A:$A,"<="&$C12) | I12: =SUMIFS('05_Daily_Funnel'!$H:$H,'05_Daily_Funnel'!$A:$A,">="&$B12,'05_Daily_Funnel'!$A:$A,"<="&$C12) | J12: =SUMIFS('05_Daily_Funnel'!$J:$J,'05_Daily_Funnel'!$A:$A,">="&$B12,'05_Daily_Funnel'!$A:$A,"<="&$C12) | K12: =IFERROR(D12/F12,0) | L12: =IFERROR(D12/I12,0) | M12: =IFERROR(J12/D12,0) | N12: =IFERROR(G12/F12,0) | O12: =IFERROR(H12/G12,0) | P12: =IFERROR(I12/H12,0) | Q12: =IFERROR(SUMPRODUCT(('05_Daily_Funnel'!$A$5:$A$95>=$B12)*('05_Daily_Funnel'!$A$5:$A$95<=$C12)*('05_Daily_Funnel'!$E$5:$E$95)*('05_Daily_Funnel'!$Q$5:$Q$95))/F12,0)
A13: W22 2026 | B13: 46167 | C13: 46173 | D13: =SUMIFS('05_Daily_Funnel'!$C:$C,'05_Daily_Funnel'!$A:$A,">="&$B13,'05_Daily_Funnel'!$A:$A,"<="&$C13) | E13: =SUMIFS('05_Daily_Funnel'!$D:$D,'05_Daily_Funnel'!$A:$A,">="&$B13,'05_Daily_Funnel'!$A:$A,"<="&$C13) | F13: =SUMIFS('05_Daily_Funnel'!$E:$E,'05_Daily_Funnel'!$A:$A,">="&$B13,'05_Daily_Funnel'!$A:$A,"<="&$C13) | G13: =SUMIFS('05_Daily_Funnel'!$F:$F,'05_Daily_Funnel'!$A:$A,">="&$B13,'05_Daily_Funnel'!$A:$A,"<="&$C13) | H13: =SUMIFS('05_Daily_Funnel'!$G:$G,'05_Daily_Funnel'!$A:$A,">="&$B13,'05_Daily_Funnel'!$A:$A,"<="&$C13) | I13: =SUMIFS('05_Daily_Funnel'!$H:$H,'05_Daily_Funnel'!$A:$A,">="&$B13,'05_Daily_Funnel'!$A:$A,"<="&$C13) | J13: =SUMIFS('05_Daily_Funnel'!$J:$J,'05_Daily_Funnel'!$A:$A,">="&$B13,'05_Daily_Funnel'!$A:$A,"<="&$C13) | K13: =IFERROR(D13/F13,0) | L13: =IFERROR(D13/I13,0) | M13: =IFERROR(J13/D13,0) | N13: =IFERROR(G13/F13,0) | O13: =IFERROR(H13/G13,0) | P13: =IFERROR(I13/H13,0) | Q13: =IFERROR(SUMPRODUCT(('05_Daily_Funnel'!$A$5:$A$95>=$B13)*('05_Daily_Funnel'!$A$5:$A$95<=$C13)*('05_Daily_Funnel'!$E$5:$E$95)*('05_Daily_Funnel'!$Q$5:$Q$95))/F13,0)
A14: W23 2026 | B14: 46174 | C14: 46180 | D14: =SUMIFS('05_Daily_Funnel'!$C:$C,'05_Daily_Funnel'!$A:$A,">="&$B14,'05_Daily_Funnel'!$A:$A,"<="&$C14) | E14: =SUMIFS('05_Daily_Funnel'!$D:$D,'05_Daily_Funnel'!$A:$A,">="&$B14,'05_Daily_Funnel'!$A:$A,"<="&$C14) | F14: =SUMIFS('05_Daily_Funnel'!$E:$E,'05_Daily_Funnel'!$A:$A,">="&$B14,'05_Daily_Funnel'!$A:$A,"<="&$C14) | G14: =SUMIFS('05_Daily_Funnel'!$F:$F,'05_Daily_Funnel'!$A:$A,">="&$B14,'05_Daily_Funnel'!$A:$A,"<="&$C14) | H14: =SUMIFS('05_Daily_Funnel'!$G:$G,'05_Daily_Funnel'!$A:$A,">="&$B14,'05_Daily_Funnel'!$A:$A,"<="&$C14) | I14: =SUMIFS('05_Daily_Funnel'!$H:$H,'05_Daily_Funnel'!$A:$A,">="&$B14,'05_Daily_Funnel'!$A:$A,"<="&$C14) | J14: =SUMIFS('05_Daily_Funnel'!$J:$J,'05_Daily_Funnel'!$A:$A,">="&$B14,'05_Daily_Funnel'!$A:$A,"<="&$C14) | K14: =IFERROR(D14/F14,0) | L14: =IFERROR(D14/I14,0) | M14: =IFERROR(J14/D14,0) | N14: =IFERROR(G14/F14,0) | O14: =IFERROR(H14/G14,0) | P14: =IFERROR(I14/H14,0) | Q14: =IFERROR(SUMPRODUCT(('05_Daily_Funnel'!$A$5:$A$95>=$B14)*('05_Daily_Funnel'!$A$5:$A$95<=$C14)*('05_Daily_Funnel'!$E$5:$E$95)*('05_Daily_Funnel'!$Q$5:$Q$95))/F14,0)
A15: W24 2026 | B15: 46181 | C15: 46187 | D15: =SUMIFS('05_Daily_Funnel'!$C:$C,'05_Daily_Funnel'!$A:$A,">="&$B15,'05_Daily_Funnel'!$A:$A,"<="&$C15) | E15: =SUMIFS('05_Daily_Funnel'!$D:$D,'05_Daily_Funnel'!$A:$A,">="&$B15,'05_Daily_Funnel'!$A:$A,"<="&$C15) | F15: =SUMIFS('05_Daily_Funnel'!$E:$E,'05_Daily_Funnel'!$A:$A,">="&$B15,'05_Daily_Funnel'!$A:$A,"<="&$C15) | G15: =SUMIFS('05_Daily_Funnel'!$F:$F,'05_Daily_Funnel'!$A:$A,">="&$B15,'05_Daily_Funnel'!$A:$A,"<="&$C15) | H15: =SUMIFS('05_Daily_Funnel'!$G:$G,'05_Daily_Funnel'!$A:$A,">="&$B15,'05_Daily_Funnel'!$A:$A,"<="&$C15) | I15: =SUMIFS('05_Daily_Funnel'!$H:$H,'05_Daily_Funnel'!$A:$A,">="&$B15,'05_Daily_Funnel'!$A:$A,"<="&$C15) | J15: =SUMIFS('05_Daily_Funnel'!$J:$J,'05_Daily_Funnel'!$A:$A,">="&$B15,'05_Daily_Funnel'!$A:$A,"<="&$C15) | K15: =IFERROR(D15/F15,0) | L15: =IFERROR(D15/I15,0) | M15: =IFERROR(J15/D15,0) | N15: =IFERROR(G15/F15,0) | O15: =IFERROR(H15/G15,0) | P15: =IFERROR(I15/H15,0) | Q15: =IFERROR(SUMPRODUCT(('05_Daily_Funnel'!$A$5:$A$95>=$B15)*('05_Daily_Funnel'!$A$5:$A$95<=$C15)*('05_Daily_Funnel'!$E$5:$E$95)*('05_Daily_Funnel'!$Q$5:$Q$95))/F15,0)
A16: W25 2026 | B16: 46188 | C16: 46194 | D16: =SUMIFS('05_Daily_Funnel'!$C:$C,'05_Daily_Funnel'!$A:$A,">="&$B16,'05_Daily_Funnel'!$A:$A,"<="&$C16) | E16: =SUMIFS('05_Daily_Funnel'!$D:$D,'05_Daily_Funnel'!$A:$A,">="&$B16,'05_Daily_Funnel'!$A:$A,"<="&$C16) | F16: =SUMIFS('05_Daily_Funnel'!$E:$E,'05_Daily_Funnel'!$A:$A,">="&$B16,'05_Daily_Funnel'!$A:$A,"<="&$C16) | G16: =SUMIFS('05_Daily_Funnel'!$F:$F,'05_Daily_Funnel'!$A:$A,">="&$B16,'05_Daily_Funnel'!$A:$A,"<="&$C16) | H16: =SUMIFS('05_Daily_Funnel'!$G:$G,'05_Daily_Funnel'!$A:$A,">="&$B16,'05_Daily_Funnel'!$A:$A,"<="&$C16) | I16: =SUMIFS('05_Daily_Funnel'!$H:$H,'05_Daily_Funnel'!$A:$A,">="&$B16,'05_Daily_Funnel'!$A:$A,"<="&$C16) | J16: =SUMIFS('05_Daily_Funnel'!$J:$J,'05_Daily_Funnel'!$A:$A,">="&$B16,'05_Daily_Funnel'!$A:$A,"<="&$C16) | K16: =IFERROR(D16/F16,0) | L16: =IFERROR(D16/I16,0) | M16: =IFERROR(J16/D16,0) | N16: =IFERROR(G16/F16,0) | O16: =IFERROR(H16/G16,0) | P16: =IFERROR(I16/H16,0) | Q16: =IFERROR(SUMPRODUCT(('05_Daily_Funnel'!$A$5:$A$95>=$B16)*('05_Daily_Funnel'!$A$5:$A$95<=$C16)*('05_Daily_Funnel'!$E$5:$E$95)*('05_Daily_Funnel'!$Q$5:$Q$95))/F16,0)
... A18: W27 2026 | B18: 46202 | C18: 46203 | D18: =SUMIFS('05_Daily_Funnel'!$C:$C,'05_Daily_Funnel'!$A:$A,">="&$B18,'05_Daily_Funnel'!$A:$A,"<="&$C18) | E18: =SUMIFS('05_Daily_Funnel'!$D:$D,'05_Daily_Funnel'!$A:$A,">="&$B18,'05_Daily_Funnel'!$A:$A,"<="&$C18) | F18: =SUMIFS('05_Daily_Funnel'!$E:$E,'05_Daily_Funnel'!$A:$A,">="&$B18,'05_Daily_Funnel'!$A:$A,"<="&$C18) | G18: =SUMIFS('05_Daily_Funnel'!$F:$F,'05_Daily_Funnel'!$A:$A,">="&$B18,'05_Daily_Funnel'!$A:$A,"<="&$C18) | H18: =SUMIFS('05_Daily_Funnel'!$G:$G,'05_Daily_Funnel'!$A:$A,">="&$B18,'05_Daily_Funnel'!$A:$A,"<="&$C18) | I18: =SUMIFS('05_Daily_Funnel'!$H:$H,'05_Daily_Funnel'!$A:$A,">="&$B18,'05_Daily_Funnel'!$A:$A,"<="&$C18) | J18: =SUMIFS('05_Daily_Funnel'!$J:$J,'05_Daily_Funnel'!$A:$A,">="&$B18,'05_Daily_Funnel'!$A:$A,"<="&$C18) | K18: =IFERROR(D18/F18,0) | L18: =IFERROR(D18/I18,0) | M18: =IFERROR(J18/D18,0) | N18: =IFERROR(G18/F18,0) | O18: =IFERROR(H18/G18,0) | P18: =IFERROR(I18/H18,0) | Q18: =IFERROR(SUMPRODUCT(('05_Daily_Funnel'!$A$5:$A$95>=$B18)*('05_Daily_Funnel'!$A$5:$A$95<=$C18)*('05_Daily_Funnel'!$E$5:$E$95)*('05_Daily_Funnel'!$Q$5:$Q$95))/F18,0)

Sheet 11_Monthly_Tracker
A1: 11 Monthly Tracker
A2: Time-based rollup for management reporting.
A4: Period | B4: Start Date | C4: End Date | D4: Spend | E4: Conversations | F4: CRM Leads | G4: MQL | H4: SQL | I4: Deals Won | J4: Revenue | K4: CPL | L4: CAC | M4: ROAS | N4: Lead→MQL | O4: MQL→SQL | P4: SQL→Deal | Q4: SLA Met %
A5: Apr 2026 | B5: 46113 | C5: 46142 | D5: =SUMIFS('05_Daily_Funnel'!$C:$C,'05_Daily_Funnel'!$A:$A,">="&$B5,'05_Daily_Funnel'!$A:$A,"<="&$C5) | E5: =SUMIFS('05_Daily_Funnel'!$D:$D,'05_Daily_Funnel'!$A:$A,">="&$B5,'05_Daily_Funnel'!$A:$A,"<="&$C5) | F5: =SUMIFS('05_Daily_Funnel'!$E:$E,'05_Daily_Funnel'!$A:$A,">="&$B5,'05_Daily_Funnel'!$A:$A,"<="&$C5) | G5: =SUMIFS('05_Daily_Funnel'!$F:$F,'05_Daily_Funnel'!$A:$A,">="&$B5,'05_Daily_Funnel'!$A:$A,"<="&$C5) | H5: =SUMIFS('05_Daily_Funnel'!$G:$G,'05_Daily_Funnel'!$A:$A,">="&$B5,'05_Daily_Funnel'!$A:$A,"<="&$C5) | I5: =SUMIFS('05_Daily_Funnel'!$H:$H,'05_Daily_Funnel'!$A:$A,">="&$B5,'05_Daily_Funnel'!$A:$A,"<="&$C5) | J5: =SUMIFS('05_Daily_Funnel'!$J:$J,'05_Daily_Funnel'!$A:$A,">="&$B5,'05_Daily_Funnel'!$A:$A,"<="&$C5) | K5: =IFERROR(D5/F5,0) | L5: =IFERROR(D5/I5,0) | M5: =IFERROR(J5/D5,0) | N5: =IFERROR(G5/F5,0) | O5: =IFERROR(H5/G5,0) | P5: =IFERROR(I5/H5,0) | Q5: =IFERROR(SUMPRODUCT(('05_Daily_Funnel'!$A$5:$A$95>=$B5)*('05_Daily_Funnel'!$A$5:$A$95<=$C5)*('05_Daily_Funnel'!$E$5:$E$95)*('05_Daily_Funnel'!$Q$5:$Q$95))/F5,0)
A6: May 2026 | B6: 46143 | C6: 46173 | D6: =SUMIFS('05_Daily_Funnel'!$C:$C,'05_Daily_Funnel'!$A:$A,">="&$B6,'05_Daily_Funnel'!$A:$A,"<="&$C6) | E6: =SUMIFS('05_Daily_Funnel'!$D:$D,'05_Daily_Funnel'!$A:$A,">="&$B6,'05_Daily_Funnel'!$A:$A,"<="&$C6) | F6: =SUMIFS('05_Daily_Funnel'!$E:$E,'05_Daily_Funnel'!$A:$A,">="&$B6,'05_Daily_Funnel'!$A:$A,"<="&$C6) | G6: =SUMIFS('05_Daily_Funnel'!$F:$F,'05_Daily_Funnel'!$A:$A,">="&$B6,'05_Daily_Funnel'!$A:$A,"<="&$C6) | H6: =SUMIFS('05_Daily_Funnel'!$G:$G,'05_Daily_Funnel'!$A:$A,">="&$B6,'05_Daily_Funnel'!$A:$A,"<="&$C6) | I6: =SUMIFS('05_Daily_Funnel'!$H:$H,'05_Daily_Funnel'!$A:$A,">="&$B6,'05_Daily_Funnel'!$A:$A,"<="&$C6) | J6: =SUMIFS('05_Daily_Funnel'!$J:$J,'05_Daily_Funnel'!$A:$A,">="&$B6,'05_Daily_Funnel'!$A:$A,"<="&$C6) | K6: =IFERROR(D6/F6,0) | L6: =IFERROR(D6/I6,0) | M6: =IFERROR(J6/D6,0) | N6: =IFERROR(G6/F6,0) | O6: =IFERROR(H6/G6,0) | P6: =IFERROR(I6/H6,0) | Q6: =IFERROR(SUMPRODUCT(('05_Daily_Funnel'!$A$5:$A$95>=$B6)*('05_Daily_Funnel'!$A$5:$A$95<=$C6)*('05_Daily_Funnel'!$E$5:$E$95)*('05_Daily_Funnel'!$Q$5:$Q$95))/F6,0)
A7: Jun 2026 | B7: 46174 | C7: 46203 | D7: =SUMIFS('05_Daily_Funnel'!$C:$C,'05_Daily_Funnel'!$A:$A,">="&$B7,'05_Daily_Funnel'!$A:$A,"<="&$C7) | E7: =SUMIFS('05_Daily_Funnel'!$D:$D,'05_Daily_Funnel'!$A:$A,">="&$B7,'05_Daily_Funnel'!$A:$A,"<="&$C7) | F7: =SUMIFS('05_Daily_Funnel'!$E:$E,'05_Daily_Funnel'!$A:$A,">="&$B7,'05_Daily_Funnel'!$A:$A,"<="&$C7) | G7: =SUMIFS('05_Daily_Funnel'!$F:$F,'05_Daily_Funnel'!$A:$A,">="&$B7,'05_Daily_Funnel'!$A:$A,"<="&$C7) | H7: =SUMIFS('05_Daily_Funnel'!$G:$G,'05_Daily_Funnel'!$A:$A,">="&$B7,'05_Daily_Funnel'!$A:$A,"<="&$C7) | I7: =SUMIFS('05_Daily_Funnel'!$H:$H,'05_Daily_Funnel'!$A:$A,">="&$B7,'05_Daily_Funnel'!$A:$A,"<="&$C7) | J7: =SUMIFS('05_Daily_Funnel'!$J:$J,'05_Daily_Funnel'!$A:$A,">="&$B7,'05_Daily_Funnel'!$A:$A,"<="&$C7) | K7: =IFERROR(D7/F7,0) | L7: =IFERROR(D7/I7,0) | M7: =IFERROR(J7/D7,0) | N7: =IFERROR(G7/F7,0) | O7: =IFERROR(H7/G7,0) | P7: =IFERROR(I7/H7,0) | Q7: =IFERROR(SUMPRODUCT(('05_Daily_Funnel'!$A$5:$A$95>=$B7)*('05_Daily_Funnel'!$A$5:$A$95<=$C7)*('05_Daily_Funnel'!$E$5:$E$95)*('05_Daily_Funnel'!$Q$5:$Q$95))/F7,0)

Sheet 12_Quarterly_Tracker
A1: 12 Quarterly Tracker
A2: Time-based rollup for management reporting.
A4: Period | B4: Start Date | C4: End Date | D4: Spend | E4: Conversations | F4: CRM Leads | G4: MQL | H4: SQL | I4: Deals Won | J4: Revenue | K4: CPL | L4: CAC | M4: ROAS | N4: Lead→MQL | O4: MQL→SQL | P4: SQL→Deal | Q4: SLA Met %
A5: Q2 2026 | B5: 46113 | C5: 46203 | D5: =SUMIFS('05_Daily_Funnel'!$C:$C,'05_Daily_Funnel'!$A:$A,">="&$B5,'05_Daily_Funnel'!$A:$A,"<="&$C5) | E5: =SUMIFS('05_Daily_Funnel'!$D:$D,'05_Daily_Funnel'!$A:$A,">="&$B5,'05_Daily_Funnel'!$A:$A,"<="&$C5) | F5: =SUMIFS('05_Daily_Funnel'!$E:$E,'05_Daily_Funnel'!$A:$A,">="&$B5,'05_Daily_Funnel'!$A:$A,"<="&$C5) | G5: =SUMIFS('05_Daily_Funnel'!$F:$F,'05_Daily_Funnel'!$A:$A,">="&$B5,'05_Daily_Funnel'!$A:$A,"<="&$C5) | H5: =SUMIFS('05_Daily_Funnel'!$G:$G,'05_Daily_Funnel'!$A:$A,">="&$B5,'05_Daily_Funnel'!$A:$A,"<="&$C5) | I5: =SUMIFS('05_Daily_Funnel'!$H:$H,'05_Daily_Funnel'!$A:$A,">="&$B5,'05_Daily_Funnel'!$A:$A,"<="&$C5) | J5: =SUMIFS('05_Daily_Funnel'!$J:$J,'05_Daily_Funnel'!$A:$A,">="&$B5,'05_Daily_Funnel'!$A:$A,"<="&$C5) | K5: =IFERROR(D5/F5,0) | L5: =IFERROR(D5/I5,0) | M5: =IFERROR(J5/D5,0) | N5: =IFERROR(G5/F5,0) | O5: =IFERROR(H5/G5,0) | P5: =IFERROR(I5/H5,0) | Q5: =IFERROR(SUMPRODUCT(('05_Daily_Funnel'!$A$5:$A$95>=$B5)*('05_Daily_Funnel'!$A$5:$A$95<=$C5)*('05_Daily_Funnel'!$E$5:$E$95)*('05_Daily_Funnel'!$Q$5:$Q$95))/F5,0)

Sheet 13_SLA_Lead_Scoring
A1: 13 | SLA & Lead Scoring Definitions
A2: Definitions for MQL/SQL/deal handoff.
A4: Area | B4: Rule | C4: Target / Value | D4: Owner | E4: Action if missed
A5: Speed to Lead | B5: First human reply after prospect creation | C5: <= 60 minutes | D5: Sales Agent | E5: Manager alert + recovery follow-up
A6: MQL Definition | B6: Need confirmed + valid business + score >= 50 | C6: MQL | D6: Marketing + Sales | E6: Nurture if unqualified
A7: SQL Definition | B7: Budget/tax urgency/demo request + score >= 65 | C7: SQL | D7: Sales | E7: Book demo or send proposal
A8: Deal Definition | B8: Paid subscription or confirmed invoice | C8: Deal Won | D8: Sales + Finance | E8: Record revenue
A9: Lost Definition | B9: Clear rejection/no response after cadence | C9: Deal Lost | D9: Sales | E9: Record lost reason
A10: Follow-up Cadence | B10: Day 0, Day 1, Day 3, Day 7 | C10: 4 touches minimum | D10: Sales Agent | E10: Recycle to nurture
A11: ROAS Formula | B11: Revenue / Amount Spent | C11: >= 2.0 target | D11: Management | E11: Shift budget
A12: CAC Formula | B12: Amount Spent / Deals Won | C12: Lower is better | D12: Management | E12: Pause high CAC creatives
